Workbook
Name solver_opt: 'Part A'!$BV$28
Name solver_lhs1: 'Part A'!$BV$24
Name solver_adj: 'Part A'!$BR$24:$BU$24

Sheet Introduction
B2: 🔍SAPM Assignment - Summer Term 2025🪴
B11: Team | F11: Index
B12: Name | C12: ID Number
F13: Approach Summary | G13: Individual Stock Selection > Our Approach > Selection of Industry > Selection of a stock in a particular industry
B14: Arnav Agarwal | C14: 2022B1A41724P
B15: Atharva Toshniwal | C15: 2022B3A80224P
F16: Part A | G16: > Performance of the selected stocks in one year ( from April 2024 to April 2025) > Equal Weighted Performance > Optimized Portfolio Performance
F19: Part B | G19: > Backtesting of the selected stocks in one month ( May 2025)
F22: Part C | G22: > Performance of the selected instruments in one year ( from April 2024 to April 2025) > Equal Weighted Performance > Optimized Portfolio Performance
F25: Part D | G25: > Backtesting of the selected instruments in one month ( May 2025)
F28: Part E | G28: > Observations > Final Conclusions

Sheet Approach Summary
B3: 🎯 Our Approach 📃
B4: Step 1 | C4: We began by identifying key industries based on their economic importance, market stability, and historical return potential. Preference was given to sectors demonstrating strong growth prospects and consistent performance.
B5: Step 2 | C5: For each selected industry, we shortlisted five leading companies. These were chosen based on market capitalization, brand strength, historical returns, and relevance within the sector.
B6: Step 3 | C6: The evaluation criteria were grouped into five core categories: valuation metrics, profitability metrics, efficiency metrics, leverage/liquidity metrics, and market strength/scale metrics.
B7: Step 4 | C7: Each metric and sub-metric was assigned a specific weight based on its relevance to the industry context. The weights were supported by rationale rooted in financial theory and sector characteristics.
B8: Step 5 | C8: To ensure comparability across different scales and units, all metric values were normalized. For positively contributing metrics (e.g., ROE, Net Profit Margin, Asset Turnover ⬆️), we applied: Normalized Value= (Value−Min) / (Max−Min)
B9: Step 6 | C9: For negatively contributing metrics (e.g., P/E Ratio, Debt-to-Equity, Inventory Days ⬇️), we used: Normalized Value = (Max − Value) / (Max − Min)
B10: Step 7 | C10: Normalized values were then multiplied by their respective metric weights to compute a final weighted score for each stock.
B11: Step 8 | C11: The company with the highest cumulative weighted score in each industry was selected, reflecting optimal performance across valuation, operational, and financial parameters.
B14: Why Tele - Communications? | C14: The telecom industry plays a critical role in enabling digital infrastructure and connectivity in India, making it foundational to both economic activity and national development. With the rapid expansion of 5G, increased data consumption, and digital payments, telecom companies are set to benefit from long-term demand. Additionally, the sector features strong industry leaders with wide subscriber bases, high entry barriers, and consistent cash flows. These attributes make it attractive for stable, long-term portfolio inclusion.
B17: 📡Stocks of Tele-Communications📞
D21: Valuation💰 | O21: Profitability 💸 | X21: Efficiency 🔁 | AC21: Financial Health 🩺 | AJ21: Returns 📈 | AO21: Final Value
B22: Name of the ratio | D22: P/E Ratio | F22: P/B Ratio | H22: EV/EBITDA | J22: PEG Ratio | L22: Market Cap (in Cr) | O22: Net Profit Margin | Q22: ROE | S22: ROA | U22: Gross Margin | X22: Asset Turnover | Z22: Inventory Turnover | AC22: Current Ratio | AE22: Debt-to-Equity | AG22: Interest Coverage | AJ22: Operating Margin | AL22: Dividend Yield
B23: Weight | D23: 0.08 | F23: 0.05 | H23: 0.1 | J23: 0.05 | L23: 0.02 | O23: 0.07 | Q23: 0.1 | S23: 0.05 | U23: 0.03 | X23: 0.07 | Z23: 0.08 | AC23: 0.07 | AE23: 0.1 | AG23: 0.03 | AJ23: 0.05 | AL23: 0.05
B24: Reason | D24: Telecoms are mature and earnings-stable; P/E captures valuation based on profitability and investor sentiment. | F24: Book value is less indicative in telecoms due to high asset depreciation and long-lived infrastructure. | H24: The most accurate metric for telecoms, accounting for debt and depreciation in this high-capex industry. | J24: Telecoms have stable, moderate growth; this ratio adds context to valuation by factoring in expected growth. | L24: While scale offers network advantages, telecom markets are often regulated, so size doesn’t always mean dominance. | O24: Margins matter due to high operating leverage; small margin shifts can significantly impact profits. | Q24: Crucial for capital-heavy firms, shows how well telecoms convert invested capital into profit. | S24: Telecoms have large fixed asset bases; ROA shows how productively these are deployed, but leverage skews it. | U24: Fixed infrastructure costs dominate telecoms, so gross margin varies little and has limited insight. | X24: Telecoms must monetize infrastructure efficiently; asset turnover captures how well they do it. | Z24: Many telecoms sell devices or maintain inventory; turnover reflects working capital and sales flow health. | AC24: Telecoms face high liabilities; current ratio reveals ability to meet obligations. | AE24: Telecoms are often heavily leveraged due to infrastructure investment, managing debt load is critical. | AG24: Important in debt-heavy sectors, but often less volatile in large telecoms with steady cash flows. | AJ24: Reflects efficiency in core services, but overlaps with EBITDA, so slightly lower weight. | AL24: Many telecoms are mature and offer dividends, but capital reinvestment can be more important for growth.
D25: Lower⬇️ | E25: Value Weighted | F25: Lower⬇️ | G25: Value Weighted | H25: Lower⬇️ | I25: Value Weighted | J25: Lower⬇️ | K25: Value Weighted | L25: Higher⬆️ | M25: Value Weighted | O25: Higher⬆️ | P25: Value Weighted | Q25: Higher⬆️ | R25: Value Weighted | S25: Higher⬆️ | T25: Value Weighted | U25: Higher⬆️ | V25: Value Weighted | X25: Higher⬆️ | Y25: Value Weighted | Z25: Higher⬆️ | AA25: Value Weighted | AC25: Higher⬆️ | AD25: Value Weighted | AE25: Lower⬇️ | AF25: Value Weighted | AG25: Higher⬆️ | AH25: Value Weighted | AJ25: Higher⬆️ | AK25: Value Weighted | AL25: Higher⬆️ | AM25: Value Weighted
B26: Bharti Airtel Ltd | D26: 43.9 | E26: 0.47 | F26: 10.2 | G26: 0.48 | H26: 14.4 | I26: 0.54 | J26: 1.43 | K26: 0.66 | L26: 1216200 | M26: 1 | O26: 0.26 | P26: 1 | Q26: 0.28 | R26: 0.3 | S26: 0.06 | T26: 0.11 | U26: 1 | V26: 1 | X26: 0.36 | Y26: 0 | Z26: NA | AA26: 0 | AC26: 0.37 | AD26: 0.09 | AE26: 1.88 | AF26: 0.46 | AG26: 2.43 | AH26: 0 | AJ26: 0.54 | AK26: 0.71 | AL26: 0.0079 | AM26: 0.53 | AO26: 0.41861711
B28: Indus Towers Ltd | D28: 11.2 | E28: 1 | F28: 3.42 | G28: 1 | H28: 6.15 | I28: 1 | J28: 0.42 | K28: 1 | L28: 111085 | M28: 0.08 | O28: 0.23 | P28: 0.85 | Q28: 0.33 | R28: 0.44 | S28: 0.17 | T28: 1 | U28: 0.63 | V28: 0 | X28: 0.51 | Y28: 0.27 | Z28: 3012.84 | AA28: 0 | AC28: 1.32 | AD28: 1 | AE28: 0.65 | AF28: 0.15 | AG28: 9.05 | AH28: 0.05 | AJ28: 0.69 | AK28: 1 | AL28: 0 | AM28: 0 | AO28: 0.5905296
B30: Bharti Hexacom Ltd | D30: 73.1 | E30: 0 | F30: 16.5 | G30: 0 | H30: 24 | I30: 0 | J30: 2.07 | K30: 0.45 | L30: 98005 | M30: 0.07 | O30: 0.21 | P30: 0.73 | Q30: 0.25 | R30: 0.23 | S30: 0.07 | T30: 0.16 | U30: 1 | V30: 1 | X30: 0.45 | Y30: 0.16 | Z30: NA | AA30: 0 | AC30: 0.28 | AD30: 0 | AE30: 1.24 | AF30: 0.3 | AG30: 3.32 | AH30: 0.01 | AJ30: 0.49 | AK30: 0.63 | AL30: 0.0051 | AM30: 0.34 | AO30: 0.22600959
B32: Tata Communications Ltd | D32: 36.1 | E32: 0.6 | F32: 15.8 | G32: 0.05 | H32: 12.7 | I32: 0.63 | J32: 1.05 | K32: 0.79 | L32: 47846 | M32: 0.03 | O32: 0.05 | P32: 0 | Q32: 0.55 | R32: 1 | S32: 0.05 | T32: 0 | U32: 1 | V32: 1 | X32: 0.91 | Y32: 1 | Z32: 3.03 | AA32: 0 | AC32: 0.51 | AD32: 0.22 | AE32: 4.09 | AF32: 1 | AG32: 2.88 | AH32: 0 | AJ32: 0.2 | AK32: 0.08 | AL32: 0.0149 | AM32: 1 | AO32: 0.52355242
B34: Railtel Corporation of India Ltd | D34: 43.6 | E34: 0.48 | F34: 6.87 | G34: 0.74 | H34: 21.8 | I34: 0.12 | J34: 3.4 | K34: 0 | L34: 13746 | M34: 0 | O34: 0.08 | P34: 0.15 | Q34: 0.17 | R34: 0 | S34: 0.07 | T34: 0.14 | U34: 1 | V34: 1 | X34: 0.76 | Y34: 0.73 | Z34: NA | AA34: 0 | AC34: 1.29 | AD34: 0.97 | AE34: 0.02 | AF34: 0 | AG34: 137 | AH34: 1 | AJ34: 0.15 | AK34: 0 | AL34: 0.0067 | AM34: 0.45 | AO34: 0.30607056
B36: Why Defence? | C36: The defence sector in India is gaining prominence due to increasing government focus on indigenization, rising defence budgets, and strategic geopolitical priorities. With large, long-term contracts and government backing, this sector presents a unique blend of stability and long-term growth. Prominent companies benefit from monopolistic or semi-monopolistic market positions and offer significant upside as the sector expands through Make in India initiatives.
B38: 🏰 Stocks of Defence 🪖
D42: Valuation💰 | O42: Profitability 💸 | X42: Efficiency 🔁 | AC42: Financial Health 🩺 | AJ42: Returns 📈 | AO42: Final Value
B43: Name of the ratio | D43: P/E Ratio | F43: P/B Ratio | H43: EV/EBITDA | J43: PEG Ratio | L43: Market Cap | O43: Net Profit Margin | Q43: ROE | S43: ROA | U43: Gross Margin | X43: Asset Turnover | Z43: Inventory Turnover | AC43: Current Ratio | AE43: Debt-to-Equity | AG43: Interest Coverage | AJ43: Operating Margin | AL43: Dividend Yield
B44: Weight | D44: 0.05 | F44: 0.07 | H44: 0.12 | J44: 0.03 | L44: 0.03 | O44: 0.08 | Q44: 0.12 | S44: 0.06 | U44: 0.05 | X44: 0.06 | Z44: 0.05 | AC44: 0.1 | AE44: 0.12 | AG44: 0.05 | AJ44: 0.06 | AL44: 0.04
B45: Reason | D45: Earnings can fluctuate with contracts and defense budgets, so less predictive on its own. | F45: Important for asset-heavy defence manufacturers where tangible assets like plants and IP matter. | H45: Essential for capital-intensive firms; neutralizes accounting and capex differences. | J45: Many defence companies grow steadily but slowly, growth potential is less central than cash flow. | L45: Larger firms win bigger contracts and offer stability, but scale isn’t always correlated with performance. | O45: Important for contract profitability, especially in cost-plus vs. fixed-price models. | Q45: Vital in defence where firms must efficiently use capital while facing long sales cycles. | S45: Useful in assessing how well plants, equipment, and R&D investments are leveraged. | U45: Indicates pricing power and manufacturing cost control, especially in complex production. | X45: Key for companies with high R&D or inventory levels; shows contract-to-revenue speed. | Z45: Defence has long build cycles and specialized parts, so turnover offers limited insight but still relevant. | AC45: Crucial in managing contract milestones, delayed payments, and high working capital needs. | AE45: High weight due to the need for financial stability in a sector with unpredictable payment cycles. | AG45: Important for balance sheet health, though most defense firms are cash-positive. | AJ45: Contract execution efficiency is critical; reflects profitability beyond COGS. | AL45: Defence stocks often attract long-term investors; dividends add income but are secondary to stability.
D46: Lower⬇️ | E46: Value Weighted | F46: Lower⬇️ | G46: Value Weighted | H46: Lower⬇️ | I46: Value Weighted | J46: Lower⬇️ | K46: Value Weighted | L46: Higher⬆️ | M46: Value Weighted | O46: Higher⬆️ | P46: Value Weighted | Q46: Higher⬆️ | R46: Value Weighted | S46: Higher⬆️ | T46: Value Weighted | U46: Higher⬆️ | V46: Value Weighted | X46: Higher⬆️ | Y46: Value Weighted | Z46: Higher⬆️ | AA46: Value Weighted | AC46: Higher⬆️ | AD46: Value Weighted | AE46: Lower⬇️ | AF46: Value Weighted | AG46: Higher⬆️ | AH46: Value Weighted | AJ46: Higher⬆️ | AK46: Value Weighted | AL46: Higher⬆️ | AM46: Value Weighted
B47: Hindustan Aeronautics Ltd | D47: 39.2 | E47: 1 | F47: 9.36 | G47: 1 | H47: 23.7 | I47: 1 | J47: 1.6 | K47: 0.99903348 | L47: 327559 | M47: 1 | O47: 0.29 | P47: 1 | Q47: 0.261 | R47: 0.6 | S47: 0.0893 | T47: 1 | U47: 0.637 | V47: 0.94 | X47: 0.33 | Y47: 0.16 | Z47: 0.65 | AA47: 0 | AC47: 2.04 | AD47: 0.72 | AE47: 0 | AF47: 0 | AG47: 1252 | AH47: 1 | AJ47: 0.31 | AK47: 1 | AL47: 0.0071 | AM47: 1 | AO47: 0.78995702
B49: Mazagon Dock Shipbuilders Ltd | D49: 53 | E49: 0.84 | F49: 16.1 | G49: 0.15 | H49: 35.2 | I49: 0.79 | J49: 1.38 | K49: 1 | L49: 128033 | M49: 0.32 | O49: 0.102 | P49: 0 | Q49: 0.34 | R49: 1 | S49: 0.083 | T49: 0.84 | U49: 0.657 | V49: 1 | X49: 0.39 | Y49: 0.47 | Z49: 0.89 | AA49: 0.3 | AC49: 1.25 | AD49: 0.07 | AE49: 0 | AF49: 0 | AG49: 697 | AH49: 0.55 | AJ49: 0.18 | AK49: 0.43 | AL49: 0.0046 | AM49: 0.42 | AO49: 0.52723966
B51: Bharat Dynamics Ltd | D51: 126 | E51: 0 | F51: 17.3 | G51: 0 | H51: 79.1 | I51: 0 | J51: 229 | K51: 0 | L51: 69284 | M51: 0.12 | O51: 0.154 | P51: 0.28 | Q51: 0.144 | R51: 0 | S51: 0.0496 | T51: 0 | U51: 0.408 | V51: 0.25 | X51: 0.3 | Y51: 0 | Z51: 0.71 | AA51: 0.07 | AC51: 2.38 | AD51: 1 | AE51: 0 | AF51: 0 | AG51: 227 | AH51: 0.16 | AJ51: 0.141 | AK51: 0.26 | AL51: 0.0028 | AM51: 0 | AO51: 0.16507603
B53: Cochin Shipyard Ltd | D53: 63.8 | E53: 0.72 | F53: 9.59 | G53: 0.97 | H53: 40.9 | I53: 0.69 | J53: 11 | K53: 0.95773658 | L53: 53779 | M53: 0.07 | O53: 0.172 | P53: 0.37 | Q53: 0.158 | R53: 0.07 | S53: 0.0676 | T53: 0.45 | U53: 0.606 | V53: 0.85 | X53: 0.36 | Y53: 0.32 | Z53: 1.46 | AA53: 1 | AC53: 1.34 | AD53: 0.14 | AE53: 0.09 | AF53: 1 | AG53: 32.1 | AH53: 0 | AJ53: 0.193 | AK53: 0.48 | AL53: 0.0048 | AM53: 0.47 | AO53: 0.57576351
B55: Garden Reach Shipbuilders & Engineers Ltd | D55: 65.9 | E55: 0.69 | F55: 16.7 | G55: 0.08 | H55: 41 | I55: 0.69 | J55: 2.54 | K55: 0.99490379 | L55: 34739 | M55: 0 | O55: 0.149 | P55: 0.25 | Q55: 0.281 | R55: 0.7 | S55: 0.0512 | T55: 0.04 | U55: 0.326 | V55: 0 | X55: 0.49 | Y55: 1 | Z55: 0.94 | AA55: 0.36 | AC55: 1.17 | AD55: 0 | AE55: 0 | AF55: 0 | AG55: 69.2 | AH55: 0.03 | AJ55: 0.083 | AK55: 0 | AL55: 0.0031 | AM55: 0.07 | AO55: 0.34079191
B57: Why Banks? | C57: The banking sector is a core component of the economy, essential for financial intermediation, credit distribution, and liquidity management. It reflects the broader economic cycle and plays a critical role in supporting growth through retail and corporate lending. We chose this sector due to its strong linkage to GDP expansion, rising credit demand, and rapid digitalization of financial services. Leading banks typically exhibit healthy balance sheets, stable net interest margins, and improving asset quality. The sector’s scale, regulatory support, and consistent earnings potential make it a strategic addition to a well-diversified portfolio.
B59: 💳Stocks of Banks🏦
D63: Valuation💰 | M63: Profitability 💸 | X63: Financial Health 🩺 | AM63: Returns 📈 | AP63: Final Value
B64: Name of the ratio | D64: P/E Ratio | F64: P/B Ratio | H64: PEG Ratio | J64: Market Cap | M64: ROE | O64: ROA | Q64: Net Interest Margin (NIM) | S64: Cost-to-Income (%) | U64: Provision for Credit Losses (PCL) (Cr) | X64: Debt-to-Equity | Z64: CASA Ratio | AB64: Loan to Asset Ratio | AD64: Loan-to-Deposit Ratios | AF64: Gross NPA Ratio | AH64: Capital Adequacy Ratio (CAR) | AJ64: Liquidity Coverage Ratio (LCR) | AM64: Dividend Yield
B65: Weight | D65: 0.06 | F65: 0.08 | H65: 0.05 | J65: 0.05 | M65: 0.1 | O65: 0.07 | Q65: 0.08 | S65: 0.04 | U65: 0.07 | X65: 0.05 | Z65: 0.05 | AB65: 0.05 | AD65: 0.05 | AF65: 0.08 | AH65: 0.05 | AJ65: 0.05 | AM65: 0.04
B66: Reason | D66: Helpful for comparing profitability across banks, but earnings can be volatile due to provisioning swings. | F66: Most critical valuation metric for banks, assets are financial, and book value closely reflects economic reality. | H66: Adds context to P/E, though banks tend to grow steadily, not exponentially. | J66: Size gives stability, brand trust, and deposit base, but fundamentals remain more important. | M66: Key indicator of how well a bank uses its capital base, high ROE signals efficient lending. | O66: Important for understanding how much profit is earned from the bank's asset base (loans, securities). | Q66: Reflects spread between lending and borrowing rates, central to banking operations. | S66: Shows how well a bank controls operating costs, lower is better, but some costs are growth investments. | U66: Indicates how much of earnings are consumed by bad loans, rising PCL is a red flag. | X66: Less meaningful in banks, but still shows aggressive capital structuring. | Z66: Higher CASA = lower cost of funds, giving banks pricing power and higher NIM. | AB66: Indicates how much of the bank’s assets are loans (earning assets), helps assess risk and returns. | AD66: Higher LDR is better because it reflects more efficient use of deposits to generate income through lending, as long as it stays within safe regulatory limits. | AF66: Directly reflects health of loan book, higher NPA = higher risk of write-offs and weaker financials. | AH66: Regulatory requirement; higher CAR = more capacity to absorb shocks and grow lending. | AJ66: Ensures the bank can survive a short-term funding crunch, especially relevant post-2008. | AM66: Useful for income, seeking investors, but less important for evaluating bank health/growth.
D67: Lower⬇️ | E67: Value Weighted | F67: Lower⬇️ | G67: Value Weighted | H67: Lower⬇️ | I67: Value Weighted | J67: Higher⬆️ | K67: Value Weighted | M67: Higher⬆️ | N67: Value Weighted | O67: Higher⬆️ | P67: Value Weighted | Q67: Higher⬆️ | R67: Value Weighted | S67: Lower⬇️ | T67: Value Weighted | U67: Lower⬇️ | V67: Value Weighted | X67: Lower⬇️ | Y67: Value Weighted | Z67: Higher⬆️ | AA67: Value Weighted | AB67: Higher⬆️ | AC67: Value Weighted | AD67: Higher⬆️ | AE67: Value Weighted | AF67: Lower⬇️ | AG67: Value Weighted | AH67: Higher⬆️ | AI67: Value Weighted | AJ67: Higher⬆️ | AK67: Value Weighted | AM67: Higher⬆️ | AN67: Value Weighted
B68: HDFC Bank | D68: 21.8 | E68: 0.23 | F68: 2.98 | G68: 0.14 | H68: 1.04 | I68: 0 | J68: 1545008 | K68: 1 | M68: 14.5 | N68: 0 | O68: 0.0174 | P68: 0.63 | Q68: 3.13 | R68: 0.47 | S68: 0.2916 | T68: 1 | U68: 14170 | V68: 0.36 | X68: 6.46 | Y68: 0.92 | Z68: 0.3818 | AA68: 0.07 | AB68: 0.144 | AC68: 1 | AD68: 0.965 | AE68: 1 | AF68: 0.0133 | AG68: 0.95 | AH68: 0.196 | AI68: 1 | AJ68: 1.1904 | AK68: 0 | AM68: 0.0109 | AN68: 0.3 | AP68: =E68*D65+G68*F65+I68*H65+K68*J65+N68*M65+P68*O65+R68*Q65+T68*S65+V68*U65+Y68*X65+AA68*Z65+AC68*AB65+AE68*AD65+AG68*AF65+AI68*AH65+AK68*AJ65+AN68*AM65 -> 0.5094
B70: ICICI Bank | D70: 20.4 | E70: 0.29 | F70: 3.34 | G70: 0 | H70: 0.51 | I70: 0.55 | J70: 1043359 | K70: 0.65 | M70: 18 | N70: 1 | O70: 0.0218 | P70: 1 | Q70: 3.83 | R70: 1 | S70: 0.3256 | T70: 0.85 | U70: 4910 | V70: 1 | X70: 5.97 | Y70: 1 | Z70: 0.4217 | AA70: 0.84 | AB70: 0.083 | AC70: 0.14 | AD70: 0.7733 | AE70: 0 | AF70: 0.0167 | AG70: 0.6 | AH70: 0.1655 | AI70: 0.52 | AJ70: 1.23 | AK70: 0.21 | AM70: 0.68 % | AN70: 0.18 | AP70: =E70*D65+G70*F65+I70*H65+K70*J65+N70*M65+P70*O65+R70*Q65+T70*S65+V70*U65+Y70*X65+AA70*Z65+AC70*AB65+AE70*AD65+AG70*AF65+AI70*AH65+AK70*AJ65+AN70*AM65 -> 0.6221
B72: State Bank of India (SBI) | D72: 26.4 | E72: 0 | F72: 1.48 | G72: 0.75 | H72: 0.26 | I72: 0.8 | J72: 718789 | K72: 0.42 | M72: 17.2 | N72: 0.77 | O72: 0.0115 | P72: 0.13 | Q72: 2.5 | R72: 0 | S72: 0.5163 | T72: 0 | U72: 19460 | V72: 0 | X72: 12.4 | Y72: 0 | Z72: 0.3871 | AA72: 0.17 | AB72: 0.084 | AC72: 0.15 | AD72: 0.9134 | AE72: 0.73 | AF72: 0.0182 | AG72: 0.45 | AH72: 0.1719 | AI72: 0.62 | AJ72: 1.3226 | AK72: 0.7 | AM72: 0.0197 | AN72: 0.56 | AP72: =E72*D65+G72*F65+I72*H65+K72*J65+N72*M65+P72*O65+R72*Q65+T72*S65+V72*U65+Y72*X65+AA72*Z65+AC72*AB65+AE72*AD65+AG72*AF65+AI72*AH65+AK72*AJ65+AN72*AM65 -> 0.384
B74: Axis Bank | D74: 13.5 | E74: 0.63 | F74: 2.04 | G74: 0.52 | H74: 0.19 | I74: 0.88 | J74: 379913 | K74: 0.18 | M74: 16.4 | N74: 0.54 | O74: 0.0178 | P74: 0.66 | Q74: 3.37 | R74: 0.65 | S74: 0.3598 | T74: 0.7 | U74: 8170 | V74: 0.78 | X74: 7.48 | Y74: 0.77 | Z74: 0.4298 | AA74: 1 | AB74: 0.133 | AC74: 0.85 | AD74: 0.887 | AE74: 0.59 | AF74: 0.0128 | AG74: 1 | AH74: 0.133 | AI74: 0 | AJ74: 1.2 | AK74: 0.05 | AM74: 0.0008 | AN74: 0 | AP74: =E74*D65+G74*F65+I74*H65+K74*J65+N74*M65+P74*O65+R74*Q65+T74*S65+V74*U65+Y74*X65+AA74*Z65+AC74*AB65+AE74*AD65+AG74*AF65+AI74*AH65+AK74*AJ65+AN74*AM65 -> 0.6102
B76: Bank of Baroda | D76: 6.04 | E76: 1 | F76: 0.85 | G76: 1 | H76: 0.07 | I76: 1 | J76: 124800 | K76: 0 | M76: 15.5 | N76: 0.29 | O76: 0.01 | P76: 0 | Q76: 2.56 | R76: 0.05 | S76: 0.4794 | T76: 0.16 | U76: 10280 | V76: 0.63 | X76: 11.1 | Y76: 0.2 | Z76: 0.3781 | AA76: 0 | AB76: 0.073 | AC76: 0 | AD76: 0.82 | AE76: 0.24 | AF76: 0.0226 | AG76: 0 | AH76: 0.1596 | AI76: 0.42 | AJ76: 1.38 | AK76: 1 | AM76: 0.0346 | AN76: 1 | AP76: =E76*D65+G76*F65+I76*H65+K76*J65+N76*M65+P76*O65+R76*Q65+T76*S65+V76*U65+Y76*X65+AA76*Z65+AC76*AB65+AE76*AD65+AG76*AF65+AI76*AH65+AK76*AJ65+AN76*AM65 -> 0.4065
B78: Why IT? | C78: India's IT sector is a global leader in software services, digital transformation, and outsourcing. It contributes significantly to GDP and export earnings. The sector has shown resilience during economic downturns and continues to grow through cloud services, AI, and enterprise digitalization. Market leaders in this sector deliver high return on equity, strong margins, and dividend payouts, making it an essential inclusion for both growth and stability.
B80: 📱Stocks of IT🖥️
D84: Valuation💰 | O84: Profitability 💸 | X84: Efficiency 🔁 | AC84: Financial Health 🩺 | AJ84: Returns 📈 | AO84: Final Value
B85: Name of the ratio | D85: P/E Ratio | F85: P/B Ratio | H85: EV/EBITDA | J85: PEG Ratio | L85: Market Cap (in Cr) | O85: Net Profit Margin(Latest Quarter) | Q85: ROE | S85: ROA | U85: Gross Margin(Latest Quarter GPM) | X85: Asset Turnover Ratio | Z85: Inventory Turnover Ratio | AC85: Current Ratio | AE85: Debt-to-Equity | AG85: Interest Coverage | AJ85: Operating Margin(Latest Quarter) | AL85: Dividend Yield
B86: Weight | D86: 0.14 | F86: 0.063 | H86: 0.072 | J86: 0.045 | L86: 0.05 | O86: 0.09 | Q86: 0.042 | S86: 0.033 | U86: 0.045 | X86: 0.01 | Z86: 0.045 | AC86: 0.045 | AE86: 0.12 | AG86: 0.09 | AJ86: 0.045 | AL86: 0.09
B87: Reason | D87: A lower P/E indicates potential undervaluation. In the margin-rich, stable IT sector, a high weight rewards firms delivering strong earnings at reasonable prices. | F87: IT firms are asset-light; book value may understate true worth, but it still helps identify overpriced stocks. | H87: Helps normalize for varying capital structures across IT services and product companies. | J87: Many IT firms have moderate to high growth; PEG provides a more complete valuation picture than P/E alone. | L87: Larger IT firms often enjoy better client retention and pricing leverage. Scale also signals operational maturity. | O87: High profit margins are typical in IT due to low variable costs; strong margins show efficiency and pricing power. | Q87: Useful, though less emphasized in asset-light models where equity bases are low. | S87: Lower relevance since intangible-heavy IT firms don't rely on physical assets. | U87: Important to understand cost efficiency, especially for product-based or SaaS firms. | X87: Very low relevance in IT, since companies often have minimal physical assets and low capex. | Z87: Relevant mainly for hardware, product-based, or integrated IT firms (e.g., OEMs). Less so for pure services. | AC87: Moderate importance; most IT companies have healthy cash balances and low short-term liabilities. | AE87: IT companies are expected to maintain low debt. High leverage in this sector is a red flag. | AG87: Strong coverage ensures debt doesn’t strain operations; highly relevant when evaluating financially disciplined IT firms. | AJ87: IT companies should maintain high operating margins to show scalability of delivery. | AL87: Many mature IT companies (e.g., Infosys, TCS) offer consistent dividends; important for income investors.
D88: Lower⬇️ | E88: Value Weighted | F88: Lower⬇️ | G88: Value Weighted | H88: Lower⬇️ | I88: Value Weighted | J88: Lower⬇️ | K88: Value Weighted | L88: Higher⬆️ | M88: Value Weighted | O88: Higher⬆️ | P88: Value Weighted | Q88: Higher⬆️ | R88: Value Weighted | S88: Higher⬆️ | T88: Value Weighted | U88: Higher⬆️ | V88: Value Weighted | X88: Higher⬆️ | Y88: Value Weighted | Z88: Higher⬆️ | AA88: Value Weighted | AC88: Higher⬆️ | AD88: Value Weighted | AE88: Lower⬇️ | AF88: Value Weighted | AG88: Higher⬆️ | AH88: Value Weighted | AJ88: Higher⬆️ | AK88: Value Weighted | AL88: Higher⬆️ | AM88: Value Weighted
B89: Persistent Systems Ltd | D89: 69.2 | E89: 0 | F89: 14.7 | G89: 0 | H89: 43.6 | I89: 0 | J89: 2.11 | K89: 0.5576 | L89: 94004 Cr. | M89: 0 | O89: 0.122 | P89: 0.08 | Q89: 0.241 | R89: 0.0691 | S89: 0.168 | T89: 0.0497 | U89: 1 | V89: 1 | X89: 1.48 | Y89: 0.6296 | Z89: NA | AA89: 0 | AC89: 2.2 | AD89: 0.8679 | AE89: 0.05 | AF89: 1 | AG89: 27.3 | AH89: 0.0593 | AJ89: 0.18 | AK89: 0.17 | AL89: 0.0058 | AM89: 0 | AO89: =E89*D86+G89*F86+I89*H86+K89*J86+M89*L86+P89*O86+R89*Q86+T89*S86+V89*U86+Y89*X86+AA89*Z86+AD89*AC86+AF89*AE86+AH89*AG86+AK89*AJ86+AM89*AL86 -> 0.2601728
B91: Tata Consultancy Services (TCS) | D91: 25.7 | E91: 0.9886 | F91: 13.1 | G91: 0.2003 | H91: 17.4 | I91: 0.9258 | J91: 3.03 | K91: 0 | L91: 1245020 Cr. | M91: 1 | O91: 0.191 | P91: 1 | Q91: 0.524 | R91: 1 | S91: 0.321 | T91: 1 | U91: 1 | V91: 1 | X91: 1.68 | Y91: 1 | Z91: 2 | AA91: 0.0573 | AC91: 1.74 | AD91: 0 | AE91: 0.1 | AF91: 0 | AG91: 83 | AH91: 0.8858 | AJ91: 0.263 | AK91: 1 | AL91: 0.0174 | AM91: 0.4549 | AO91: =E91*D86+G91*F86+I91*H86+K91*J86+M91*L86+P91*O86+R91*Q86+T91*S86+V91*U86+Y91*X86+AA91*Z86+AD91*AC86+AF91*AE86+AH91*AG86+AK91*AJ86+AM91*AL86 -> 0.655922
B93: Infosys | D93: 25.2 | E93: 1 | F93: 6.97 | G93: 0.9675 | H93: 15.3 | I93: 1 | J93: 2.52 | K93: 0.3091 | L93: 668007 Cr. | M93: 0.4978 | O93: 0.172 | P93: 0.7467 | Q93: 0.288 | R93: 0.2237 | S93: 0.187 | T93: 0.1677 | U93: 1 | V93: 1 | X93: 1.15 | Y93: 0.0185 | Z93: NA | AA93: 0 | AC93: 1.97 | AD93: 0.434 | AE93: 0.09 | AF93: 0.2 | AG93: 90.7 | AH93: 1 | AJ93: 0.241 | AK93: 0.78 | AL93: 0.0267 | AM93: 0.8196 | AO93: =E93*D86+G93*F86+I93*H86+K93*J86+M93*L86+P93*O86+R93*Q86+T93*S86+V93*U86+Y93*X86+AA93*Z86+AD93*AC86+AF93*AE86+AH93*AG86+AK93*AJ86+AM93*AL86 -> 0.6814635
B95: HCL Technologies | D95: 26.9 | E95: 0.9614 | F95: 6.71 | G95: 1 | H95: 16.2 | I95: 0.9682 | J95: 2.77 | K95: 0.1576 | L95: 467646 Cr. | M95: 0.3246 | O95: 0.142 | P95: 0.3467 | Q95: 0.252 | R95: 0.1053 | S95: 0.17 | T95: 0.0621 | U95: 0.984 | V95: 0 | X95: 1.14 | Y95: 0 | Z95: 12.8 | AA95: 0.3668 | AC95: 2.22 | AD95: 0.9057 | AE95: 0.09 | AF95: 0.2 | AG95: 37.1 | AH95: 0.2047 | AJ95: 0.214 | AK95: 0.51 | AL95: 0.0313 | AM95: 1 | AO95: =E95*D86+G95*F86+I95*H86+K95*J86+M95*L86+P95*O86+R95*Q86+T95*S86+V95*U86+Y95*X86+AA95*Z86+AD95*AC86+AF95*AE86+AH95*AG86+AK95*AJ86+AM95*AL86 -> 0.5409388
B97: LTIMindtree Ltd | D97: 34.1 | E97: 0.7977 | F97: 6.91 | G97: 0.975 | H97: 20.8 | I97: 0.8057 | J97: 1.38 | K97: 1 | L97: 156858 Cr. | M97: 0.0546 | O97: 0.116 | P97: 0 | Q97: 0.215 | R97: 0 | S97: 0.158 | T97: 0 | U97: 1 | V97: 1 | X97: 1.31 | Y97: 0.3148 | Z97: 34.9 | AA97: 1 | AC97: 2.27 | AD97: 1 | AE97: 0.1 | AF97: 0 | AG97: 23.3 | AH97: 0 | AJ97: 0.163 | AK97: 0 | AL97: 0.0123 | AM97: 0.2549 | AO97: =E97*D86+G97*F86+I97*H86+K97*J86+M97*L86+P97*O86+R97*Q86+T97*S86+V97*U86+Y97*X86+AA97*Z86+AD97*AC86+AF97*AE86+AH97*AG86+AK97*AJ86+AM97*AL86 -> 0.4399324
B99: Why FMCG? | C99: The FMCG sector is known for its defensive nature and consistent demand, even in times of economic slowdown. It includes essential goods like food, hygiene, and personal care products. This ensures stable revenues and low volatility. Top FMCG companies benefit from powerful brand equity, strong distribution networks, and steady profitability. These characteristics make the sector ideal for balancing risk within a diversified portfolio.
B100: Why we discarded it?
B102: 🍷Stocks of FMCG🍫
D106: Valuation💰 | O106: Profitability 💸 | X106: Efficiency 🔁 | AC106: Financial Health 🩺 | AJ106: Returns 📈 | AO106: Final Value
B107: Name of the ratio | D107: P/E Ratio | F107: P/B Ratio | H107: EV/EBITDA | J107: PEG Ratio | L107: Market Cap (in Cr) | O107: Net Profit Margin(Latest Quarter) | Q107: ROE | S107: ROA | U107: Gross Margin(Latest Quarter GPM) | X107: Asset Turnover Ratio | Z107: Inventory Turnover Ratio | AC107: Current Ratio | AE107: Debt-to-Equity | AG107: Interest Coverage | AJ107: Operating Margin(Latest Quarter) | AL107: Dividend Yield
B108: Weight | D108: 0.09 | F108: 0.063 | H108: 0.072 | J108: 0.045 | L108: 0.1 | O108: 0.09 | Q108: 0.072 | S108: 0.063 | U108: 0.045 | X108: 0.045 | Z108: 0.045 | AC108: 0.045 | AE108: 0.09 | AG108: 0.045 | AJ108: 0.045 | AL108: 0.045
B109: Reason | D109: FMCG stocks are often richly valued due to consistent profits; P/E helps assess if they're overpriced. | F109: Less important in FMCG where intangible assets (brands) dominate, but still helpful in comparing capital efficiency. | H109: Useful for comparing FMCG firms with different depreciation methods and capital structures. | J109: Growth is often modest but predictable; PEG adds perspective beyond P/E. | L109: Larger FMCG firms have stronger distribution networks and pricing power, size adds resilience. | O109: High margins show brand strength, pricing power, and cost control in a competitive space. | Q109: High ROE is expected in FMCG due to asset-light, brand-rich models; vital for investor appeal. | S109: Important in FMCG to measure how well a company turns inventory and operations into profit. | U109: Reflects pricing power and cost of goods sold, critical for assessing raw material impact. | X109: High turnover is a hallmark of FMCG; reflects operational efficiency and demand cycle speed. | Z109: FMCG relies on fast-moving goods; this directly ties to liquidity and demand accuracy. | AC109: Important but typically healthy in FMCG due to strong cash flows and limited receivables. | AE109: FMCG companies are typically low-debt; high D/E is a red flag in an otherwise stable sector. | AG109: Less critical but supports D/E insights; confirms stability of earnings. | AJ109: Indicates how efficiently the business turns sales into profit, key in low-margin products. | AL109: Many FMCG stocks are favorites among income investors; consistent dividends add attractiveness.
D110: Lower⬇️ | E110: Value Weighted | F110: Lower⬇️ | G110: Value Weighted | H110: Lower⬇️ | I110: Value Weighted | J110: Lower⬇️ | K110: Value Weighted | L110: Higher⬆️ | M110: Value Weighted | O110: Higher⬆️ | P110: Value Weighted | Q110: Higher⬆️ | R110: Value Weighted | S110: Higher⬆️ | T110: Value Weighted | U110: Higher⬆️ | V110: Value Weighted | X110: Higher⬆️ | Y110: Value Weighted | Z110: Higher⬆️ | AA110: Value Weighted | AC110: Higher⬆️ | AD110: Value Weighted | AE110: Lower⬇️ | AF110: Value Weighted | AG110: Higher⬆️ | AH110: Value Weighted | AJ110: Higher⬆️ | AK110: Value Weighted | AL110: Higher⬆️ | AM110: Value Weighted
B111: Hindustan Unilever (HUL) | D111: 52 | E111: 0.49 | F111: 11 | G111: 0.93 | H111: 33.8 | I111: 0.5 | J111: 6.03 | K111: 0.3 | L111: 542027 | M111: =(L111 - MIN($L$111:$L$119)) / (MAX($L$111:$L$119) - MIN($L$111:$L$119)) -> 1 | O111: 16.4 % | P111: 0.26 | Q111: 20.7 % | R111: 0 | S111: 13.2 % | T111: 0 | U111: 51.4 % | V111: 0.6 | X111: 0.8 | Y111: 0 | Z111: 6.55 | AA111: 0.67 | AC111: 1.11 | AD111: 0.14 | AE111: 0.03 | AF111: 0.9 | AG111: 36.7 | AH111: 0.05 | AJ111: 23.1 % | AK111: 0.3 | AL111: 1.86 % | AM111: 0.51 | AO111: =E111*D108+G111*F108+I111*H108+K111*J108+M111*L108+P111*O108+R111*Q108+T111*S108+V111*U108+Y111*Y108+AA111*AA108+AD111*AD108+AF111*AF108+AH111*AH108+AK111*AK108+AM111*AM108 -> 0.30259
B113: Nestlé India Ltd | D113: 76.6 | E113: 0 | F113: 57.6 | G113: 0 | H113: 49.3 | I113: 0 | J113: 8.08 | K113: 0 | L113: 237057 | M113: =(L113 - MIN($L$111:$L$119)) / (MAX($L$111:$L$119) - MIN($L$111:$L$119)) -> 0.24222772 | O113: 0.161 | P113: 0.23 | Q113: 0.83 | R113: 1 | S113: 0.271 | T113: 1 | U113: 0.562 | V113: 0.86 | X113: 1.77 | Y113: 0.81 | Z113: 3.26 | AA113: 0.17 | AC113: 0.8 | AD113: 0 | AE113: 0.28 | AF113: 0.03 | AG113: 31.6 | AH113: 0.04 | AJ113: 0.252 | AK113: 0.43 | AL113: 0.011 | AM113: 0.27 | AO113: =E113*D108+G113*F108+I113*H108+K113*J108+M113*L108+P113*O108+R113*Q108+T113*S108+V113*U108+Y113*Y108+AA113*AA108+AD113*AD108+AF113*AF108+AH113*AH108+AK113*AK108+AM113*AM108 -> 0.21862277
B115: ITC Ltd | D115: 26.4 | E115: 1 | F115: 7.48 | G115: 1 | H115: 18.2 | I115: 1 | J115: 5.11 | K115: 0.44 | L115: 523904 | M115: =(L115 - MIN($L$111:$L$119)) / (MAX($L$111:$L$119) - MIN($L$111:$L$119)) -> 0.95496899 | O115: 0.275 | P115: 1 | Q115: 0.275 | R115: 0.11 | S115: 0.223 | T115: 0.66 | U115: 0.588 | V115: 1 | X115: 0.84 | Y115: 0.03 | Z115: 2.15 | AA115: 0 | AC115: 3.06 | AD115: 1 | AE115: 0 | AF115: 1 | AG115: 599 | AH115: 1 | AJ115: 0.347 | AK115: 1 | AL115: 0.0343 | AM115: 1 | AO115: =E115*D108+G115*F108+I115*H108+K115*J108+M115*L108+P115*O108+R115*Q108+T115*S108+V115*U108+Y115*Y108+AA115*AA108+AD115*AD108+AF115*AF108+AH115*AH108+AK115*AK108+AM115*AM108 -> 0.5247969
B117: Britannia Industries | D117: 63.6 | E117: 0.26 | F117: 32 | G117: 0.51 | H117: 41.3 | I117: 0.26 | J117: 6.82 | K117: 0.19 | L117: 139571 | M117: =(L117 - MIN($L$111:$L$119)) / (MAX($L$111:$L$119) - MIN($L$111:$L$119)) -> 0 | O117: 0.126 | P117: 0 | Q117: 0.529 | R117: 0.52 | S117: 0.245 | T117: 0.81 | U117: 0.401 | V117: 0 | X117: 2 | Y117: 1 | Z117: 8.77 | AA117: 1 | AC117: 1.08 | AD117: 0.12 | AE117: 0.29 | AF117: 0 | AG117: 22.3 | AH117: 0.02 | AJ117: 0.181 | AK117: 0 | AL117: 0.0127 | AM117: 0.33 | AO117: =E117*D108+G117*F108+I117*H108+K117*J108+M117*L108+P117*O108+R117*Q108+T117*S108+V117*U108+Y117*Y108+AA117*AA108+AD117*AD108+AF117*AF108+AH117*AH108+AK117*AK108+AM117*AM108 -> 0.17127
B119: Varun Beverages (PepsiCo bottler) | D119: 56.1 | E119: 0.41 | F119: 9.4 | G119: 0.96 | H119: 30.5 | I119: 0.6 | J119: 1.35 | K119: 1 | L119: 156109 | M119: =(L119 - MIN($L$111:$L$119)) / (MAX($L$111:$L$119) - MIN($L$111:$L$119)) -> 0.041092691 | O119: 0.131 | P119: 0.03 | Q119: 0.225 | R119: 0.04 | S119: 0.14 | T119: 0.06 | U119: 0.546 | V119: 0.78 | X119: 1.04 | Y119: 0.2 | Z119: 3.86 | AA119: 0.26 | AC119: 1.74 | AD119: 0.42 | AE119: 0.17 | AF119: 0.41 | AG119: 10.3 | AH119: 0 | AJ119: 0.227 | AK119: 0.28 | AL119: 0.0022 | AM119: 0 | AO119: =E119*D108+G119*F108+I119*H108+K119*J108+M119*L108+P119*O108+R119*Q108+T119*S108+V119*U108+Y119*Y108+AA119*AA108+AD119*AD108+AF119*AF108+AH119*AH108+AK119*AK108+AM119*AM108 -> 0.23414927

Sheet Part A
B2: XAU/INR – Gold Price per Gram (INR) | N2: ICICI Bank Ltd XNSE: ICICIBANK | Z2: Indus Towers Ltd (INDUSTOWER.NS) | AL2: Hindustan Aeronautics Limited (HAL.NS) | AX2: ITC Limited (ITC.NS)
BK5: COVARIANCE MATRIX | BL5: XAU/INR – Gold Price per Gram (INR) | BM5: ICICI Bank Ltd | BN5: Indus Towers Ltd | BO5: Hindustan Aeronautics Limited | BQ5: CORRELATION MATRIX | BR5: XAU/INR – Gold Price per Gram (INR) | BS5: ICICI Bank Ltd | BT5: Indus Towers Ltd | BU5: Hindustan Aeronautics Limited
B6: Date | C6: Open | D6: High | E6: Low | F6: Close | G6: Volume | H6: Daily Returns | I6: Standard Deviation | J6: Average Return | K6: Annual Return | N6: =IFERROR(__xludf.DUMMYFUNCTION("GOOGLEFINANCE(""NSE:ICICIBANK"", ""all"", DATE(2024,4,1), DATE(2025,4,30))"),"Date") -> Date | O6: =IFERROR(__xludf.DUMMYFUNCTION("""COMPUTED_VALUE"""),"Open") -> Open | P6: =IFERROR(__xludf.DUMMYFUNCTION("""COMPUTED_VALUE"""),"High") -> High | Q6: =IFERROR(__xludf.DUMMYFUNCTION("""COMPUTED_VALUE"""),"Low") -> Low | R6: =IFERROR(__xludf.DUMMYFUNCTION("""COMPUTED_VALUE"""),"Close") -> Close | S6: =IFERROR(__xludf.DUMMYFUNCTION("""COMPUTED_VALUE"""),"Volume") -> Volume | T6: Daily Returns | U6: Standard Deviation | V6: Average Return | W6: Annual Return | Z6: =IFERROR(__xludf.DUMMYFUNCTION("GOOGLEFINANCE(""NSE:INDUSTOWER"", ""all"", DATE(2024,4,1), DATE(2025,4,30)) "),"Date") -> Date | AA6: =IFERROR(__xludf.DUMMYFUNCTION("""COMPUTED_VALUE"""),"Open") -> Open | AB6: =IFERROR(__xludf.DUMMYFUNCTION("""COMPUTED_VALUE"""),"High") -> High | AC6: =IFERROR(__xludf.DUMMYFUNCTION("""COMPUTED_VALUE"""),"Low") -> Low | AD6: =IFERROR(__xludf.DUMMYFUNCTION("""COMPUTED_VALUE"""),"Close") -> Close | AE6: =IFERROR(__xludf.DUMMYFUNCTION("""COMPUTED_VALUE"""),"Volume") -> Volume | AF6: Daily Returns | AG6: Standard Deviation | AH6: Average Return | AI6: Annual Return | AL6: =IFERROR(__xludf.DUMMYFUNCTION("GOOGLEFINANCE(""NSE:HAL"", ""all"", DATE(2024,4,1), DATE(2025,4,30))"),"Date") -> Date | AM6: =IFERROR(__xludf.DUMMYFUNCTION("""COMPUTED_VALUE"""),"Open") -> Open | AN6: =IFERROR(__xludf.DUMMYFUNCTION("""COMPUTED_VALUE"""),"High") -> High | AO6: =IFERROR(__xludf.DUMMYFUNCTION("""COMPUTED_VALUE"""),"Low") -> Low | AP6: =IFERROR(__xludf.DUMMYFUNCTION("""COMPUTED_VALUE"""),"Close") -> Close | AQ6: =IFERROR(__xludf.DUMMYFUNCTION("""COMPUTED_VALUE"""),"Volume") -> Volume | AR6: Daily Returns | AS6: Standard Deviation | AT6: Average Return | AU6: Annual Return | AX6: =IFERROR(__xludf.DUMMYFUNCTION("GOOGLEFINANCE(""NSE:ITC"", ""all"", DATE(2024,4,1), DATE(2025,4,30)) "),"Date") -> Date | AY6: =IFERROR(__xludf.DUMMYFUNCTION("""COMPUTED_VALUE"""),"Open") -> Open | AZ6: =IFERROR(__xludf.DUMMYFUNCTION("""COMPUTED_VALUE"""),"High") -> High | BA6: =IFERROR(__xludf.DUMMYFUNCTION("""COMPUTED_VALUE"""),"Low") -> Low | BB6: =IFERROR(__xludf.DUMMYFUNCTION("""COMPUTED_VALUE"""),"Close") -> Close | BC6: =IFERROR(__xludf.DUMMYFUNCTION("""COMPUTED_VALUE"""),"Volume") -> Volume | BD6: Daily Returns | BE6: Standard Deviation | BF6: Average Return | BG6: Annual Return | BI6: T-Bill RATE | BK6: XAU/INR – Gold Price per Gram (INR) | BL6: =(COVAR('Part A'!H7:H271,'Part A'!H7:H271))*(252) -> 0.028790752 | BM6: =(COVAR('Part A'!H7:H272,'Part A'!T7:T272))*(252) -> 0.0014539536 | BN6: =(COVAR('Part A'!H7:H272,'Part A'!AF7:AF272))*(252) -> 0.0058478105 | BO6: =(COVAR('Part A'!H7:H272,'Part A'!AR7:AR272))*(252) -> 0.0050895786 | BQ6: XAU/INR – Gold Price per Gram (INR) | BR6: =CORREL('Part A'!H7:H272,'Part A'!H7:H272) -> 1 | BS6: =CORREL('Part A'!H7:H272,'Part A'!T7:T272) -> 0.041214768 | BT6: =CORREL('Part A'!H7:H272,'Part A'!AF7:AF272) -> 0.092611843 | BU6: =CORREL('Part A'!H7:H272,'Part A'!AR7:AR272) -> 0.068538574
B7: 45383 | C7: 6003.51 | D7: 6072.94 | E7: 5974.12 | F7: 6033.77 | G7: - | H7: 0 | I7: =STDEV(H7:H271)*15.8745078664 -> 0.16999944 | J7: =AVERAGE(H7:H271) -> 0.0014853748 | K7: =(1 + J7)^252 - 1 -> 0.45359052 | N7: =IFERROR(__xludf.DUMMYFUNCTION("""COMPUTED_VALUE"""),45383.64583333333) -> 45383.646 | O7: =IFERROR(__xludf.DUMMYFUNCTION("""COMPUTED_VALUE"""),1096.05) -> 1096.05 | P7: =IFERROR(__xludf.DUMMYFUNCTION("""COMPUTED_VALUE"""),1102.95) -> 1102.95 | Q7: =IFERROR(__xludf.DUMMYFUNCTION("""COMPUTED_VALUE"""),1094.45) -> 1094.45 | R7: =IFERROR(__xludf.DUMMYFUNCTION("""COMPUTED_VALUE"""),1099.65) -> 1099.65 | S7: =IFERROR(__xludf.DUMMYFUNCTION("""COMPUTED_VALUE"""),1.0848191E7) -> 10848191 | T7: 0 | U7: =STDEV(T7:T271)*15.8745078664 -> 0.20830139 | V7: =AVERAGE(T7:T271) -> 0.00098332978 | W7: =(1 + V7)^252 - 1 -> 0.28104654 | Z7: =IFERROR(__xludf.DUMMYFUNCTION("""COMPUTED_VALUE"""),45383.64583333333) -> 45383.646 | AA7: =IFERROR(__xludf.DUMMYFUNCTION("""COMPUTED_VALUE"""),294.9) -> 294.9 | AB7: =IFERROR(__xludf.DUMMYFUNCTION("""COMPUTED_VALUE"""),319.5) -> 319.5 | AC7: =IFERROR(__xludf.DUMMYFUNCTION("""COMPUTED_VALUE"""),292.15) -> 292.15 | AD7: =IFERROR(__xludf.DUMMYFUNCTION("""COMPUTED_VALUE"""),315.2) -> 315.2 | AE7: =IFERROR(__xludf.DUMMYFUNCTION("""COMPUTED_VALUE"""),4.02675E7) -> 40267500 | AF7: 0 | AG7: =STDEV(AF8:AF271)*15.8745078664 -> 0.37354583 | AH7: =AVERAGE(AF7:AF271) -> 0.00097565997 | AI7: =(1 + AH7)^252 - 1 -> 0.27857535 | AL7: =IFERROR(__xludf.DUMMYFUNCTION("""COMPUTED_VALUE"""),45383.64583333333) -> 45383.646 | AM7: =IFERROR(__xludf.DUMMYFUNCTION("""COMPUTED_VALUE"""),3392.0) -> 3392 | AN7: =IFERROR(__xludf.DUMMYFUNCTION("""COMPUTED_VALUE"""),3454.25) -> 3454.25 | AO7: =IFERROR(__xludf.DUMMYFUNCTION("""COMPUTED_VALUE"""),3362.1) -> 3362.1 | AP7: =IFERROR(__xludf.DUMMYFUNCTION("""COMPUTED_VALUE"""),3403.35) -> 3403.35 | AQ7: =IFERROR(__xludf.DUMMYFUNCTION("""COMPUTED_VALUE"""),2513886.0) -> 2513886 | AR7: 0 | AS7: =STDEV(AR7:AR271)*15.8745078664 -> 0.43847136 | AT7: =AVERAGE(AR7:AR271) -> 0.0010438666 | AU7: =(1 + AT7)^252 - 1 -> 0.30071899 | AX7: =IFERROR(__xludf.DUMMYFUNCTION("""COMPUTED_VALUE"""),45383.64583333333) -> 45383.646 | AY7: =IFERROR(__xludf.DUMMYFUNCTION("""COMPUTED_VALUE"""),429.1) -> 429.1 | AZ7: =IFERROR(__xludf.DUMMYFUNCTION("""COMPUTED_VALUE"""),431.35) -> 431.35 | BA7: =IFERROR(__xludf.DUMMYFUNCTION("""COMPUTED_VALUE"""),425.75) -> 425.75 | BB7: =IFERROR(__xludf.DUMMYFUNCTION("""COMPUTED_VALUE"""),426.7) -> 426.7 | BC7: =IFERROR(__xludf.DUMMYFUNCTION("""COMPUTED_VALUE"""),9382308.0) -> 9382308 | BD7: 0 | BE7: =STDEV(BD7:BD271)*15.8745078664 -> 0.19804371 | BF7: =AVERAGE(BD7:BD271) -> -7.9676896e-06 | BG7: =(1 + BF7)^252 - 1 -> -0.0020058514 | BI7: 0.0586 | BK7: ICICI Bank Ltd | BL7: =(COVAR('Part A'!H7:H272,'Part A'!T7:T272))*(252) -> 0.0014539536 | BM7: =(COVAR('Part A'!T7:T271,'Part A'!T7:T271))*(252) -> 0.043225734 | BN7: =(COVAR('Part A'!T7:T272,'Part A'!AF7:AF272))*(252) -> 0.031250305 | BO7: =(COVAR('Part A'!T7:T272,'Part A'!AR7:AR272))*(252) -> 0.03469537 | BQ7: ICICI Bank Ltd | BR7: =CORREL('Part A'!H7:H272,'Part A'!T7:T272) -> 0.041214768 | BS7: =CORREL('Part A'!T7:T272,'Part A'!T7:T272) -> 1 | BT7: =CORREL('Part A'!AF7:AF272,'Part A'!T7:T272) -> 0.40390834 | BU7: =CORREL('Part A'!AR7:AR272,'Part A'!T7:T272) -> 0.38131166
B8: 45384 | C8: 6036.07 | D8: 6112.94 | E8: 6022.03 | F8: 6107.29 | G8: - | H8: =LN(F8/F7) -> 0.012111117 | N8: =IFERROR(__xludf.DUMMYFUNCTION("""COMPUTED_VALUE"""),45384.64583333333) -> 45384.646 | O8: =IFERROR(__xludf.DUMMYFUNCTION("""COMPUTED_VALUE"""),1094.45) -> 1094.45 | P8: =IFERROR(__xludf.DUMMYFUNCTION("""COMPUTED_VALUE"""),1094.45) -> 1094.45 | Q8: =IFERROR(__xludf.DUMMYFUNCTION("""COMPUTED_VALUE"""),1079.25) -> 1079.25 | R8: =IFERROR(__xludf.DUMMYFUNCTION("""COMPUTED_VALUE"""),1081.2) -> 1081.2 | S8: =IFERROR(__xludf.DUMMYFUNCTION("""COMPUTED_VALUE"""),1.4380396E7) -> 14380396 | T8: =LN(R8/R7) -> -0.016920412 | Z8: =IFERROR(__xludf.DUMMYFUNCTION("""COMPUTED_VALUE"""),45384.64583333333) -> 45384.646 | AA8: =IFERROR(__xludf.DUMMYFUNCTION("""COMPUTED_VALUE"""),314.5) -> 314.5 | AB8: =IFERROR(__xludf.DUMMYFUNCTION("""COMPUTED_VALUE"""),314.5) -> 314.5 | AC8: =IFERROR(__xludf.DUMMYFUNCTION("""COMPUTED_VALUE"""),303.65) -> 303.65 | AD8: =IFERROR(__xludf.DUMMYFUNCTION("""COMPUTED_VALUE"""),304.75) -> 304.75 | AE8: =IFERROR(__xludf.DUMMYFUNCTION("""COMPUTED_VALUE"""),1.8843574E7) -> 18843574 | AF8: =LN(AD8/AD7) -> -0.03371559 | AL8: =IFERROR(__xludf.DUMMYFUNCTION("""COMPUTED_VALUE"""),45384.64583333333) -> 45384.646 | AM8: =IFERROR(__xludf.DUMMYFUNCTION("""COMPUTED_VALUE"""),3440.0) -> 3440 | AN8: =IFERROR(__xludf.DUMMYFUNCTION("""COMPUTED_VALUE"""),3584.0) -> 3584 | AO8: =IFERROR(__xludf.DUMMYFUNCTION("""COMPUTED_VALUE"""),3412.0) -> 3412 | AP8: =IFERROR(__xludf.DUMMYFUNCTION("""COMPUTED_VALUE"""),3543.0) -> 3543 | AQ8: =IFERROR(__xludf.DUMMYFUNCTION("""COMPUTED_VALUE"""),3169551.0) -> 3169551 | AR8: =LN(AP8/AP7) -> 0.040213585 | AX8: =IFERROR(__xludf.DUMMYFUNCTION("""COMPUTED_VALUE"""),45384.64583333333) -> 45384.646 | AY8: =IFERROR(__xludf.DUMMYFUNCTION("""COMPUTED_VALUE"""),428.7) -> 428.7 | AZ8: =IFERROR(__xludf.DUMMYFUNCTION("""COMPUTED_VALUE"""),428.7) -> 428.7 | BA8: =IFERROR(__xludf.DUMMYFUNCTION("""COMPUTED_VALUE"""),424.6) -> 424.6 | BB8: =IFERROR(__xludf.DUMMYFUNCTION("""COMPUTED_VALUE"""),425.85) -> 425.85 | BC8: =IFERROR(__xludf.DUMMYFUNCTION("""COMPUTED_VALUE"""),8853678.0) -> 8853678 | BD8: =LN(BB8/BB7) -> -0.0019940186 | BK8: Indus Towers Ltd | BL8: =(COVAR('Part A'!H7:H272,'Part A'!AF7:AF272))*(252) -> 0.0058478105 | BM8: =(COVAR('Part A'!T7:T272,'Part A'!AF7:AF272))*(252) -> 0.031250305 | BN8: =(COVAR('Part A'!AF7:AF272,'Part A'!AF7:AF272))*(252) -> 0.13848429 | BO8: =(COVAR('Part A'!AF7:AF272,'Part A'!AR7:AR272))*(252) -> 0.074433701 | BQ8: Indus Towers Ltd | BR8: =CORREL('Part A'!AF7:AF272,'Part A'!H7:H272) -> 0.092611843 | BS8: =CORREL('Part A'!AF7:AF272,'Part A'!T7:T272) -> 0.40390834 | BT8: =CORREL('Part A'!AF7:AF272,'Part A'!AF7:AF272) -> 1 | BU8: =CORREL('Part A'!AF7:AF272,'Part A'!AR7:AR272) -> 0.45703462
B9: 45385 | C9: 6110.08 | D9: 6178.04 | E9: 6082.12 | F9: 6171.38 | G9: - | H9: =LN(F9/F8) -> 0.010439336 | N9: =IFERROR(__xludf.DUMMYFUNCTION("""COMPUTED_VALUE"""),45385.64583333333) -> 45385.646 | O9: =IFERROR(__xludf.DUMMYFUNCTION("""COMPUTED_VALUE"""),1075.0) -> 1075 | P9: =IFERROR(__xludf.DUMMYFUNCTION("""COMPUTED_VALUE"""),1083.65) -> 1083.65 | Q9: =IFERROR(__xludf.DUMMYFUNCTION("""COMPUTED_VALUE"""),1072.25) -> 1072.25 | R9: =IFERROR(__xludf.DUMMYFUNCTION("""COMPUTED_VALUE"""),1077.2) -> 1077.2 | S9: =IFERROR(__xludf.DUMMYFUNCTION("""COMPUTED_VALUE"""),1.5477184E7) -> 15477184 | T9: =LN(R9/R8) -> -0.0037064535 | Z9: =IFERROR(__xludf.DUMMYFUNCTION("""COMPUTED_VALUE"""),45385.64583333333) -> 45385.646 | AA9: =IFERROR(__xludf.DUMMYFUNCTION("""COMPUTED_VALUE"""),304.8) -> 304.8 | AB9: =IFERROR(__xludf.DUMMYFUNCTION("""COMPUTED_VALUE"""),307.4) -> 307.4 | AC9: =IFERROR(__xludf.DUMMYFUNCTION("""COMPUTED_VALUE"""),298.4) -> 298.4 | AD9: =IFERROR(__xludf.DUMMYFUNCTION("""COMPUTED_VALUE"""),300.55) -> 300.55 | AE9: =IFERROR(__xludf.DUMMYFUNCTION("""COMPUTED_VALUE"""),2.1197899E7) -> 21197899 | AF9: =LN(AD9/AD8) -> -0.013877639 | AL9: =IFERROR(__xludf.DUMMYFUNCTION("""COMPUTED_VALUE"""),45385.64583333333) -> 45385.646 | AM9: =IFERROR(__xludf.DUMMYFUNCTION("""COMPUTED_VALUE"""),3540.0) -> 3540 | AN9: =IFERROR(__xludf.DUMMYFUNCTION("""COMPUTED_VALUE"""),3610.8) -> 3610.8 | AO9: =IFERROR(__xludf.DUMMYFUNCTION("""COMPUTED_VALUE"""),3508.3) -> 3508.3 | AP9: =IFERROR(__xludf.DUMMYFUNCTION("""COMPUTED_VALUE"""),3589.3) -> 3589.3 | AQ9: =IFERROR(__xludf.DUMMYFUNCTION("""COMPUTED_VALUE"""),2077663.0) -> 2077663 | AR9: =LN(AP9/AP8) -> 0.012983372 | AX9: =IFERROR(__xludf.DUMMYFUNCTION("""COMPUTED_VALUE"""),45385.64583333333) -> 45385.646 | AY9: =IFERROR(__xludf.DUMMYFUNCTION("""COMPUTED_VALUE"""),426.0) -> 426 | AZ9: =IFERROR(__xludf.DUMMYFUNCTION("""COMPUTED_VALUE"""),428.8) -> 428.8 | BA9: =IFERROR(__xludf.DUMMYFUNCTION("""COMPUTED_VALUE"""),421.0) -> 421 | BB9: =IFERROR(__xludf.DUMMYFUNCTION("""COMPUTED_VALUE"""),425.2) -> 425.2 | BC9: =IFERROR(__xludf.DUMMYFUNCTION("""COMPUTED_VALUE"""),1.266452E7) -> 12664520 | BD9: =LN(BB9/BB8) -> -0.0015275251 | BK9: Hindustan Aeronautics Limited | BL9: =(COVAR('Part A'!H7:H272,'Part A'!AR7:AR272))*(252) -> 0.0050895786 | BM9: =(COVAR('Part A'!T7:T272,'Part A'!AR7:AR272))*(252) -> 0.03469537 | BN9: =(COVAR('Part A'!AF7:AF272,'Part A'!AR7:AR272))*(252) -> 0.074433701 | BO9: =(COVAR('Part A'!AR7:AR272,'Part A'!AR7:AR272))*(252) -> 0.19153163 | BQ9: Hindustan Aeronautics Limited | BR9: =CORREL('Part A'!H7:H272,'Part A'!AR7:AR272) -> 0.068538574 | BS9: =CORREL('Part A'!T7:T272,'Part A'!AR7:AR272) -> 0.38131166 | BT9: =CORREL('Part A'!AF7:AF272,'Part A'!AR7:AR272) -> 0.45703462 | BU9: =CORREL('Part A'!AR7:AR272,'Part A'!AR7:AR272) -> 1
B10: 45386 | C10: 6173.52 | D10: 6183.24 | E10: 6111.03 | F10: 6136.13 | G10: - | H10: =LN(F10/F9) -> -0.0057282255 | N10: =IFERROR(__xludf.DUMMYFUNCTION("""COMPUTED_VALUE"""),45386.64583333333) -> 45386.646 | O10: =IFERROR(__xludf.DUMMYFUNCTION("""COMPUTED_VALUE"""),1084.75) -> 1084.75 | P10: =IFERROR(__xludf.DUMMYFUNCTION("""COMPUTED_VALUE"""),1085.8) -> 1085.8 | Q10: =IFERROR(__xludf.DUMMYFUNCTION("""COMPUTED_VALUE"""),1063.45) -> 1063.45 | R10: =IFERROR(__xludf.DUMMYFUNCTION("""COMPUTED_VALUE"""),1078.85) -> 1078.85 | S10: =IFERROR(__xludf.DUMMYFUNCTION("""COMPUTED_VALUE"""),2.1419689E7) -> 21419689 | T10: =LN(R10/R9) -> 0.001530577 | Z10: =IFERROR(__xludf.DUMMYFUNCTION("""COMPUTED_VALUE"""),45386.64583333333) -> 45386.646 | AA10: =IFERROR(__xludf.DUMMYFUNCTION("""COMPUTED_VALUE"""),304.05) -> 304.05 | AB10: =IFERROR(__xludf.DUMMYFUNCTION("""COMPUTED_VALUE"""),310.0) -> 310 | AC10: =IFERROR(__xludf.DUMMYFUNCTION("""COMPUTED_VALUE"""),301.55) -> 301.55 | AD10: =IFERROR(__xludf.DUMMYFUNCTION("""COMPUTED_VALUE"""),306.6) -> 306.6 | AE10: =IFERROR(__xludf.DUMMYFUNCTION("""COMPUTED_VALUE"""),1.38752E7) -> 13875200 | AF10: =LN(AD10/AD9) -> 0.019929837 | AL10: =IFERROR(__xludf.DUMMYFUNCTION("""COMPUTED_VALUE"""),45386.64583333333) -> 45386.646 | AM10: =IFERROR(__xludf.DUMMYFUNCTION("""COMPUTED_VALUE"""),3609.95) -> 3609.95 | AN10: =IFERROR(__xludf.DUMMYFUNCTION("""COMPUTED_VALUE"""),3614.95) -> 3614.95 | AO10: =IFERROR(__xludf.DUMMYFUNCTION("""COMPUTED_VALUE"""),3512.2) -> 3512.2 | AP10: =IFERROR(__xludf.DUMMYFUNCTION("""COMPUTED_VALUE"""),3540.95) -> 3540.95 | AQ10: =IFERROR(__xludf.DUMMYFUNCTION("""COMPUTED_VALUE"""),1591827.0) -> 1591827 | AR10: =LN(AP10/AP9) -> -0.013562145 | AX10: =IFERROR(__xludf.DUMMYFUNCTION("""COMPUTED_VALUE"""),45386.64583333333) -> 45386.646 | AY10: =IFERROR(__xludf.DUMMYFUNCTION("""COMPUTED_VALUE"""),425.55) -> 425.55 | AZ10: =IFERROR(__xludf.DUMMYFUNCTION("""COMPUTED_VALUE"""),427.35) -> 427.35 | BA10: =IFERROR(__xludf.DUMMYFUNCTION("""COMPUTED_VALUE"""),419.9) -> 419.9 | BB10: =IFERROR(__xludf.DUMMYFUNCTION("""COMPUTED_VALUE"""),422.75) -> 422.75 | BC10: =IFERROR(__xludf.DUMMYFUNCTION("""COMPUTED_VALUE"""),1.835841E7) -> 18358410 | BD10: =LN(BB10/BB9) -> -0.0057786587
B11: 45387 | C11: 6138.98 | D11: 6242.15 | E11: 6084.12 | F11: 6237.71 | G11: - | H11: =LN(F11/F10) -> 0.016418878 | N11: =IFERROR(__xludf.DUMMYFUNCTION("""COMPUTED_VALUE"""),45387.64583333333) -> 45387.646 | O11: =IFERROR(__xludf.DUMMYFUNCTION("""COMPUTED_VALUE"""),1070.0) -> 1070 | P11: =IFERROR(__xludf.DUMMYFUNCTION("""COMPUTED_VALUE"""),1086.0) -> 1086 | Q11: =IFERROR(__xludf.DUMMYFUNCTION("""COMPUTED_VALUE"""),1067.45) -> 1067.45 | R11: =IFERROR(__xludf.DUMMYFUNCTION("""COMPUTED_VALUE"""),1083.4) -> 1083.4 | S11: =IFERROR(__xludf.DUMMYFUNCTION("""COMPUTED_VALUE"""),1.5340637E7) -> 15340637 | T11: =LN(R11/R10) -> 0.0042085852 | Z11: =IFERROR(__xludf.DUMMYFUNCTION("""COMPUTED_VALUE"""),45387.64583333333) -> 45387.646 | AA11: =IFERROR(__xludf.DUMMYFUNCTION("""COMPUTED_VALUE"""),305.95) -> 305.95 | AB11: =IFERROR(__xludf.DUMMYFUNCTION("""COMPUTED_VALUE"""),321.55) -> 321.55 | AC11: =IFERROR(__xludf.DUMMYFUNCTION("""COMPUTED_VALUE"""),302.1) -> 302.1 | AD11: =IFERROR(__xludf.DUMMYFUNCTION("""COMPUTED_VALUE"""),314.0) -> 314 | AE11: =IFERROR(__xludf.DUMMYFUNCTION("""COMPUTED_VALUE"""),2.1960872E7) -> 21960872 | AF11: =LN(AD11/AD10) -> 0.023849019 | AL11: =IFERROR(__xludf.DUMMYFUNCTION("""COMPUTED_VALUE"""),45387.64583333333) -> 45387.646 | AM11: =IFERROR(__xludf.DUMMYFUNCTION("""COMPUTED_VALUE"""),3545.0) -> 3545 | AN11: =IFERROR(__xludf.DUMMYFUNCTION("""COMPUTED_VALUE"""),3595.0) -> 3595 | AO11: =IFERROR(__xludf.DUMMYFUNCTION("""COMPUTED_VALUE"""),3507.85) -> 3507.85 | AP11: =IFERROR(__xludf.DUMMYFUNCTION("""COMPUTED_VALUE"""),3586.05) -> 3586.05 | AQ11: =IFERROR(__xludf.DUMMYFUNCTION("""COMPUTED_VALUE"""),1123258.0) -> 1123258 | AR11: =LN(AP11/AP10) -> 0.012656265 | AX11: =IFERROR(__xludf.DUMMYFUNCTION("""COMPUTED_VALUE"""),45387.64583333333) -> 45387.646 | AY11: =IFERROR(__xludf.DUMMYFUNCTION("""COMPUTED_VALUE"""),422.5) -> 422.5 | AZ11: =IFERROR(__xludf.DUMMYFUNCTION("""COMPUTED_VALUE"""),431.7) -> 431.7 | BA11: =IFERROR(__xludf.DUMMYFUNCTION("""COMPUTED_VALUE"""),419.95) -> 419.95 | BB11: =IFERROR(__xludf.DUMMYFUNCTION("""COMPUTED_VALUE"""),427.55) -> 427.55 | BC11: =IFERROR(__xludf.DUMMYFUNCTION("""COMPUTED_VALUE"""),1.6147032E7) -> 16147032 | BD11: =LN(BB11/BB10) -> 0.011290253 | BK11: COVARIANCE MATRIX | BL11: XAU/INR – Gold Price per Gram (INR) | BM11: ICICI Bank Ltd | BN11: Indus Towers Ltd | BO11: Hindustan Aeronautics Limited | BQ11: EQUALLY WEIGHTED
B12: 45390 | C12: 6219.67 | D12: 6302.78 | E12: 6168.43 | F12: 6260.67 | G12: - | H12: =LN(F12/F11) -> 0.0036740803 | N12: =IFERROR(__xludf.DUMMYFUNCTION("""COMPUTED_VALUE"""),45390.64583333333) -> 45390.646 | O12: =IFERROR(__xludf.DUMMYFUNCTION("""COMPUTED_VALUE"""),1078.35) -> 1078.35 | P12: =IFERROR(__xludf.DUMMYFUNCTION("""COMPUTED_VALUE"""),1091.75) -> 1091.75 | Q12: =IFERROR(__xludf.DUMMYFUNCTION("""COMPUTED_VALUE"""),1076.3) -> 1076.3 | R12: =IFERROR(__xludf.DUMMYFUNCTION("""COMPUTED_VALUE"""),1087.15) -> 1087.15 | S12: =IFERROR(__xludf.DUMMYFUNCTION("""COMPUTED_VALUE"""),8023461.0) -> 8023461 | T12: =LN(R12/R11) -> 0.0034553489 | Z12: =IFERROR(__xludf.DUMMYFUNCTION("""COMPUTED_VALUE"""),45390.64583333333) -> 45390.646 | AA12: =IFERROR(__xludf.DUMMYFUNCTION("""COMPUTED_VALUE"""),316.5) -> 316.5 | AB12: =IFERROR(__xludf.DUMMYFUNCTION("""COMPUTED_VALUE"""),331.5) -> 331.5 | AC12: =IFERROR(__xludf.DUMMYFUNCTION("""COMPUTED_VALUE"""),315.95) -> 315.95 | AD12: =IFERROR(__xludf.DUMMYFUNCTION("""COMPUTED_VALUE"""),327.8) -> 327.8 | AE12: =IFERROR(__xludf.DUMMYFUNCTION("""COMPUTED_VALUE"""),2.8736885E7) -> 28736885 | AF12: =LN(AD12/AD11) -> 0.04301068 | AL12: =IFERROR(__xludf.DUMMYFUNCTION("""COMPUTED_VALUE"""),45390.64583333333) -> 45390.646 | AM12: =IFERROR(__xludf.DUMMYFUNCTION("""COMPUTED_VALUE"""),3600.0) -> 3600 | AN12: =IFERROR(__xludf.DUMMYFUNCTION("""COMPUTED_VALUE"""),3600.0) -> 3600 | AO12: =IFERROR(__xludf.DUMMYFUNCTION("""COMPUTED_VALUE"""),3543.05) -> 3543.05 | AP12: =IFERROR(__xludf.DUMMYFUNCTION("""COMPUTED_VALUE"""),3567.15) -> 3567.15 | AQ12: =IFERROR(__xludf.DUMMYFUNCTION("""COMPUTED_VALUE"""),865339.0) -> 865339 | AR12: =LN(AP12/AP11) -> -0.0052843606 | AX12: =IFERROR(__xludf.DUMMYFUNCTION("""COMPUTED_VALUE"""),45390.64583333333) -> 45390.646 | AY12: =IFERROR(__xludf.DUMMYFUNCTION("""COMPUTED_VALUE"""),428.3) -> 428.3 | AZ12: =IFERROR(__xludf.DUMMYFUNCTION("""COMPUTED_VALUE"""),431.4) -> 431.4 | BA12: =IFERROR(__xludf.DUMMYFUNCTION("""COMPUTED_VALUE"""),427.75) -> 427.75 | BB12: =IFERROR(__xludf.DUMMYFUNCTION("""COMPUTED_VALUE"""),429.1) -> 429.1 | BC12: =IFERROR(__xludf.DUMMYFUNCTION("""COMPUTED_VALUE"""),8516632.0) -> 8516632 | BD12: =LN(BB12/BB11) -> 0.0036187514 | BK12: XAU/INR – Gold Price per Gram (INR) | BL12: 0.028790752 | BM12: 0.0014539536 | BN12: 0.0058478105 | BO12: 0.0050895786
B13: 45391 | C13: 6262.85 | D13: 6328.57 | E13: 6254.18 | F13: 6291.41 | G13: - | H13: =LN(F13/F12) -> 0.0048980028 | N13: =IFERROR(__xludf.DUMMYFUNCTION("""COMPUTED_VALUE"""),45391.64583333333) -> 45391.646 | O13: =IFERROR(__xludf.DUMMYFUNCTION("""COMPUTED_VALUE"""),1091.95) -> 1091.95 | P13: =IFERROR(__xludf.DUMMYFUNCTION("""COMPUTED_VALUE"""),1115.25) -> 1115.25 | Q13: =IFERROR(__xludf.DUMMYFUNCTION("""COMPUTED_VALUE"""),1088.3) -> 1088.3 | R13: =IFERROR(__xludf.DUMMYFUNCTION("""COMPUTED_VALUE"""),1107.05) -> 1107.05 | S13: =IFERROR(__xludf.DUMMYFUNCTION("""COMPUTED_VALUE"""),1.2298463E7) -> 12298463 | T13: =LN(R13/R12) -> 0.018139227 | Z13: =IFERROR(__xludf.DUMMYFUNCTION("""COMPUTED_VALUE"""),45391.64583333333) -> 45391.646 | AA13: =IFERROR(__xludf.DUMMYFUNCTION("""COMPUTED_VALUE"""),328.5) -> 328.5 | AB13: =IFERROR(__xludf.DUMMYFUNCTION("""COMPUTED_VALUE"""),331.0) -> 331 | AC13: =IFERROR(__xludf.DUMMYFUNCTION("""COMPUTED_VALUE"""),324.2) -> 324.2 | AD13: =IFERROR(__xludf.DUMMYFUNCTION("""COMPUTED_VALUE"""),328.0) -> 328 | AE13: =IFERROR(__xludf.DUMMYFUNCTION("""COMPUTED_VALUE"""),1.3705541E7) -> 13705541 | AF13: =LN(AD13/AD12) -> 0.00060994207 | AL13: =IFERROR(__xludf.DUMMYFUNCTION("""COMPUTED_VALUE"""),45391.64583333333) -> 45391.646 | AM13: =IFERROR(__xludf.DUMMYFUNCTION("""COMPUTED_VALUE"""),3568.0) -> 3568 | AN13: =IFERROR(__xludf.DUMMYFUNCTION("""COMPUTED_VALUE"""),3589.0) -> 3589 | AO13: =IFERROR(__xludf.DUMMYFUNCTION("""COMPUTED_VALUE"""),3527.0) -> 3527 | AP13: =IFERROR(__xludf.DUMMYFUNCTION("""COMPUTED_VALUE"""),3546.55) -> 3546.55 | AQ13: =IFERROR(__xludf.DUMMYFUNCTION("""COMPUTED_VALUE"""),649755.0) -> 649755 | AR13: =LN(AP13/AP12) -> -0.0057916577 | AX13: =IFERROR(__xludf.DUMMYFUNCTION("""COMPUTED_VALUE"""),45391.64583333333) -> 45391.646 | AY13: =IFERROR(__xludf.DUMMYFUNCTION("""COMPUTED_VALUE"""),430.45) -> 430.45 | AZ13: =IFERROR(__xludf.DUMMYFUNCTION("""COMPUTED_VALUE"""),431.5) -> 431.5 | BA13: =IFERROR(__xludf.DUMMYFUNCTION("""COMPUTED_VALUE"""),425.55) -> 425.55 | BB13: =IFERROR(__xludf.DUMMYFUNCTION("""COMPUTED_VALUE"""),426.35) -> 426.35 | BC13: =IFERROR(__xludf.DUMMYFUNCTION("""COMPUTED_VALUE"""),6708894.0) -> 6708894 | BD13: =LN(BB13/BB12) -> -0.0064293868 | BK13: ICICI Bank Ltd | BL13: 0.0014539536 | BM13: 0.043225734 | BN13: 0.031250305 | BO13: 0.03469537 | BQ13: COMPANY | BR13: XAU/INR – Gold Price per Gram (INR) | BS13: ICICI Bank Ltd | BT13: Indus Towers Ltd | BU13: Hindustan Aeronautics Limited
B14: 45392 | C14: 6293.12 | D14: 6314.96 | E14: 6218.03 | F14: 6254.62 | G14: - | H14: =LN(F14/F13) -> -0.0058648203 | N14: =IFERROR(__xludf.DUMMYFUNCTION("""COMPUTED_VALUE"""),45392.64583333333) -> 45392.646 | O14: =IFERROR(__xludf.DUMMYFUNCTION("""COMPUTED_VALUE"""),1110.95) -> 1110.95 | P14: =IFERROR(__xludf.DUMMYFUNCTION("""COMPUTED_VALUE"""),1116.55) -> 1116.55 | Q14: =IFERROR(__xludf.DUMMYFUNCTION("""COMPUTED_VALUE"""),1105.15) -> 1105.15 | R14: =IFERROR(__xludf.DUMMYFUNCTION("""COMPUTED_VALUE"""),1109.4) -> 1109.4 | S14: =IFERROR(__xludf.DUMMYFUNCTION("""COMPUTED_VALUE"""),1.0598E7) -> 10598000 | T14: =LN(R14/R13) -> 0.0021205088 | Z14: =IFERROR(__xludf.DUMMYFUNCTION("""COMPUTED_VALUE"""),45392.64583333333) -> 45392.646 | AA14: =IFERROR(__xludf.DUMMYFUNCTION("""COMPUTED_VALUE"""),325.0) -> 325 | AB14: =IFERROR(__xludf.DUMMYFUNCTION("""COMPUTED_VALUE"""),330.0) -> 330 | AC14: =IFERROR(__xludf.DUMMYFUNCTION("""COMPUTED_VALUE"""),317.15) -> 317.15 | AD14: =IFERROR(__xludf.DUMMYFUNCTION("""COMPUTED_VALUE"""),326.7) -> 326.7 | AE14: =IFERROR(__xludf.DUMMYFUNCTION("""COMPUTED_VALUE"""),1.7295594E7) -> 17295594 | AF14: =LN(AD14/AD13) -> -0.0039712898 | AL14: =IFERROR(__xludf.DUMMYFUNCTION("""COMPUTED_VALUE"""),45392.64583333333) -> 45392.646 | AM14: =IFERROR(__xludf.DUMMYFUNCTION("""COMPUTED_VALUE"""),3550.0) -> 3550 | AN14: =IFERROR(__xludf.DUMMYFUNCTION("""COMPUTED_VALUE"""),3623.6) -> 3623.6 | AO14: =IFERROR(__xludf.DUMMYFUNCTION("""COMPUTED_VALUE"""),3548.65) -> 3548.65 | AP14: =IFERROR(__xludf.DUMMYFUNCTION("""COMPUTED_VALUE"""),3565.4) -> 3565.4 | AQ14: =IFERROR(__xludf.DUMMYFUNCTION("""COMPUTED_VALUE"""),1160813.0) -> 1160813 | AR14: =LN(AP14/AP13) -> 0.0053009496 | AX14: =IFERROR(__xludf.DUMMYFUNCTION("""COMPUTED_VALUE"""),45392.64583333333) -> 45392.646 | AY14: =IFERROR(__xludf.DUMMYFUNCTION("""COMPUTED_VALUE"""),428.3) -> 428.3 | AZ14: =IFERROR(__xludf.DUMMYFUNCTION("""COMPUTED_VALUE"""),437.8) -> 437.8 | BA14: =IFERROR(__xludf.DUMMYFUNCTION("""COMPUTED_VALUE"""),425.75) -> 425.75 | BB14: =IFERROR(__xludf.DUMMYFUNCTION("""COMPUTED_VALUE"""),436.95) -> 436.95 | BC14: =IFERROR(__xludf.DUMMYFUNCTION("""COMPUTED_VALUE"""),1.4008124E7) -> 14008124 | BD14: =LN(BB14/BB13) -> 0.024558167 | BK14: Indus Towers Ltd | BL14: 0.0058478105 | BM14: 0.031250305 | BN14: 0.13848429 | BO14: 0.074433701 | BQ14: Weights | BR14: 0.25 | BS14: 0.25 | BT14: 0.25 | BU14: 0.25
B15: 45394 | C15: 6354.25 | D15: 6534.13 | E15: 6270.12 | F15: 6292.97 | G15: - | H15: =LN(F15/F14) -> 0.0061127467 | N15: =IFERROR(__xludf.DUMMYFUNCTION("""COMPUTED_VALUE"""),45394.64583333333) -> 45394.646 | O15: =IFERROR(__xludf.DUMMYFUNCTION("""COMPUTED_VALUE"""),1103.5) -> 1103.5 | P15: =IFERROR(__xludf.DUMMYFUNCTION("""COMPUTED_VALUE"""),1111.85) -> 1111.85 | Q15: =IFERROR(__xludf.DUMMYFUNCTION("""COMPUTED_VALUE"""),1095.8) -> 1095.8 | R15: =IFERROR(__xludf.DUMMYFUNCTION("""COMPUTED_VALUE"""),1104.4) -> 1104.4 | S15: =IFERROR(__xludf.DUMMYFUNCTION("""COMPUTED_VALUE"""),1.2216657E7) -> 12216657 | T15: =LN(R15/R14) -> -0.0045171276 | Z15: =IFERROR(__xludf.DUMMYFUNCTION("""COMPUTED_VALUE"""),45394.64583333333) -> 45394.646 | AA15: =IFERROR(__xludf.DUMMYFUNCTION("""COMPUTED_VALUE"""),331.9) -> 331.9 | AB15: =IFERROR(__xludf.DUMMYFUNCTION("""COMPUTED_VALUE"""),336.0) -> 336 | AC15: =IFERROR(__xludf.DUMMYFUNCTION("""COMPUTED_VALUE"""),323.7) -> 323.7 | AD15: =IFERROR(__xludf.DUMMYFUNCTION("""COMPUTED_VALUE"""),328.05) -> 328.05 | AE15: =IFERROR(__xludf.DUMMYFUNCTION("""COMPUTED_VALUE"""),2.0855397E7) -> 20855397 | AF15: =LN(AD15/AD14) -> 0.0041237172 | AL15: =IFERROR(__xludf.DUMMYFUNCTION("""COMPUTED_VALUE"""),45394.64583333333) -> 45394.646 | AM15: =IFERROR(__xludf.DUMMYFUNCTION("""COMPUTED_VALUE"""),3565.0) -> 3565 | AN15: =IFERROR(__xludf.DUMMYFUNCTION("""COMPUTED_VALUE"""),3677.55) -> 3677.55 | AO15: =IFERROR(__xludf.DUMMYFUNCTION("""COMPUTED_VALUE"""),3550.0) -> 3550 | AP15: =IFERROR(__xludf.DUMMYFUNCTION("""COMPUTED_VALUE"""),3638.1) -> 3638.1 | AQ15: =IFERROR(__xludf.DUMMYFUNCTION("""COMPUTED_VALUE"""),3042596.0) -> 3042596 | AR15: =LN(AP15/AP14) -> 0.020185318 | AX15: =IFERROR(__xludf.DUMMYFUNCTION("""COMPUTED_VALUE"""),45394.64583333333) -> 45394.646 | AY15: =IFERROR(__xludf.DUMMYFUNCTION("""COMPUTED_VALUE"""),435.0) -> 435 | AZ15: =IFERROR(__xludf.DUMMYFUNCTION("""COMPUTED_VALUE"""),435.75) -> 435.75 | BA15: =IFERROR(__xludf.DUMMYFUNCTION("""COMPUTED_VALUE"""),428.3) -> 428.3 | BB15: =IFERROR(__xludf.DUMMYFUNCTION("""COMPUTED_VALUE"""),430.1) -> 430.1 | BC15: =IFERROR(__xludf.DUMMYFUNCTION("""COMPUTED_VALUE"""),1.8088372E7) -> 18088372 | BD15: =LN(BB15/BB14) -> -0.015801032 | BK15: Hindustan Aeronautics Limited | BL15: 0.0050895786 | BM15: 0.03469537 | BN15: 0.074433701 | BO15: 0.19153163 | BQ15: Annual Return | BR15: =(1 + 'Part A'!$J$7)^252 - 1 -> 0.45359052 | BS15: =(1 + 'Part A'!$V$7)^252 - 1 -> 0.28104654 | BT15: =(1 + 'Part A'!$AH$7)^252 - 1 -> 0.27857535 | BU15: =(1 + 'Part A'!$AT$7)^252 - 1 -> 0.30071899
B16: 45397 | C16: 6296.74 | D16: 6410.33 | E16: 6239.58 | F16: 6393.08 | G16: - | H16: =LN(F16/F15) -> 0.015783018 | N16: =IFERROR(__xludf.DUMMYFUNCTION("""COMPUTED_VALUE"""),45397.64583333333) -> 45397.646 | O16: =IFERROR(__xludf.DUMMYFUNCTION("""COMPUTED_VALUE"""),1100.2) -> 1100.2 | P16: =IFERROR(__xludf.DUMMYFUNCTION("""COMPUTED_VALUE"""),1106.15) -> 1106.15 | Q16: =IFERROR(__xludf.DUMMYFUNCTION("""COMPUTED_VALUE"""),1076.6) -> 1076.6 | R16: =IFERROR(__xludf.DUMMYFUNCTION("""COMPUTED_VALUE"""),1078.35) -> 1078.35 | S16: =IFERROR(__xludf.DUMMYFUNCTION("""COMPUTED_VALUE"""),1.0526597E7) -> 10526597 | T16: =LN(R16/R15) -> -0.023870106 | Z16: =IFERROR(__xludf.DUMMYFUNCTION("""COMPUTED_VALUE"""),45397.64583333333) -> 45397.646 | AA16: =IFERROR(__xludf.DUMMYFUNCTION("""COMPUTED_VALUE"""),322.35) -> 322.35 | AB16: =IFERROR(__xludf.DUMMYFUNCTION("""COMPUTED_VALUE"""),337.75) -> 337.75 | AC16: =IFERROR(__xludf.DUMMYFUNCTION("""COMPUTED_VALUE"""),322.25) -> 322.25 | AD16: =IFERROR(__xludf.DUMMYFUNCTION("""COMPUTED_VALUE"""),334.55) -> 334.55 | AE16: =IFERROR(__xludf.DUMMYFUNCTION("""COMPUTED_VALUE"""),1.54309E7) -> 15430900 | AF16: =LN(AD16/AD15) -> 0.019620309 | AL16: =IFERROR(__xludf.DUMMYFUNCTION("""COMPUTED_VALUE"""),45397.64583333333) -> 45397.646 | AM16: =IFERROR(__xludf.DUMMYFUNCTION("""COMPUTED_VALUE"""),3640.0) -> 3640 | AN16: =IFERROR(__xludf.DUMMYFUNCTION("""COMPUTED_VALUE"""),3700.0) -> 3700 | AO16: =IFERROR(__xludf.DUMMYFUNCTION("""COMPUTED_VALUE"""),3564.05) -> 3564.05 | AP16: =IFERROR(__xludf.DUMMYFUNCTION("""COMPUTED_VALUE"""),3629.25) -> 3629.25 | AQ16: =IFERROR(__xludf.DUMMYFUNCTION("""COMPUTED_VALUE"""),3848159.0) -> 3848159 | AR16: =LN(AP16/AP15) -> -0.002435552 | AX16: =IFERROR(__xludf.DUMMYFUNCTION("""COMPUTED_VALUE"""),45397.64583333333) -> 45397.646 | AY16: =IFERROR(__xludf.DUMMYFUNCTION("""COMPUTED_VALUE"""),428.0) -> 428 | AZ16: =IFERROR(__xludf.DUMMYFUNCTION("""COMPUTED_VALUE"""),429.15) -> 429.15 | BA16: =IFERROR(__xludf.DUMMYFUNCTION("""COMPUTED_VALUE"""),422.9) -> 422.9 | BB16: =IFERROR(__xludf.DUMMYFUNCTION("""COMPUTED_VALUE"""),425.9) -> 425.9 | BC16: =IFERROR(__xludf.DUMMYFUNCTION("""COMPUTED_VALUE"""),8746243.0) -> 8746243 | BD16: =LN(BB16/BB15) -> -0.0098131629 | BQ16: Standard Deviation | BR16: =STDEV('Part A'!$H$7:$H$271)*(252)^0.5 -> 0.16999944 | BS16: =STDEV(T7:T271)*15.8745078664 -> 0.20830139 | BT16: =STDEV(AF8:AF271)*15.8745078664 -> 0.37354583 | BU16: =STDEV('Part A'!$AR$7:$AR$271)*15.8745078664 -> 0.43847136
B17: 45398 | C17: 6398.04 | D17: 6450.94 | E17: 6345.29 | F17: 6406.13 | G17: - | H17: =LN(F17/F16) -> 0.0020391891 | N17: =IFERROR(__xludf.DUMMYFUNCTION("""COMPUTED_VALUE"""),45398.64583333333) -> 45398.646 | O17: =IFERROR(__xludf.DUMMYFUNCTION("""COMPUTED_VALUE"""),1070.55) -> 1070.55 | P17: =IFERROR(__xludf.DUMMYFUNCTION("""COMPUTED_VALUE"""),1074.6) -> 1074.6 | Q17: =IFERROR(__xludf.DUMMYFUNCTION("""COMPUTED_VALUE"""),1062.7) -> 1062.7 | R17: =IFERROR(__xludf.DUMMYFUNCTION("""COMPUTED_VALUE"""),1067.05) -> 1067.05 | S17: =IFERROR(__xludf.DUMMYFUNCTION("""COMPUTED_VALUE"""),1.1278092E7) -> 11278092 | T17: =LN(R17/R16) -> -0.010534264 | Z17: =IFERROR(__xludf.DUMMYFUNCTION("""COMPUTED_VALUE"""),45398.64583333333) -> 45398.646 | AA17: =IFERROR(__xludf.DUMMYFUNCTION("""COMPUTED_VALUE"""),336.8) -> 336.8 | AB17: =IFERROR(__xludf.DUMMYFUNCTION("""COMPUTED_VALUE"""),339.15) -> 339.15 | AC17: =IFERROR(__xludf.DUMMYFUNCTION("""COMPUTED_VALUE"""),326.45) -> 326.45 | AD17: =IFERROR(__xludf.DUMMYFUNCTION("""COMPUTED_VALUE"""),332.5) -> 332.5 | AE17: =IFERROR(__xludf.DUMMYFUNCTION("""COMPUTED_VALUE"""),1.499568E7) -> 14995680 | AF17: =LN(AD17/AD16) -> -0.0061464851 | AL17: =IFERROR(__xludf.DUMMYFUNCTION("""COMPUTED_VALUE"""),45398.64583333333) -> 45398.646 | AM17: =IFERROR(__xludf.DUMMYFUNCTION("""COMPUTED_VALUE"""),3626.0) -> 3626 | AN17: =IFERROR(__xludf.DUMMYFUNCTION("""COMPUTED_VALUE"""),3738.95) -> 3738.95 | AO17: =IFERROR(__xludf.DUMMYFUNCTION("""COMPUTED_VALUE"""),3585.35) -> 3585.35 | AP17: =IFERROR(__xludf.DUMMYFUNCTION("""COMPUTED_VALUE"""),3722.15) -> 3722.15 | AQ17: =IFERROR(__xludf.DUMMYFUNCTION("""COMPUTED_VALUE"""),2939862.0) -> 2939862 | AR17: =LN(AP17/AP16) -> 0.025275443 | AX17: =IFERROR(__xludf.DUMMYFUNCTION("""COMPUTED_VALUE"""),45398.64583333333) -> 45398.646 | AY17: =IFERROR(__xludf.DUMMYFUNCTION("""COMPUTED_VALUE"""),423.25) -> 423.25 | AZ17: =IFERROR(__xludf.DUMMYFUNCTION("""COMPUTED_VALUE"""),427.0) -> 427 | BA17: =IFERROR(__xludf.DUMMYFUNCTION("""COMPUTED_VALUE"""),423.2) -> 423.2 | BB17: =IFERROR(__xludf.DUMMYFUNCTION("""COMPUTED_VALUE"""),425.9) -> 425.9 | BC17: =IFERROR(__xludf.DUMMYFUNCTION("""COMPUTED_VALUE"""),9973638.0) -> 9973638 | BD17: =LN(BB17/BB16) -> 0 | BQ17: PORTFOLIO | BR17: RETURN | BS17: VARIANCE | BT17: STANDARD DEVIATION | BU17: STANDARD DEVIATION(%) | BV17: SHARPE RATIO
B18: 45400 | C18: 6342.86 | D18: 6426.98 | E18: 6342.86 | F18: 6388.2 | G18: - | H18: =LN(F18/F17) -> -0.0028028059 | N18: =IFERROR(__xludf.DUMMYFUNCTION("""COMPUTED_VALUE"""),45400.64583333333) -> 45400.646 | O18: =IFERROR(__xludf.DUMMYFUNCTION("""COMPUTED_VALUE"""),1074.0) -> 1074 | P18: =IFERROR(__xludf.DUMMYFUNCTION("""COMPUTED_VALUE"""),1078.05) -> 1078.05 | Q18: =IFERROR(__xludf.DUMMYFUNCTION("""COMPUTED_VALUE"""),1050.45) -> 1050.45 | R18: =IFERROR(__xludf.DUMMYFUNCTION("""COMPUTED_VALUE"""),1055.45) -> 1055.45 | S18: =IFERROR(__xludf.DUMMYFUNCTION("""COMPUTED_VALUE"""),1.6564216E7) -> 16564216 | T18: =LN(R18/R17) -> -0.010930615 | Z18: =IFERROR(__xludf.DUMMYFUNCTION("""COMPUTED_VALUE"""),45400.64583333333) -> 45400.646 | AA18: =IFERROR(__xludf.DUMMYFUNCTION("""COMPUTED_VALUE"""),335.5) -> 335.5 | AB18: =IFERROR(__xludf.DUMMYFUNCTION("""COMPUTED_VALUE"""),353.85) -> 353.85 | AC18: =IFERROR(__xludf.DUMMYFUNCTION("""COMPUTED_VALUE"""),335.0) -> 335 | AD18: =IFERROR(__xludf.DUMMYFUNCTION("""COMPUTED_VALUE"""),344.4) -> 344.4 | AE18: =IFERROR(__xludf.DUMMYFUNCTION("""COMPUTED_VALUE"""),4.0001173E7) -> 40001173 | AF18: =LN(AD18/AD17) -> 0.035163912 | AL18: =IFERROR(__xludf.DUMMYFUNCTION("""COMPUTED_VALUE"""),45400.64583333333) -> 45400.646 | AM18: =IFERROR(__xludf.DUMMYFUNCTION("""COMPUTED_VALUE"""),3744.0) -> 3744 | AN18: =IFERROR(__xludf.DUMMYFUNCTION("""COMPUTED_VALUE"""),3768.0) -> 3768 | AO18: =IFERROR(__xludf.DUMMYFUNCTION("""COMPUTED_VALUE"""),3652.7) -> 3652.7 | AP18: =IFERROR(__xludf.DUMMYFUNCTION("""COMPUTED_VALUE"""),3677.15) -> 3677.15 | AQ18: =IFERROR(__xludf.DUMMYFUNCTION("""COMPUTED_VALUE"""),2294396.0) -> 2294396 | AR18: =LN(AP18/AP17) -> -0.012163463 | AX18: =IFERROR(__xludf.DUMMYFUNCTION("""COMPUTED_VALUE"""),45400.64583333333) -> 45400.646 | AY18: =IFERROR(__xludf.DUMMYFUNCTION("""COMPUTED_VALUE"""),426.0) -> 426 | AZ18: =IFERROR(__xludf.DUMMYFUNCTION("""COMPUTED_VALUE"""),426.9) -> 426.9 | BA18: =IFERROR(__xludf.DUMMYFUNCTION("""COMPUTED_VALUE"""),417.65) -> 417.65 | BB18: =IFERROR(__xludf.DUMMYFUNCTION("""COMPUTED_VALUE"""),418.85) -> 418.85 | BC18: =IFERROR(__xludf.DUMMYFUNCTION("""COMPUTED_VALUE"""),2.1312388E7) -> 21312388 | BD18: =LN(BB18/BB17) -> -0.016691716 | BQ18: VALUES | BR18: {=MMULT($BR$14:$BU$14, TRANSPOSE($BR$15:$BU$15))} -> 0.32848285 | BS18: {=MMULT($BR$14:$BU$14, MMULT('Part A'!$BL$6:$BO$9, TRANSPOSE($BR$14:$BU$14)))} -> 0.044223365 | BT18: {=SQRT(MMULT($BR$14:$BU$14, MMULT('Part A'!$BL$6:$BO$9, TRANSPOSE($BR$14:$BU$14))))} -> 0.21029352 | BU18: {=SQRT(MMULT($BR$14:$BU$14, MMULT('Part A'!$BL$6:$BO$9, TRANSPOSE($BR$14:$BU$14))))} -> 0.21029352 | BV18: =($BR$18-'Part A'!$BI$7)/($BU$18) -> 1.2833626
B19: 45401 | C19: 6389.53 | D19: 6500.33 | E19: 6364.78 | F19: 6408.75 | G19: - | H19: =LN(F19/F18) -> 0.0032117055 | N19: =IFERROR(__xludf.DUMMYFUNCTION("""COMPUTED_VALUE"""),45401.64583333333) -> 45401.646 | O19: =IFERROR(__xludf.DUMMYFUNCTION("""COMPUTED_VALUE"""),1052.95) -> 1052.95 | P19: =IFERROR(__xludf.DUMMYFUNCTION("""COMPUTED_VALUE"""),1072.0) -> 1072 | Q19: =IFERROR(__xludf.DUMMYFUNCTION("""COMPUTED_VALUE"""),1048.1) -> 1048.1 | R19: =IFERROR(__xludf.DUMMYFUNCTION("""COMPUTED_VALUE"""),1067.25) -> 1067.25 | S19: =IFERROR(__xludf.DUMMYFUNCTION("""COMPUTED_VALUE"""),1.1284433E7) -> 11284433 | T19: =LN(R19/R18) -> 0.01111803 | Z19: =IFERROR(__xludf.DUMMYFUNCTION("""COMPUTED_VALUE"""),45401.64583333333) -> 45401.646 | AA19: =IFERROR(__xludf.DUMMYFUNCTION("""COMPUTED_VALUE"""),342.05) -> 342.05 | AB19: =IFERROR(__xludf.DUMMYFUNCTION("""COMPUTED_VALUE"""),359.5) -> 359.5 | AC19: =IFERROR(__xludf.DUMMYFUNCTION("""COMPUTED_VALUE"""),336.85) -> 336.85 | AD19: =IFERROR(__xludf.DUMMYFUNCTION("""COMPUTED_VALUE"""),351.4) -> 351.4 | AE19: =IFERROR(__xludf.DUMMYFUNCTION("""COMPUTED_VALUE"""),4.0376246E7) -> 40376246 | AF19: =LN(AD19/AD18) -> 0.020121403 | AL19: =IFERROR(__xludf.DUMMYFUNCTION("""COMPUTED_VALUE"""),45401.64583333333) -> 45401.646 | AM19: =IFERROR(__xludf.DUMMYFUNCTION("""COMPUTED_VALUE"""),3660.0) -> 3660 | AN19: =IFERROR(__xludf.DUMMYFUNCTION("""COMPUTED_VALUE"""),3761.15) -> 3761.15 | AO19: =IFERROR(__xludf.DUMMYFUNCTION("""COMPUTED_VALUE"""),3621.0) -> 3621 | AP19: =IFERROR(__xludf.DUMMYFUNCTION("""COMPUTED_VALUE"""),3751.3) -> 3751.3 | AQ19: =IFERROR(__xludf.DUMMYFUNCTION("""COMPUTED_VALUE"""),2256325.0) -> 2256325 | AR19: =LN(AP19/AP18) -> 0.019964451 | AX19: =IFERROR(__xludf.DUMMYFUNCTION("""COMPUTED_VALUE"""),45401.64583333333) -> 45401.646 | AY19: =IFERROR(__xludf.DUMMYFUNCTION("""COMPUTED_VALUE"""),418.0) -> 418 | AZ19: =IFERROR(__xludf.DUMMYFUNCTION("""COMPUTED_VALUE"""),426.25) -> 426.25 | BA19: =IFERROR(__xludf.DUMMYFUNCTION("""COMPUTED_VALUE"""),416.0) -> 416 | BB19: =IFERROR(__xludf.DUMMYFUNCTION("""COMPUTED_VALUE"""),424.75) -> 424.75 | BC19: =IFERROR(__xludf.DUMMYFUNCTION("""COMPUTED_VALUE"""),1.6582634E7) -> 16582634 | BD19: =LN(BB19/BB18) -> 0.0139879
B20: 45404 | C20: 6402.05 | D20: 6403.56 | E20: 6232.12 | F20: 6234.84 | G20: - | H20: =LN(F20/F19) -> -0.027511327 | N20: =IFERROR(__xludf.DUMMYFUNCTION("""COMPUTED_VALUE"""),45404.64583333333) -> 45404.646 | O20: =IFERROR(__xludf.DUMMYFUNCTION("""COMPUTED_VALUE"""),1078.8) -> 1078.8 | P20: =IFERROR(__xludf.DUMMYFUNCTION("""COMPUTED_VALUE"""),1088.7) -> 1088.7 | Q20: =IFERROR(__xludf.DUMMYFUNCTION("""COMPUTED_VALUE"""),1070.35) -> 1070.35 | R20: =IFERROR(__xludf.DUMMYFUNCTION("""COMPUTED_VALUE"""),1086.65) -> 1086.65 | S20: =IFERROR(__xludf.DUMMYFUNCTION("""COMPUTED_VALUE"""),1.0346714E7) -> 10346714 | T20: =LN(R20/R19) -> 0.018014323 | Z20: =IFERROR(__xludf.DUMMYFUNCTION("""COMPUTED_VALUE"""),45404.64583333333) -> 45404.646 | AA20: =IFERROR(__xludf.DUMMYFUNCTION("""COMPUTED_VALUE"""),352.0) -> 352 | AB20: =IFERROR(__xludf.DUMMYFUNCTION("""COMPUTED_VALUE"""),355.25) -> 355.25 | AC20: =IFERROR(__xludf.DUMMYFUNCTION("""COMPUTED_VALUE"""),341.65) -> 341.65 | AD20: =IFERROR(__xludf.DUMMYFUNCTION("""COMPUTED_VALUE"""),349.8) -> 349.8 | AE20: =IFERROR(__xludf.DUMMYFUNCTION("""COMPUTED_VALUE"""),1.8832015E7) -> 18832015 | AF20: =LN(AD20/AD19) -> -0.0045636132 | AL20: =IFERROR(__xludf.DUMMYFUNCTION("""COMPUTED_VALUE"""),45404.64583333333) -> 45404.646 | AM20: =IFERROR(__xludf.DUMMYFUNCTION("""COMPUTED_VALUE"""),3800.0) -> 3800 | AN20: =IFERROR(__xludf.DUMMYFUNCTION("""COMPUTED_VALUE"""),3810.0) -> 3810 | AO20: =IFERROR(__xludf.DUMMYFUNCTION("""COMPUTED_VALUE"""),3732.6) -> 3732.6 | AP20: =IFERROR(__xludf.DUMMYFUNCTION("""COMPUTED_VALUE"""),3785.5) -> 3785.5 | AQ20: =IFERROR(__xludf.DUMMYFUNCTION("""COMPUTED_VALUE"""),1337755.0) -> 1337755 | AR20: =LN(AP20/AP19) -> 0.009075532 | AX20: =IFERROR(__xludf.DUMMYFUNCTION("""COMPUTED_VALUE"""),45404.64583333333) -> 45404.646 | AY20: =IFERROR(__xludf.DUMMYFUNCTION("""COMPUTED_VALUE"""),427.0) -> 427 | AZ20: =IFERROR(__xludf.DUMMYFUNCTION("""COMPUTED_VALUE"""),427.6) -> 427.6 | BA20: =IFERROR(__xludf.DUMMYFUNCTION("""COMPUTED_VALUE"""),423.35) -> 423.35 | BB20: =IFERROR(__xludf.DUMMYFUNCTION("""COMPUTED_VALUE"""),425.3) -> 425.3 | BC20: =IFERROR(__xludf.DUMMYFUNCTION("""COMPUTED_VALUE"""),7112139.0) -> 7112139 | BD20: =LN(BB20/BB19) -> 0.0012940417
B21: 45405 | C21: 6237.19 | D21: 6258.85 | E21: 6139.58 | F21: 6215.31 | G21: - | H21: =LN(F21/F20) -> -0.0031373142 | N21: =IFERROR(__xludf.DUMMYFUNCTION("""COMPUTED_VALUE"""),45405.64583333333) -> 45405.646 | O21: =IFERROR(__xludf.DUMMYFUNCTION("""COMPUTED_VALUE"""),1100.0) -> 1100 | P21: =IFERROR(__xludf.DUMMYFUNCTION("""COMPUTED_VALUE"""),1100.0) -> 1100 | Q21: =IFERROR(__xludf.DUMMYFUNCTION("""COMPUTED_VALUE"""),1082.7) -> 1082.7 | R21: =IFERROR(__xludf.DUMMYFUNCTION("""COMPUTED_VALUE"""),1090.25) -> 1090.25 | S21: =IFERROR(__xludf.DUMMYFUNCTION("""COMPUTED_VALUE"""),9848215.0) -> 9848215 | T21: =LN(R21/R20) -> 0.0033074586 | Z21: =IFERROR(__xludf.DUMMYFUNCTION("""COMPUTED_VALUE"""),45405.64583333333) -> 45405.646 | AA21: =IFERROR(__xludf.DUMMYFUNCTION("""COMPUTED_VALUE"""),359.85) -> 359.85 | AB21: =IFERROR(__xludf.DUMMYFUNCTION("""COMPUTED_VALUE"""),366.55) -> 366.55 | AC21: =IFERROR(__xludf.DUMMYFUNCTION("""COMPUTED_VALUE"""),356.85) -> 356.85 | AD21: =IFERROR(__xludf.DUMMYFUNCTION("""COMPUTED_VALUE"""),359.5) -> 359.5 | AE21: =IFERROR(__xludf.DUMMYFUNCTION("""COMPUTED_VALUE"""),2.7662734E7) -> 27662734 | AF21: =LN(AD21/AD20) -> 0.027352615 | AL21: =IFERROR(__xludf.DUMMYFUNCTION("""COMPUTED_VALUE"""),45405.64583333333) -> 45405.646 | AM21: =IFERROR(__xludf.DUMMYFUNCTION("""COMPUTED_VALUE"""),3800.0) -> 3800 | AN21: =IFERROR(__xludf.DUMMYFUNCTION("""COMPUTED_VALUE"""),3831.85) -> 3831.85 | AO21: =IFERROR(__xludf.DUMMYFUNCTION("""COMPUTED_VALUE"""),3783.05) -> 3783.05 | AP21: =IFERROR(__xludf.DUMMYFUNCTION("""COMPUTED_VALUE"""),3795.7) -> 3795.7 | AQ21: =IFERROR(__xludf.DUMMYFUNCTION("""COMPUTED_VALUE"""),1321429.0) -> 1321429 | AR21: =LN(AP21/AP20) -> 0.0026908685 | AX21: =IFERROR(__xludf.DUMMYFUNCTION("""COMPUTED_VALUE"""),45405.64583333333) -> 45405.646 | AY21: =IFERROR(__xludf.DUMMYFUNCTION("""COMPUTED_VALUE"""),425.3) -> 425.3 | AZ21: =IFERROR(__xludf.DUMMYFUNCTION("""COMPUTED_VALUE"""),430.5) -> 430.5 | BA21: =IFERROR(__xludf.DUMMYFUNCTION("""COMPUTED_VALUE"""),425.1) -> 425.1 | BB21: =IFERROR(__xludf.DUMMYFUNCTION("""COMPUTED_VALUE"""),429.2) -> 429.2 | BC21: =IFERROR(__xludf.DUMMYFUNCTION("""COMPUTED_VALUE"""),1.2021404E7) -> 12021404 | BD21: =LN(BB21/BB20) -> 0.0091282085 | BQ21: OPTIMAL WEIGHT
B22: 45406 | C22: 6218.34 | D22: 6261.84 | E22: 6191.71 | F22: 6202.96 | G22: - | H22: =LN(F22/F21) -> -0.0019890056 | N22: =IFERROR(__xludf.DUMMYFUNCTION("""COMPUTED_VALUE"""),45406.64583333333) -> 45406.646 | O22: =IFERROR(__xludf.DUMMYFUNCTION("""COMPUTED_VALUE"""),1092.25) -> 1092.25 | P22: =IFERROR(__xludf.DUMMYFUNCTION("""COMPUTED_VALUE"""),1098.4) -> 1098.4 | Q22: =IFERROR(__xludf.DUMMYFUNCTION("""COMPUTED_VALUE"""),1089.0) -> 1089 | R22: =IFERROR(__xludf.DUMMYFUNCTION("""COMPUTED_VALUE"""),1096.75) -> 1096.75 | S22: =IFERROR(__xludf.DUMMYFUNCTION("""COMPUTED_VALUE"""),5461309.0) -> 5461309 | T22: =LN(R22/R21) -> 0.0059442333 | Z22: =IFERROR(__xludf.DUMMYFUNCTION("""COMPUTED_VALUE"""),45406.64583333333) -> 45406.646 | AA22: =IFERROR(__xludf.DUMMYFUNCTION("""COMPUTED_VALUE"""),363.2) -> 363.2 | AB22: =IFERROR(__xludf.DUMMYFUNCTION("""COMPUTED_VALUE"""),364.0) -> 364 | AC22: =IFERROR(__xludf.DUMMYFUNCTION("""COMPUTED_VALUE"""),346.85) -> 346.85 | AD22: =IFERROR(__xludf.DUMMYFUNCTION("""COMPUTED_VALUE"""),348.35) -> 348.35 | AE22: =IFERROR(__xludf.DUMMYFUNCTION("""COMPUTED_VALUE"""),2.0859429E7) -> 20859429 | AF22: =LN(AD22/AD21) -> -0.031506456 | AL22: =IFERROR(__xludf.DUMMYFUNCTION("""COMPUTED_VALUE"""),45406.64583333333) -> 45406.646 | AM22: =IFERROR(__xludf.DUMMYFUNCTION("""COMPUTED_VALUE"""),3826.1) -> 3826.1 | AN22: =IFERROR(__xludf.DUMMYFUNCTION("""COMPUTED_VALUE"""),4000.0) -> 4000 | AO22: =IFERROR(__xludf.DUMMYFUNCTION("""COMPUTED_VALUE"""),3812.5) -> 3812.5 | AP22: =IFERROR(__xludf.DUMMYFUNCTION("""COMPUTED_VALUE"""),3946.7) -> 3946.7 | AQ22: =IFERROR(__xludf.DUMMYFUNCTION("""COMPUTED_VALUE"""),4429158.0) -> 4429158 | AR22: =LN(AP22/AP21) -> 0.03901094 | AX22: =IFERROR(__xludf.DUMMYFUNCTION("""COMPUTED_VALUE"""),45406.64583333333) -> 45406.646 | AY22: =IFERROR(__xludf.DUMMYFUNCTION("""COMPUTED_VALUE"""),429.25) -> 429.25 | AZ22: =IFERROR(__xludf.DUMMYFUNCTION("""COMPUTED_VALUE"""),430.8) -> 430.8 | BA22: =IFERROR(__xludf.DUMMYFUNCTION("""COMPUTED_VALUE"""),428.3) -> 428.3 | BB22: =IFERROR(__xludf.DUMMYFUNCTION("""COMPUTED_VALUE"""),428.9) -> 428.9 | BC22: =IFERROR(__xludf.DUMMYFUNCTION("""COMPUTED_VALUE"""),5845170.0) -> 5845170 | BD22: =LN(BB22/BB21) -> -0.00069921923
B23: 45407 | C23: 6204.11 | D23: 6277.52 | E23: 6176.12 | F23: 6244.9 | G23: - | H23: =LN(F23/F22) -> 0.0067385332 | N23: =IFERROR(__xludf.DUMMYFUNCTION("""COMPUTED_VALUE"""),45407.64583333333) -> 45407.646 | O23: =IFERROR(__xludf.DUMMYFUNCTION("""COMPUTED_VALUE"""),1090.0) -> 1090 | P23: =IFERROR(__xludf.DUMMYFUNCTION("""COMPUTED_VALUE"""),1125.65) -> 1125.65 | Q23: =IFERROR(__xludf.DUMMYFUNCTION("""COMPUTED_VALUE"""),1089.95) -> 1089.95 | R23: =IFERROR(__xludf.DUMMYFUNCTION("""COMPUTED_VALUE"""),1113.75) -> 1113.75 | S23: =IFERROR(__xludf.DUMMYFUNCTION("""COMPUTED_VALUE"""),1.9905338E7) -> 19905338 | T23: =LN(R23/R22) -> 0.015381439 | Z23: =IFERROR(__xludf.DUMMYFUNCTION("""COMPUTED_VALUE"""),45407.64583333333) -> 45407.646 | AA23: =IFERROR(__xludf.DUMMYFUNCTION("""COMPUTED_VALUE"""),349.0) -> 349 | AB23: =IFERROR(__xludf.DUMMYFUNCTION("""COMPUTED_VALUE"""),356.8) -> 356.8 | AC23: =IFERROR(__xludf.DUMMYFUNCTION("""COMPUTED_VALUE"""),345.2) -> 345.2 | AD23: =IFERROR(__xludf.DUMMYFUNCTION("""COMPUTED_VALUE"""),351.65) -> 351.65 | AE23: =IFERROR(__xludf.DUMMYFUNCTION("""COMPUTED_VALUE"""),1.5367285E7) -> 15367285 | AF23: =LN(AD23/AD22) -> 0.0094286413 | AL23: =IFERROR(__xludf.DUMMYFUNCTION("""COMPUTED_VALUE"""),45407.64583333333) -> 45407.646 | AM23: =IFERROR(__xludf.DUMMYFUNCTION("""COMPUTED_VALUE"""),3958.6) -> 3958.6 | AN23: =IFERROR(__xludf.DUMMYFUNCTION("""COMPUTED_VALUE"""),4035.0) -> 4035 | AO23: =IFERROR(__xludf.DUMMYFUNCTION("""COMPUTED_VALUE"""),3939.0) -> 3939 | AP23: =IFERROR(__xludf.DUMMYFUNCTION("""COMPUTED_VALUE"""),4000.75) -> 4000.75 | AQ23: =IFERROR(__xludf.DUMMYFUNCTION("""COMPUTED_VALUE"""),2632613.0) -> 2632613 | AR23: =LN(AP23/AP22) -> 0.013602057 | AX23: =IFERROR(__xludf.DUMMYFUNCTION("""COMPUTED_VALUE"""),45407.64583333333) -> 45407.646 | AY23: =IFERROR(__xludf.DUMMYFUNCTION("""COMPUTED_VALUE"""),431.0) -> 431 | AZ23: =IFERROR(__xludf.DUMMYFUNCTION("""COMPUTED_VALUE"""),438.3) -> 438.3 | BA23: =IFERROR(__xludf.DUMMYFUNCTION("""COMPUTED_VALUE"""),429.0) -> 429 | BB23: =IFERROR(__xludf.DUMMYFUNCTION("""COMPUTED_VALUE"""),437.55) -> 437.55 | BC23: =IFERROR(__xludf.DUMMYFUNCTION("""COMPUTED_VALUE"""),2.9211997E7) -> 29211997 | BD23: =LN(BB23/BB22) -> 0.019967193 | BQ23: COMPANY | BR23: XAU/INR – Gold Price per Gram (INR) | BS23: ICICI Bank Ltd | BT23: Indus Towers Ltd | BU23: Hindustan Aeronautics Limited
B24: 45408 | C24: 6246.85 | D24: 6303.16 | E24: 6230.12 | F24: 6266.93 | G24: - | H24: =LN(F24/F23) -> 0.0035214709 | N24: =IFERROR(__xludf.DUMMYFUNCTION("""COMPUTED_VALUE"""),45408.64583333333) -> 45408.646 | O24: =IFERROR(__xludf.DUMMYFUNCTION("""COMPUTED_VALUE"""),1112.15) -> 1112.15 | P24: =IFERROR(__xludf.DUMMYFUNCTION("""COMPUTED_VALUE"""),1120.0) -> 1120 | Q24: =IFERROR(__xludf.DUMMYFUNCTION("""COMPUTED_VALUE"""),1102.75) -> 1102.75 | R24: =IFERROR(__xludf.DUMMYFUNCTION("""COMPUTED_VALUE"""),1107.9) -> 1107.9 | S24: =IFERROR(__xludf.DUMMYFUNCTION("""COMPUTED_VALUE"""),1.4190059E7) -> 14190059 | T24: =LN(R24/R23) -> -0.0052663683 | Z24: =IFERROR(__xludf.DUMMYFUNCTION("""COMPUTED_VALUE"""),45408.64583333333) -> 45408.646 | AA24: =IFERROR(__xludf.DUMMYFUNCTION("""COMPUTED_VALUE"""),352.0) -> 352 | AB24: =IFERROR(__xludf.DUMMYFUNCTION("""COMPUTED_VALUE"""),355.45) -> 355.45 | AC24: =IFERROR(__xludf.DUMMYFUNCTION("""COMPUTED_VALUE"""),348.6) -> 348.6 | AD24: =IFERROR(__xludf.DUMMYFUNCTION("""COMPUTED_VALUE"""),353.3) -> 353.3 | AE24: =IFERROR(__xludf.DUMMYFUNCTION("""COMPUTED_VALUE"""),1.1226725E7) -> 11226725 | AF24: =LN(AD24/AD23) -> 0.0046811916 | AL24: =IFERROR(__xludf.DUMMYFUNCTION("""COMPUTED_VALUE"""),45408.64583333333) -> 45408.646 | AM24: =IFERROR(__xludf.DUMMYFUNCTION("""COMPUTED_VALUE"""),4019.95) -> 4019.95 | AN24: =IFERROR(__xludf.DUMMYFUNCTION("""COMPUTED_VALUE"""),4039.95) -> 4039.95 | AO24: =IFERROR(__xludf.DUMMYFUNCTION("""COMPUTED_VALUE"""),3966.35) -> 3966.35 | AP24: =IFERROR(__xludf.DUMMYFUNCTION("""COMPUTED_VALUE"""),3984.4) -> 3984.4 | AQ24: =IFERROR(__xludf.DUMMYFUNCTION("""COMPUTED_VALUE"""),1432727.0) -> 1432727 | AR24: =LN(AP24/AP23) -> -0.0040951073 | AX24: =IFERROR(__xludf.DUMMYFUNCTION("""COMPUTED_VALUE"""),45408.64583333333) -> 45408.646 | AY24: =IFERROR(__xludf.DUMMYFUNCTION("""COMPUTED_VALUE"""),439.25) -> 439.25 | AZ24: =IFERROR(__xludf.DUMMYFUNCTION("""COMPUTED_VALUE"""),443.3) -> 443.3 | BA24: =IFERROR(__xludf.DUMMYFUNCTION("""COMPUTED_VALUE"""),436.4) -> 436.4 | BB24: =IFERROR(__xludf.DUMMYFUNCTION("""COMPUTED_VALUE"""),440.0) -> 440 | BC24: =IFERROR(__xludf.DUMMYFUNCTION("""COMPUTED_VALUE"""),1.4773975E7) -> 14773975 | BD24: =LN(BB24/BB23) -> 0.0055837419 | BQ24: Weights | BR24: 0.742 | BS24: 0.2577 | BT24: -0.0048 | BU24: 0.005
B25: 45411 | C25: 6271.52 | D25: 6297.52 | E25: 6218.78 | F25: 6262.07 | G25: - | H25: =LN(F25/F24) -> -0.00077580018 | N25: =IFERROR(__xludf.DUMMYFUNCTION("""COMPUTED_VALUE"""),45411.64583333333) -> 45411.646 | O25: =IFERROR(__xludf.DUMMYFUNCTION("""COMPUTED_VALUE"""),1108.0) -> 1108 | P25: =IFERROR(__xludf.DUMMYFUNCTION("""COMPUTED_VALUE"""),1163.45) -> 1163.45 | Q25: =IFERROR(__xludf.DUMMYFUNCTION("""COMPUTED_VALUE"""),1107.9) -> 1107.9 | R25: =IFERROR(__xludf.DUMMYFUNCTION("""COMPUTED_VALUE"""),1160.15) -> 1160.15 | S25: =IFERROR(__xludf.DUMMYFUNCTION("""COMPUTED_VALUE"""),2.8578063E7) -> 28578063 | T25: =LN(R25/R24) -> 0.046082976 | Z25: =IFERROR(__xludf.DUMMYFUNCTION("""COMPUTED_VALUE"""),45411.64583333333) -> 45411.646 | AA25: =IFERROR(__xludf.DUMMYFUNCTION("""COMPUTED_VALUE"""),352.0) -> 352 | AB25: =IFERROR(__xludf.DUMMYFUNCTION("""COMPUTED_VALUE"""),354.9) -> 354.9 | AC25: =IFERROR(__xludf.DUMMYFUNCTION("""COMPUTED_VALUE"""),343.85) -> 343.85 | AD25: =IFERROR(__xludf.DUMMYFUNCTION("""COMPUTED_VALUE"""),352.0) -> 352 | AE25: =IFERROR(__xludf.DUMMYFUNCTION("""COMPUTED_VALUE"""),1.412104E7) -> 14121040 | AF25: =LN(AD25/AD24) -> -0.0036863788 | AL25: =IFERROR(__xludf.DUMMYFUNCTION("""COMPUTED_VALUE"""),45411.64583333333) -> 45411.646 | AM25: =IFERROR(__xludf.DUMMYFUNCTION("""COMPUTED_VALUE"""),4006.35) -> 4006.35 | AN25: =IFERROR(__xludf.DUMMYFUNCTION("""COMPUTED_VALUE"""),4044.75) -> 4044.75 | AO25: =IFERROR(__xludf.DUMMYFUNCTION("""COMPUTED_VALUE"""),3975.3) -> 3975.3 | AP25: =IFERROR(__xludf.DUMMYFUNCTION("""COMPUTED_VALUE"""),4017.7) -> 4017.7 | AQ25: =IFERROR(__xludf.DUMMYFUNCTION("""COMPUTED_VALUE"""),1202126.0) -> 1202126 | AR25: =LN(AP25/AP24) -> 0.0083228633 | AX25: =IFERROR(__xludf.DUMMYFUNCTION("""COMPUTED_VALUE"""),45411.64583333333) -> 45411.646 | AY25: =IFERROR(__xludf.DUMMYFUNCTION("""COMPUTED_VALUE"""),442.0) -> 442 | AZ25: =IFERROR(__xludf.DUMMYFUNCTION("""COMPUTED_VALUE"""),442.45) -> 442.45 | BA25: =IFERROR(__xludf.DUMMYFUNCTION("""COMPUTED_VALUE"""),434.6) -> 434.6 | BB25: =IFERROR(__xludf.DUMMYFUNCTION("""COMPUTED_VALUE"""),438.2) -> 438.2 | BC25: =IFERROR(__xludf.DUMMYFUNCTION("""COMPUTED_VALUE"""),1.1627882E7) -> 11627882 | BD25: =LN(BB25/BB24) -> -0.0040992998 | BQ25: Annual Return | BR25: =(1 + 'Part A'!$J$7)^252 - 1 -> 0.45359052 | BS25: =(1 + 'Part A'!$V$7)^252 - 1 -> 0.28104654 | BT25: =(1 + 'Part A'!$AH$7)^252 - 1 -> 0.27857535 | BU25: =(1 + 'Part A'!$AT$7)^252 - 1 -> 0.30071899
B26: 45412 | C26: 6264.34 | D26: 6269.02 | E26: 6131.71 | F26: 6132.56 | G26: - | H26: =LN(F26/F25) -> -0.02089852 | N26: =IFERROR(__xludf.DUMMYFUNCTION("""COMPUTED_VALUE"""),45412.64583333333) -> 45412.646 | O26: =IFERROR(__xludf.DUMMYFUNCTION("""COMPUTED_VALUE"""),1159.95) -> 1159.95 | P26: =IFERROR(__xludf.DUMMYFUNCTION("""COMPUTED_VALUE"""),1169.55) -> 1169.55 | Q26: =IFERROR(__xludf.DUMMYFUNCTION("""COMPUTED_VALUE"""),1146.75) -> 1146.75 | R26: =IFERROR(__xludf.DUMMYFUNCTION("""COMPUTED_VALUE"""),1150.4) -> 1150.4 | S26: =IFERROR(__xludf.DUMMYFUNCTION("""COMPUTED_VALUE"""),2.9568491E7) -> 29568491 | T26: =LN(R26/R25) -> -0.0084395991 | Z26: =IFERROR(__xludf.DUMMYFUNCTION("""COMPUTED_VALUE"""),45412.64583333333) -> 45412.646 | AA26: =IFERROR(__xludf.DUMMYFUNCTION("""COMPUTED_VALUE"""),353.0) -> 353 | AB26: =IFERROR(__xludf.DUMMYFUNCTION("""COMPUTED_VALUE"""),360.5) -> 360.5 | AC26: =IFERROR(__xludf.DUMMYFUNCTION("""COMPUTED_VALUE"""),352.55) -> 352.55 | AD26: =IFERROR(__xludf.DUMMYFUNCTION("""COMPUTED_VALUE"""),354.8) -> 354.8 | AE26: =IFERROR(__xludf.DUMMYFUNCTION("""COMPUTED_VALUE"""),1.5377757E7) -> 15377757 | AF26: =LN(AD26/AD25) -> 0.0079230748 | AL26: =IFERROR(__xludf.DUMMYFUNCTION("""COMPUTED_VALUE"""),45412.64583333333) -> 45412.646 | AM26: =IFERROR(__xludf.DUMMYFUNCTION("""COMPUTED_VALUE"""),4035.35) -> 4035.35 | AN26: =IFERROR(__xludf.DUMMYFUNCTION("""COMPUTED_VALUE"""),4035.85) -> 4035.85 | AO26: =IFERROR(__xludf.DUMMYFUNCTION("""COMPUTED_VALUE"""),3930.0) -> 3930 | AP26: =IFERROR(__xludf.DUMMYFUNCTION("""COMPUTED_VALUE"""),3939.35) -> 3939.35 | AQ26: =IFERROR(__xludf.DUMMYFUNCTION("""COMPUTED_VALUE"""),2054258.0) -> 2054258 | AR26: =LN(AP26/AP25) -> -0.019693865 | AX26: =IFERROR(__xludf.DUMMYFUNCTION("""COMPUTED_VALUE"""),45412.64583333333) -> 45412.646 | AY26: =IFERROR(__xludf.DUMMYFUNCTION("""COMPUTED_VALUE"""),439.95) -> 439.95 | AZ26: =IFERROR(__xludf.DUMMYFUNCTION("""COMPUTED_VALUE"""),440.5) -> 440.5 | BA26: =IFERROR(__xludf.DUMMYFUNCTION("""COMPUTED_VALUE"""),435.1) -> 435.1 | BB26: =IFERROR(__xludf.DUMMYFUNCTION("""COMPUTED_VALUE"""),435.65) -> 435.65 | BC26: =IFERROR(__xludf.DUMMYFUNCTION("""COMPUTED_VALUE"""),1.2064043E7) -> 12064043 | BD26: =LN(BB26/BB25) -> -0.0058362585 | BQ26: Standard Deviation | BR26: =STDEV('Part A'!$H$7:$H$272)*15.8745078664 -> 0.16999944 | BS26: =STDEV('Part A'!$T$7:$T$272)*15.8745078664 -> 0.20830139 | BT26: =STDEV('Part A'!$AF$7:$AF$272)*15.8745078664 -> 0.37283891 | BU26: =STDEV('Part A'!$AR$7:$AR$272)*15.8745078664 -> 0.43847136
B27: 45414 | C27: 6223.71 | D27: 6241.52 | E27: 6132.56 | F27: 6176.34 | G27: - | H27: =LN(F27/F26) -> 0.007113582 | N27: =IFERROR(__xludf.DUMMYFUNCTION("""COMPUTED_VALUE"""),45414.64583333333) -> 45414.646 | O27: =IFERROR(__xludf.DUMMYFUNCTION("""COMPUTED_VALUE"""),1143.0) -> 1143 | P27: =IFERROR(__xludf.DUMMYFUNCTION("""COMPUTED_VALUE"""),1155.5) -> 1155.5 | Q27: =IFERROR(__xludf.DUMMYFUNCTION("""COMPUTED_VALUE"""),1133.25) -> 1133.25 | R27: =IFERROR(__xludf.DUMMYFUNCTION("""COMPUTED_VALUE"""),1139.45) -> 1139.45 | S27: =IFERROR(__xludf.DUMMYFUNCTION("""COMPUTED_VALUE"""),2.5118334E7) -> 25118334 | T27: =LN(R27/R26) -> -0.0095640181 | Z27: =IFERROR(__xludf.DUMMYFUNCTION("""COMPUTED_VALUE"""),45414.64583333333) -> 45414.646 | AA27: =IFERROR(__xludf.DUMMYFUNCTION("""COMPUTED_VALUE"""),359.0) -> 359 | AB27: =IFERROR(__xludf.DUMMYFUNCTION("""COMPUTED_VALUE"""),363.6) -> 363.6 | AC27: =IFERROR(__xludf.DUMMYFUNCTION("""COMPUTED_VALUE"""),348.45) -> 348.45 | AD27: =IFERROR(__xludf.DUMMYFUNCTION("""COMPUTED_VALUE"""),352.95) -> 352.95 | AE27: =IFERROR(__xludf.DUMMYFUNCTION("""COMPUTED_VALUE"""),1.9136966E7) -> 19136966 | AF27: =LN(AD27/AD26) -> -0.0052278466 | AL27: =IFERROR(__xludf.DUMMYFUNCTION("""COMPUTED_VALUE"""),45414.64583333333) -> 45414.646 | AM27: =IFERROR(__xludf.DUMMYFUNCTION("""COMPUTED_VALUE"""),3942.0) -> 3942 | AN27: =IFERROR(__xludf.DUMMYFUNCTION("""COMPUTED_VALUE"""),3973.1) -> 3973.1 | AO27: =IFERROR(__xludf.DUMMYFUNCTION("""COMPUTED_VALUE"""),3931.4) -> 3931.4 | AP27: =IFERROR(__xludf.DUMMYFUNCTION("""COMPUTED_VALUE"""),3947.2) -> 3947.2 | AQ27: =IFERROR(__xludf.DUMMYFUNCTION("""COMPUTED_VALUE"""),1008325.0) -> 1008325 | AR27: =LN(AP27/AP26) -> 0.0019907317 | AX27: =IFERROR(__xludf.DUMMYFUNCTION("""COMPUTED_VALUE"""),45414.64583333333) -> 45414.646 | AY27: =IFERROR(__xludf.DUMMYFUNCTION("""COMPUTED_VALUE"""),436.0) -> 436 | AZ27: =IFERROR(__xludf.DUMMYFUNCTION("""COMPUTED_VALUE"""),442.6) -> 442.6 | BA27: =IFERROR(__xludf.DUMMYFUNCTION("""COMPUTED_VALUE"""),434.85) -> 434.85 | BB27: =IFERROR(__xludf.DUMMYFUNCTION("""COMPUTED_VALUE"""),439.0) -> 439 | BC27: =IFERROR(__xludf.DUMMYFUNCTION("""COMPUTED_VALUE"""),2.3228909E7) -> 23228909 | BD27: =LN(BB27/BB26) -> 0.0076602444 | BQ27: PORTFOLIO | BR27: RETURN | BS27: VARIANCE | BT27: STANDARD DEVIATION | BU27: STANDARD DEVIATION(%) | BV27: SHARPE RATIO
B28: 45415 | C28: 6181.12 | D28: 6221.12 | E28: 6107.12 | F28: 6171.38 | G28: - | H28: =LN(F28/F27) -> -0.00080338723 | N28: =IFERROR(__xludf.DUMMYFUNCTION("""COMPUTED_VALUE"""),45415.64583333333) -> 45415.646 | O28: =IFERROR(__xludf.DUMMYFUNCTION("""COMPUTED_VALUE"""),1141.3) -> 1141.3 | P28: =IFERROR(__xludf.DUMMYFUNCTION("""COMPUTED_VALUE"""),1157.4) -> 1157.4 | Q28: =IFERROR(__xludf.DUMMYFUNCTION("""COMPUTED_VALUE"""),1135.45) -> 1135.45 | R28: =IFERROR(__xludf.DUMMYFUNCTION("""COMPUTED_VALUE"""),1142.05) -> 1142.05 | S28: =IFERROR(__xludf.DUMMYFUNCTION("""COMPUTED_VALUE"""),1.9933604E7) -> 19933604 | T28: =LN(R28/R27) -> 0.0022792033 | Z28: =IFERROR(__xludf.DUMMYFUNCTION("""COMPUTED_VALUE"""),45415.64583333333) -> 45415.646 | AA28: =IFERROR(__xludf.DUMMYFUNCTION("""COMPUTED_VALUE"""),353.5) -> 353.5 | AB28: =IFERROR(__xludf.DUMMYFUNCTION("""COMPUTED_VALUE"""),358.35) -> 358.35 | AC28: =IFERROR(__xludf.DUMMYFUNCTION("""COMPUTED_VALUE"""),347.65) -> 347.65 | AD28: =IFERROR(__xludf.DUMMYFUNCTION("""COMPUTED_VALUE"""),350.95) -> 350.95 | AE28: =IFERROR(__xludf.DUMMYFUNCTION("""COMPUTED_VALUE"""),1.4060465E7) -> 14060465 | AF28: =LN(AD28/AD27) -> -0.0056826407 | AL28: =IFERROR(__xludf.DUMMYFUNCTION("""COMPUTED_VALUE"""),45415.64583333333) -> 45415.646 | AM28: =IFERROR(__xludf.DUMMYFUNCTION("""COMPUTED_VALUE"""),3952.25) -> 3952.25 | AN28: =IFERROR(__xludf.DUMMYFUNCTION("""COMPUTED_VALUE"""),3967.0) -> 3967 | AO28: =IFERROR(__xludf.DUMMYFUNCTION("""COMPUTED_VALUE"""),3880.0) -> 3880 | AP28: =IFERROR(__xludf.DUMMYFUNCTION("""COMPUTED_VALUE"""),3920.2) -> 3920.2 | AQ28: =IFERROR(__xludf.DUMMYFUNCTION("""COMPUTED_VALUE"""),1180369.0) -> 1180369 | AR28: =LN(AP28/AP27) -> -0.0068637939 | AX28: =IFERROR(__xludf.DUMMYFUNCTION("""COMPUTED_VALUE"""),45415.64583333333) -> 45415.646 | AY28: =IFERROR(__xludf.DUMMYFUNCTION("""COMPUTED_VALUE"""),440.05) -> 440.05 | AZ28: =IFERROR(__xludf.DUMMYFUNCTION("""COMPUTED_VALUE"""),440.05) -> 440.05 | BA28: =IFERROR(__xludf.DUMMYFUNCTION("""COMPUTED_VALUE"""),431.35) -> 431.35 | BB28: =IFERROR(__xludf.DUMMYFUNCTION("""COMPUTED_VALUE"""),436.45) -> 436.45 | BC28: =IFERROR(__xludf.DUMMYFUNCTION("""COMPUTED_VALUE"""),2.2904276E7) -> 22904276 | BD28: =LN(BB28/BB27) -> -0.0058255919 | BQ28: VALUES | BR28: {=MMULT(BR24:BU24, TRANSPOSE(BR25:BU25))} -> 0.40915629 | BS28: {=MMULT(BR24:BU24, MMULT('Part A'!$BL$6:$BO$9, TRANSPOSE(BR24:BU24)))} -> 0.019290388 | BT28: =SQRT(BS28) -> 0.13888984 | BU28: =SQRT(BS28) -> 0.13888984 | BV28: =(BR28-'Part A'!BI7)/(BU28) -> 2.523988
B29: 45418 | C29: 6171.94 | D29: 6260.67 | E29: 6143.12 | F29: 6235.38 | G29: - | H29: =LN(F29/F28) -> 0.010317048 | N29: =IFERROR(__xludf.DUMMYFUNCTION("""COMPUTED_VALUE"""),45418.64583333333) -> 45418.646 | O29: =IFERROR(__xludf.DUMMYFUNCTION("""COMPUTED_VALUE"""),1141.55) -> 1141.55 | P29: =IFERROR(__xludf.DUMMYFUNCTION("""COMPUTED_VALUE"""),1158.45) -> 1158.45 | Q29: =IFERROR(__xludf.DUMMYFUNCTION("""COMPUTED_VALUE"""),1138.1) -> 1138.1 | R29: =IFERROR(__xludf.DUMMYFUNCTION("""COMPUTED_VALUE"""),1146.3) -> 1146.3 | S29: =IFERROR(__xludf.DUMMYFUNCTION("""COMPUTED_VALUE"""),1.4970524E7) -> 14970524 | T29: =LN(R29/R28) -> 0.003714471 | Z29: =IFERROR(__xludf.DUMMYFUNCTION("""COMPUTED_VALUE"""),45418.64583333333) -> 45418.646 | AA29: =IFERROR(__xludf.DUMMYFUNCTION("""COMPUTED_VALUE"""),353.8) -> 353.8 | AB29: =IFERROR(__xludf.DUMMYFUNCTION("""COMPUTED_VALUE"""),356.0) -> 356 | AC29: =IFERROR(__xludf.DUMMYFUNCTION("""COMPUTED_VALUE"""),345.45) -> 345.45 | AD29: =IFERROR(__xludf.DUMMYFUNCTION("""COMPUTED_VALUE"""),351.15) -> 351.15 | AE29: =IFERROR(__xludf.DUMMYFUNCTION("""COMPUTED_VALUE"""),7702154.0) -> 7702154 | AF29: =LN(AD29/AD28) -> 0.00056971943 | AL29: =IFERROR(__xludf.DUMMYFUNCTION("""COMPUTED_VALUE"""),45418.64583333333) -> 45418.646 | AM29: =IFERROR(__xludf.DUMMYFUNCTION("""COMPUTED_VALUE"""),3936.0) -> 3936 | AN29: =IFERROR(__xludf.DUMMYFUNCTION("""COMPUTED_VALUE"""),3938.4) -> 3938.4 | AO29: =IFERROR(__xludf.DUMMYFUNCTION("""COMPUTED_VALUE"""),3785.05) -> 3785.05 | AP29: =IFERROR(__xludf.DUMMYFUNCTION("""COMPUTED_VALUE"""),3816.4) -> 3816.4 | AQ29: =IFERROR(__xludf.DUMMYFUNCTION("""COMPUTED_VALUE"""),1613143.0) -> 1613143 | AR29: =LN(AP29/AP28) -> -0.026835103 | AX29: =IFERROR(__xludf.DUMMYFUNCTION("""COMPUTED_VALUE"""),45418.64583333333) -> 45418.646 | AY29: =IFERROR(__xludf.DUMMYFUNCTION("""COMPUTED_VALUE"""),438.0) -> 438 | AZ29: =IFERROR(__xludf.DUMMYFUNCTION("""COMPUTED_VALUE"""),440.45) -> 440.45 | BA29: =IFERROR(__xludf.DUMMYFUNCTION("""COMPUTED_VALUE"""),433.35) -> 433.35 | BB29: =IFERROR(__xludf.DUMMYFUNCTION("""COMPUTED_VALUE"""),434.75) -> 434.75 | BC29: =IFERROR(__xludf.DUMMYFUNCTION("""COMPUTED_VALUE"""),1.0355056E7) -> 10355056 | BD29: =LN(BB29/BB28) -> -0.0039026679
B30: 45419 | C30: 6237.71 | D30: 6252.52 | E30: 6200.12 | F30: 6209.12 | G30: - | H30: =LN(F30/F29) -> -0.0042203446 | N30: =IFERROR(__xludf.DUMMYFUNCTION("""COMPUTED_VALUE"""),45419.64583333333) -> 45419.646 | O30: =IFERROR(__xludf.DUMMYFUNCTION("""COMPUTED_VALUE"""),1147.95) -> 1147.95 | P30: =IFERROR(__xludf.DUMMYFUNCTION("""COMPUTED_VALUE"""),1152.75) -> 1152.75 | Q30: =IFERROR(__xludf.DUMMYFUNCTION("""COMPUTED_VALUE"""),1126.3) -> 1126.3 | R30: =IFERROR(__xludf.DUMMYFUNCTION("""COMPUTED_VALUE"""),1131.9) -> 1131.9 | S30: =IFERROR(__xludf.DUMMYFUNCTION("""COMPUTED_VALUE"""),1.5097728E7) -> 15097728 | T30: =LN(R30/R29) -> -0.012641727 | Z30: =IFERROR(__xludf.DUMMYFUNCTION("""COMPUTED_VALUE"""),45419.64583333333) -> 45419.646 | AA30: =IFERROR(__xludf.DUMMYFUNCTION("""COMPUTED_VALUE"""),347.0) -> 347 | AB30: =IFERROR(__xludf.DUMMYFUNCTION("""COMPUTED_VALUE"""),348.8) -> 348.8 | AC30: =IFERROR(__xludf.DUMMYFUNCTION("""COMPUTED_VALUE"""),335.5) -> 335.5 | AD30: =IFERROR(__xludf.DUMMYFUNCTION("""COMPUTED_VALUE"""),338.2) -> 338.2 | AE30: =IFERROR(__xludf.DUMMYFUNCTION("""COMPUTED_VALUE"""),1.2770435E7) -> 12770435 | AF30: =LN(AD30/AD29) -> -0.037576046 | AL30: =IFERROR(__xludf.DUMMYFUNCTION("""COMPUTED_VALUE"""),45419.64583333333) -> 45419.646 | AM30: =IFERROR(__xludf.DUMMYFUNCTION("""COMPUTED_VALUE"""),3815.45) -> 3815.45 | AN30: =IFERROR(__xludf.DUMMYFUNCTION("""COMPUTED_VALUE"""),3839.0) -> 3839 | AO30: =IFERROR(__xludf.DUMMYFUNCTION("""COMPUTED_VALUE"""),3693.4) -> 3693.4 | AP30: =IFERROR(__xludf.DUMMYFUNCTION("""COMPUTED_VALUE"""),3715.0) -> 3715 | AQ30: =IFERROR(__xludf.DUMMYFUNCTION("""COMPUTED_VALUE"""),1975562.0) -> 1975562 | AR30: =LN(AP30/AP29) -> -0.026928892 | AX30: =IFERROR(__xludf.DUMMYFUNCTION("""COMPUTED_VALUE"""),45419.64583333333) -> 45419.646 | AY30: =IFERROR(__xludf.DUMMYFUNCTION("""COMPUTED_VALUE"""),436.9) -> 436.9 | AZ30: =IFERROR(__xludf.DUMMYFUNCTION("""COMPUTED_VALUE"""),446.0) -> 446 | BA30: =IFERROR(__xludf.DUMMYFUNCTION("""COMPUTED_VALUE"""),435.2) -> 435.2 | BB30: =IFERROR(__xludf.DUMMYFUNCTION("""COMPUTED_VALUE"""),440.35) -> 440.35 | BC30: =IFERROR(__xludf.DUMMYFUNCTION("""COMPUTED_VALUE"""),2.5968921E7) -> 25968921 | BD30: =LN(BB30/BB29) -> 0.012798712
B31: 45420 | C31: 6209.71 | D31: 6231.12 | E31: 6184.12 | F31: 6192.12 | G31: - | H31: =LN(F31/F30) -> -0.002741663 | N31: =IFERROR(__xludf.DUMMYFUNCTION("""COMPUTED_VALUE"""),45420.64583333333) -> 45420.646 | O31: =IFERROR(__xludf.DUMMYFUNCTION("""COMPUTED_VALUE"""),1126.55) -> 1126.55 | P31: =IFERROR(__xludf.DUMMYFUNCTION("""COMPUTED_VALUE"""),1132.0) -> 1132 | Q31: =IFERROR(__xludf.DUMMYFUNCTION("""COMPUTED_VALUE"""),1116.05) -> 1116.05 | R31: =IFERROR(__xludf.DUMMYFUNCTION("""COMPUTED_VALUE"""),1123.0) -> 1123 | S31: =IFERROR(__xludf.DUMMYFUNCTION("""COMPUTED_VALUE"""),1.991309E7) -> 19913090 | T31: =LN(R31/R30) -> -0.0078939609 | Z31: =IFERROR(__xludf.DUMMYFUNCTION("""COMPUTED_VALUE"""),45420.64583333333) -> 45420.646 | AA31: =IFERROR(__xludf.DUMMYFUNCTION("""COMPUTED_VALUE"""),336.0) -> 336 | AB31: =IFERROR(__xludf.DUMMYFUNCTION("""COMPUTED_VALUE"""),342.15) -> 342.15 | AC31: =IFERROR(__xludf.DUMMYFUNCTION("""COMPUTED_VALUE"""),333.75) -> 333.75 | AD31: =IFERROR(__xludf.DUMMYFUNCTION("""COMPUTED_VALUE"""),337.3) -> 337.3 | AE31: =IFERROR(__xludf.DUMMYFUNCTION("""COMPUTED_VALUE"""),9756671.0) -> 9756671 | AF31: =LN(AD31/AD30) -> -0.0026646944 | AL31: =IFERROR(__xludf.DUMMYFUNCTION("""COMPUTED_VALUE"""),45420.64583333333) -> 45420.646 | AM31: =IFERROR(__xludf.DUMMYFUNCTION("""COMPUTED_VALUE"""),3703.0) -> 3703 | AN31: =IFERROR(__xludf.DUMMYFUNCTION("""COMPUTED_VALUE"""),3883.2) -> 3883.2 | AO31: =IFERROR(__xludf.DUMMYFUNCTION("""COMPUTED_VALUE"""),3671.0) -> 3671 | AP31: =IFERROR(__xludf.DUMMYFUNCTION("""COMPUTED_VALUE"""),3856.5) -> 3856.5 | AQ31: =IFERROR(__xludf.DUMMYFUNCTION("""COMPUTED_VALUE"""),1993745.0) -> 1993745 | AR31: =LN(AP31/AP30) -> 0.037381358 | AX31: =IFERROR(__xludf.DUMMYFUNCTION("""COMPUTED_VALUE"""),45420.64583333333) -> 45420.646 | AY31: =IFERROR(__xludf.DUMMYFUNCTION("""COMPUTED_VALUE"""),441.25) -> 441.25 | AZ31: =IFERROR(__xludf.DUMMYFUNCTION("""COMPUTED_VALUE"""),444.7) -> 444.7 | BA31: =IFERROR(__xludf.DUMMYFUNCTION("""COMPUTED_VALUE"""),438.2) -> 438.2 | BB31: =IFERROR(__xludf.DUMMYFUNCTION("""COMPUTED_VALUE"""),441.0) -> 441 | BC31: =IFERROR(__xludf.DUMMYFUNCTION("""COMPUTED_VALUE"""),1.0511646E7) -> 10511646 | BD31: =LN(BB31/BB30) -> 0.0014750102
B32: 45421 | C32: 6194.71 | D32: 6297.52 | E32: 6190.78 | F32: 6293.71 | G32: - | H32: =LN(F32/F31) -> 0.016273206 | N32: =IFERROR(__xludf.DUMMYFUNCTION("""COMPUTED_VALUE"""),45421.64583333333) -> 45421.646 | O32: =IFERROR(__xludf.DUMMYFUNCTION("""COMPUTED_VALUE"""),1120.55) -> 1120.55 | P32: =IFERROR(__xludf.DUMMYFUNCTION("""COMPUTED_VALUE"""),1128.85) -> 1128.85 | Q32: =IFERROR(__xludf.DUMMYFUNCTION("""COMPUTED_VALUE"""),1110.0) -> 1110 | R32: =IFERROR(__xludf.DUMMYFUNCTION("""COMPUTED_VALUE"""),1115.7) -> 1115.7 | S32: =IFERROR(__xludf.DUMMYFUNCTION("""COMPUTED_VALUE"""),1.2229853E7) -> 12229853 | T32: =LN(R32/R31) -> -0.0065216651 | Z32: =IFERROR(__xludf.DUMMYFUNCTION("""COMPUTED_VALUE"""),45421.64583333333) -> 45421.646 | AA32: =IFERROR(__xludf.DUMMYFUNCTION("""COMPUTED_VALUE"""),338.3) -> 338.3 | AB32: =IFERROR(__xludf.DUMMYFUNCTION("""COMPUTED_VALUE"""),341.35) -> 341.35 | AC32: =IFERROR(__xludf.DUMMYFUNCTION("""COMPUTED_VALUE"""),325.85) -> 325.85 | AD32: =IFERROR(__xludf.DUMMYFUNCTION("""COMPUTED_VALUE"""),327.85) -> 327.85 | AE32: =IFERROR(__xludf.DUMMYFUNCTION("""COMPUTED_VALUE"""),6656525.0) -> 6656525 | AF32: =LN(AD32/AD31) -> -0.028416555 | AL32: =IFERROR(__xludf.DUMMYFUNCTION("""COMPUTED_VALUE"""),45421.64583333333) -> 45421.646 | AM32: =IFERROR(__xludf.DUMMYFUNCTION("""COMPUTED_VALUE"""),3895.8) -> 3895.8 | AN32: =IFERROR(__xludf.DUMMYFUNCTION("""COMPUTED_VALUE"""),3954.0) -> 3954 | AO32: =IFERROR(__xludf.DUMMYFUNCTION("""COMPUTED_VALUE"""),3820.45) -> 3820.45 | AP32: =IFERROR(__xludf.DUMMYFUNCTION("""COMPUTED_VALUE"""),3846.65) -> 3846.65 | AQ32: =IFERROR(__xludf.DUMMYFUNCTION("""COMPUTED_VALUE"""),2335375.0) -> 2335375 | AR32: =LN(AP32/AP31) -> -0.0025573967 | AX32: =IFERROR(__xludf.DUMMYFUNCTION("""COMPUTED_VALUE"""),45421.64583333333) -> 45421.646 | AY32: =IFERROR(__xludf.DUMMYFUNCTION("""COMPUTED_VALUE"""),440.05) -> 440.05 | AZ32: =IFERROR(__xludf.DUMMYFUNCTION("""COMPUTED_VALUE"""),441.5) -> 441.5 | BA32: =IFERROR(__xludf.DUMMYFUNCTION("""COMPUTED_VALUE"""),423.35) -> 423.35 | BB32: =IFERROR(__xludf.DUMMYFUNCTION("""COMPUTED_VALUE"""),425.1) -> 425.1 | BC32: =IFERROR(__xludf.DUMMYFUNCTION("""COMPUTED_VALUE"""),2.3412609E7) -> 23412609 | BD32: =LN(BB32/BB31) -> -0.03672044
B33: 45422 | C33: 6295.12 | D33: 6385.52 | E33: 6292.12 | F33: 6338.78 | G33: - | H33: =LN(F33/F32) -> 0.007135599 | N33: =IFERROR(__xludf.DUMMYFUNCTION("""COMPUTED_VALUE"""),45422.64583333333) -> 45422.646 | O33: =IFERROR(__xludf.DUMMYFUNCTION("""COMPUTED_VALUE"""),1118.0) -> 1118 | P33: =IFERROR(__xludf.DUMMYFUNCTION("""COMPUTED_VALUE"""),1128.9) -> 1128.9 | Q33: =IFERROR(__xludf.DUMMYFUNCTION("""COMPUTED_VALUE"""),1112.05) -> 1112.05 | R33: =IFERROR(__xludf.DUMMYFUNCTION("""COMPUTED_VALUE"""),1117.05) -> 1117.05 | S33: =IFERROR(__xludf.DUMMYFUNCTION("""COMPUTED_VALUE"""),8573656.0) -> 8573656 | T33: =LN(R33/R32) -> 0.0012092712 | Z33: =IFERROR(__xludf.DUMMYFUNCTION("""COMPUTED_VALUE"""),45422.64583333333) -> 45422.646 | AA33: =IFERROR(__xludf.DUMMYFUNCTION("""COMPUTED_VALUE"""),324.85) -> 324.85 | AB33: =IFERROR(__xludf.DUMMYFUNCTION("""COMPUTED_VALUE"""),332.75) -> 332.75 | AC33: =IFERROR(__xludf.DUMMYFUNCTION("""COMPUTED_VALUE"""),322.65) -> 322.65 | AD33: =IFERROR(__xludf.DUMMYFUNCTION("""COMPUTED_VALUE"""),330.55) -> 330.55 | AE33: =IFERROR(__xludf.DUMMYFUNCTION("""COMPUTED_VALUE"""),6438304.0) -> 6438304 | AF33: =LN(AD33/AD32) -> 0.0082017471 | AL33: =IFERROR(__xludf.DUMMYFUNCTION("""COMPUTED_VALUE"""),45422.64583333333) -> 45422.646 | AM33: =IFERROR(__xludf.DUMMYFUNCTION("""COMPUTED_VALUE"""),3860.0) -> 3860 | AN33: =IFERROR(__xludf.DUMMYFUNCTION("""COMPUTED_VALUE"""),3907.7) -> 3907.7 | AO33: =IFERROR(__xludf.DUMMYFUNCTION("""COMPUTED_VALUE"""),3820.65) -> 3820.65 | AP33: =IFERROR(__xludf.DUMMYFUNCTION("""COMPUTED_VALUE"""),3872.9) -> 3872.9 | AQ33: =IFERROR(__xludf.DUMMYFUNCTION("""COMPUTED_VALUE"""),1462534.0) -> 1462534 | AR33: =LN(AP33/AP32) -> 0.0068009408 | AX33: =IFERROR(__xludf.DUMMYFUNCTION("""COMPUTED_VALUE"""),45422.64583333333) -> 45422.646 | AY33: =IFERROR(__xludf.DUMMYFUNCTION("""COMPUTED_VALUE"""),426.5) -> 426.5 | AZ33: =IFERROR(__xludf.DUMMYFUNCTION("""COMPUTED_VALUE"""),436.35) -> 436.35 | BA33: =IFERROR(__xludf.DUMMYFUNCTION("""COMPUTED_VALUE"""),426.5) -> 426.5 | BB33: =IFERROR(__xludf.DUMMYFUNCTION("""COMPUTED_VALUE"""),433.35) -> 433.35 | BC33: =IFERROR(__xludf.DUMMYFUNCTION("""COMPUTED_VALUE"""),1.3985963E7) -> 13985963 | BD33: =LN(BB33/BB32) -> 0.01922128
B34: 45425 | C34: 6346.12 | D34: 6352.12 | E34: 6261.84 | F34: 6267.71 | G34: - | H34: =LN(F34/F33) -> -0.011275264 | N34: =IFERROR(__xludf.DUMMYFUNCTION("""COMPUTED_VALUE"""),45425.64583333333) -> 45425.646 | O34: =IFERROR(__xludf.DUMMYFUNCTION("""COMPUTED_VALUE"""),1112.4) -> 1112.4 | P34: =IFERROR(__xludf.DUMMYFUNCTION("""COMPUTED_VALUE"""),1130.65) -> 1130.65 | Q34: =IFERROR(__xludf.DUMMYFUNCTION("""COMPUTED_VALUE"""),1106.7) -> 1106.7 | R34: =IFERROR(__xludf.DUMMYFUNCTION("""COMPUTED_VALUE"""),1128.0) -> 1128 | S34: =IFERROR(__xludf.DUMMYFUNCTION("""COMPUTED_VALUE"""),9707983.0) -> 9707983 | T34: =LN(R34/R33) -> 0.0097548712 | Z34: =IFERROR(__xludf.DUMMYFUNCTION("""COMPUTED_VALUE"""),45425.64583333333) -> 45425.646 | AA34: =IFERROR(__xludf.DUMMYFUNCTION("""COMPUTED_VALUE"""),329.0) -> 329 | AB34: =IFERROR(__xludf.DUMMYFUNCTION("""COMPUTED_VALUE"""),332.25) -> 332.25 | AC34: =IFERROR(__xludf.DUMMYFUNCTION("""COMPUTED_VALUE"""),321.25) -> 321.25 | AD34: =IFERROR(__xludf.DUMMYFUNCTION("""COMPUTED_VALUE"""),328.3) -> 328.3 | AE34: =IFERROR(__xludf.DUMMYFUNCTION("""COMPUTED_VALUE"""),6016682.0) -> 6016682 | AF34: =LN(AD34/AD33) -> -0.0068301093 | AL34: =IFERROR(__xludf.DUMMYFUNCTION("""COMPUTED_VALUE"""),45425.64583333333) -> 45425.646 | AM34: =IFERROR(__xludf.DUMMYFUNCTION("""COMPUTED_VALUE"""),3875.5) -> 3875.5 | AN34: =IFERROR(__xludf.DUMMYFUNCTION("""COMPUTED_VALUE"""),3937.0) -> 3937 | AO34: =IFERROR(__xludf.DUMMYFUNCTION("""COMPUTED_VALUE"""),3762.6) -> 3762.6 | AP34: =IFERROR(__xludf.DUMMYFUNCTION("""COMPUTED_VALUE"""),3921.75) -> 3921.75 | AQ34: =IFERROR(__xludf.DUMMYFUNCTION("""COMPUTED_VALUE"""),1619124.0) -> 1619124 | AR34: =LN(AP34/AP33) -> 0.012534402 | AX34: =IFERROR(__xludf.DUMMYFUNCTION("""COMPUTED_VALUE"""),45425.64583333333) -> 45425.646 | AY34: =IFERROR(__xludf.DUMMYFUNCTION("""COMPUTED_VALUE"""),433.25) -> 433.25 | AZ34: =IFERROR(__xludf.DUMMYFUNCTION("""COMPUTED_VALUE"""),435.45) -> 435.45 | BA34: =IFERROR(__xludf.DUMMYFUNCTION("""COMPUTED_VALUE"""),429.5) -> 429.5 | BB34: =IFERROR(__xludf.DUMMYFUNCTION("""COMPUTED_VALUE"""),431.85) -> 431.85 | BC34: =IFERROR(__xludf.DUMMYFUNCTION("""COMPUTED_VALUE"""),7302959.0) -> 7302959 | BD34: =LN(BB34/BB33) -> -0.0034674099
B35: 45426 | C35: 6269.12 | D35: 6334.12 | E35: 6267.12 | F35: 6325.52 | G35: - | H35: =LN(F35/F34) -> 0.009181188 | N35: =IFERROR(__xludf.DUMMYFUNCTION("""COMPUTED_VALUE"""),45426.64583333333) -> 45426.646 | O35: =IFERROR(__xludf.DUMMYFUNCTION("""COMPUTED_VALUE"""),1125.9) -> 1125.9 | P35: =IFERROR(__xludf.DUMMYFUNCTION("""COMPUTED_VALUE"""),1127.9) -> 1127.9 | Q35: =IFERROR(__xludf.DUMMYFUNCTION("""COMPUTED_VALUE"""),1118.55) -> 1118.55 | R35: =IFERROR(__xludf.DUMMYFUNCTION("""COMPUTED_VALUE"""),1120.55) -> 1120.55 | S35: =IFERROR(__xludf.DUMMYFUNCTION("""COMPUTED_VALUE"""),8944262.0) -> 8944262 | T35: =LN(R35/R34) -> -0.0066265169 | Z35: =IFERROR(__xludf.DUMMYFUNCTION("""COMPUTED_VALUE"""),45426.64583333333) -> 45426.646 | AA35: =IFERROR(__xludf.DUMMYFUNCTION("""COMPUTED_VALUE"""),330.25) -> 330.25 | AB35: =IFERROR(__xludf.DUMMYFUNCTION("""COMPUTED_VALUE"""),342.0) -> 342 | AC35: =IFERROR(__xludf.DUMMYFUNCTION("""COMPUTED_VALUE"""),328.05) -> 328.05 | AD35: =IFERROR(__xludf.DUMMYFUNCTION("""COMPUTED_VALUE"""),339.5) -> 339.5 | AE35: =IFERROR(__xludf.DUMMYFUNCTION("""COMPUTED_VALUE"""),8910910.0) -> 8910910 | AF35: =LN(AD35/AD34) -> 0.033546122 | AL35: =IFERROR(__xludf.DUMMYFUNCTION("""COMPUTED_VALUE"""),45426.64583333333) -> 45426.646 | AM35: =IFERROR(__xludf.DUMMYFUNCTION("""COMPUTED_VALUE"""),3979.65) -> 3979.65 | AN35: =IFERROR(__xludf.DUMMYFUNCTION("""COMPUTED_VALUE"""),4086.25) -> 4086.25 | AO35: =IFERROR(__xludf.DUMMYFUNCTION("""COMPUTED_VALUE"""),3976.0) -> 3976 | AP35: =IFERROR(__xludf.DUMMYFUNCTION("""COMPUTED_VALUE"""),4074.7) -> 4074.7 | AQ35: =IFERROR(__xludf.DUMMYFUNCTION("""COMPUTED_VALUE"""),2964966.0) -> 2964966 | AR35: =LN(AP35/AP34) -> 0.038259142 | AX35: =IFERROR(__xludf.DUMMYFUNCTION("""COMPUTED_VALUE"""),45426.64583333333) -> 45426.646 | AY35: =IFERROR(__xludf.DUMMYFUNCTION("""COMPUTED_VALUE"""),430.5) -> 430.5 | AZ35: =IFERROR(__xludf.DUMMYFUNCTION("""COMPUTED_VALUE"""),433.3) -> 433.3 | BA35: =IFERROR(__xludf.DUMMYFUNCTION("""COMPUTED_VALUE"""),428.55) -> 428.55 | BB35: =IFERROR(__xludf.DUMMYFUNCTION("""COMPUTED_VALUE"""),429.7) -> 429.7 | BC35: =IFERROR(__xludf.DUMMYFUNCTION("""COMPUTED_VALUE"""),1.1000103E7) -> 11000103 | BD35: =LN(BB35/BB34) -> -0.0049910149
B36: 45427 | C36: 6328.78 | D36: 6410.94 | E36: 6312.12 | F36: 6397.71 | G36: - | H36: =LN(F36/F35) -> 0.011347869 | N36: =IFERROR(__xludf.DUMMYFUNCTION("""COMPUTED_VALUE"""),45427.64583333333) -> 45427.646 | O36: =IFERROR(__xludf.DUMMYFUNCTION("""COMPUTED_VALUE"""),1122.1) -> 1122.1 | P36: =IFERROR(__xludf.DUMMYFUNCTION("""COMPUTED_VALUE"""),1127.8) -> 1127.8 | Q36: =IFERROR(__xludf.DUMMYFUNCTION("""COMPUTED_VALUE"""),1113.5) -> 1113.5 | R36: =IFERROR(__xludf.DUMMYFUNCTION("""COMPUTED_VALUE"""),1124.35) -> 1124.35 | S36: =IFERROR(__xludf.DUMMYFUNCTION("""COMPUTED_VALUE"""),1.0743423E7) -> 10743423 | T36: =LN(R36/R35) -> 0.0033854547 | Z36: =IFERROR(__xludf.DUMMYFUNCTION("""COMPUTED_VALUE"""),45427.64583333333) -> 45427.646 | AA36: =IFERROR(__xludf.DUMMYFUNCTION("""COMPUTED_VALUE"""),342.45) -> 342.45 | AB36: =IFERROR(__xludf.DUMMYFUNCTION("""COMPUTED_VALUE"""),347.9) -> 347.9 | AC36: =IFERROR(__xludf.DUMMYFUNCTION("""COMPUTED_VALUE"""),340.0) -> 340 | AD36: =IFERROR(__xludf.DUMMYFUNCTION("""COMPUTED_VALUE"""),341.8) -> 341.8 | AE36: =IFERROR(__xludf.DUMMYFUNCTION("""COMPUTED_VALUE"""),9691825.0) -> 9691825 | AF36: =LN(AD36/AD35) -> 0.0067518237 | AL36: =IFERROR(__xludf.DUMMYFUNCTION("""COMPUTED_VALUE"""),45427.64583333333) -> 45427.646 | AM36: =IFERROR(__xludf.DUMMYFUNCTION("""COMPUTED_VALUE"""),4105.8) -> 4105.8 | AN36: =IFERROR(__xludf.DUMMYFUNCTION("""COMPUTED_VALUE"""),4193.6) -> 4193.6 | AO36: =IFERROR(__xludf.DUMMYFUNCTION("""COMPUTED_VALUE"""),4051.0) -> 4051 | AP36: =IFERROR(__xludf.DUMMYFUNCTION("""COMPUTED_VALUE"""),4182.35) -> 4182.35 | AQ36: =IFERROR(__xludf.DUMMYFUNCTION("""COMPUTED_VALUE"""),2310941.0) -> 2310941 | AR36: =LN(AP36/AP35) -> 0.026076165 | AX36: =IFERROR(__xludf.DUMMYFUNCTION("""COMPUTED_VALUE"""),45427.64583333333) -> 45427.646 | AY36: =IFERROR(__xludf.DUMMYFUNCTION("""COMPUTED_VALUE"""),430.75) -> 430.75 | AZ36: =IFERROR(__xludf.DUMMYFUNCTION("""COMPUTED_VALUE"""),433.25) -> 433.25 | BA36: =IFERROR(__xludf.DUMMYFUNCTION("""COMPUTED_VALUE"""),426.75) -> 426.75 | BB36: =IFERROR(__xludf.DUMMYFUNCTION("""COMPUTED_VALUE"""),427.8) -> 427.8 | BC36: =IFERROR(__xludf.DUMMYFUNCTION("""COMPUTED_VALUE"""),7565080.0) -> 7565080 | BD36: =LN(BB36/BB35) -> -0.0044314941
B37: 45428 | C37: 6399.12 | D37: 6429.12 | E37: 6362.12 | F37: 6374.12 | G37: - | H37: =LN(F37/F36) -> -0.0036940715 | N37: =IFERROR(__xludf.DUMMYFUNCTION("""COMPUTED_VALUE"""),45428.64583333333) -> 45428.646 | O37: =IFERROR(__xludf.DUMMYFUNCTION("""COMPUTED_VALUE"""),1133.0) -> 1133 | P37: =IFERROR(__xludf.DUMMYFUNCTION("""COMPUTED_VALUE"""),1136.55) -> 1136.55 | Q37: =IFERROR(__xludf.DUMMYFUNCTION("""COMPUTED_VALUE"""),1112.8) -> 1112.8 | R37: =IFERROR(__xludf.DUMMYFUNCTION("""COMPUTED_VALUE"""),1131.05) -> 1131.05 | S37: =IFERROR(__xludf.DUMMYFUNCTION("""COMPUTED_VALUE"""),1.4265565E7) -> 14265565 | T37: =LN(R37/R36) -> 0.0059413139 | Z37: =IFERROR(__xludf.DUMMYFUNCTION("""COMPUTED_VALUE"""),45428.64583333333) -> 45428.646 | AA37: =IFERROR(__xludf.DUMMYFUNCTION("""COMPUTED_VALUE"""),342.7) -> 342.7 | AB37: =IFERROR(__xludf.DUMMYFUNCTION("""COMPUTED_VALUE"""),343.8) -> 343.8 | AC37: =IFERROR(__xludf.DUMMYFUNCTION("""COMPUTED_VALUE"""),337.55) -> 337.55 | AD37: =IFERROR(__xludf.DUMMYFUNCTION("""COMPUTED_VALUE"""),341.0) -> 341 | AE37: =IFERROR(__xludf.DUMMYFUNCTION("""COMPUTED_VALUE"""),6688038.0) -> 6688038 | AF37: =LN(AD37/AD36) -> -0.0023432934 | AL37: =IFERROR(__xludf.DUMMYFUNCTION("""COMPUTED_VALUE"""),45428.64583333333) -> 45428.646 | AM37: =IFERROR(__xludf.DUMMYFUNCTION("""COMPUTED_VALUE"""),4215.0) -> 4215 | AN37: =IFERROR(__xludf.DUMMYFUNCTION("""COMPUTED_VALUE"""),4656.4) -> 4656.4 | AO37: =IFERROR(__xludf.DUMMYFUNCTION("""COMPUTED_VALUE"""),4157.0) -> 4157 | AP37: =IFERROR(__xludf.DUMMYFUNCTION("""COMPUTED_VALUE"""),4603.7) -> 4603.7 | AQ37: =IFERROR(__xludf.DUMMYFUNCTION("""COMPUTED_VALUE"""),1.0028325E7) -> 10028325 | AR37: =LN(AP37/AP36) -> 0.095987038 | AX37: =IFERROR(__xludf.DUMMYFUNCTION("""COMPUTED_VALUE"""),45428.64583333333) -> 45428.646 | AY37: =IFERROR(__xludf.DUMMYFUNCTION("""COMPUTED_VALUE"""),430.0) -> 430 | AZ37: =IFERROR(__xludf.DUMMYFUNCTION("""COMPUTED_VALUE"""),432.6) -> 432.6 | BA37: =IFERROR(__xludf.DUMMYFUNCTION("""COMPUTED_VALUE"""),422.9) -> 422.9 | BB37: =IFERROR(__xludf.DUMMYFUNCTION("""COMPUTED_VALUE"""),431.45) -> 431.45 | BC37: =IFERROR(__xludf.DUMMYFUNCTION("""COMPUTED_VALUE"""),2.3025186E7) -> 23025186 | BD37: =LN(BB37/BB36) -> 0.0084958323
B38: 45429 | C38: 6376.78 | D38: 6488.78 | E38: 6372.12 | F38: 6465.52 | G38: - | H38: =LN(F38/F37) -> 0.0142374 | N38: =IFERROR(__xludf.DUMMYFUNCTION("""COMPUTED_VALUE"""),45429.64583333333) -> 45429.646 | O38: =IFERROR(__xludf.DUMMYFUNCTION("""COMPUTED_VALUE"""),1131.05) -> 1131.05 | P38: =IFERROR(__xludf.DUMMYFUNCTION("""COMPUTED_VALUE"""),1144.0) -> 1144 | Q38: =IFERROR(__xludf.DUMMYFUNCTION("""COMPUTED_VALUE"""),1120.6) -> 1120.6 | R38: =IFERROR(__xludf.DUMMYFUNCTION("""COMPUTED_VALUE"""),1130.5) -> 1130.5 | S38: =IFERROR(__xludf.DUMMYFUNCTION("""COMPUTED_VALUE"""),8641784.0) -> 8641784 | T38: =LN(R38/R37) -> -0.00048639209 | Z38: =IFERROR(__xludf.DUMMYFUNCTION("""COMPUTED_VALUE"""),45429.64583333333) -> 45429.646 | AA38: =IFERROR(__xludf.DUMMYFUNCTION("""COMPUTED_VALUE"""),343.4) -> 343.4 | AB38: =IFERROR(__xludf.DUMMYFUNCTION("""COMPUTED_VALUE"""),349.0) -> 349 | AC38: =IFERROR(__xludf.DUMMYFUNCTION("""COMPUTED_VALUE"""),342.5) -> 342.5 | AD38: =IFERROR(__xludf.DUMMYFUNCTION("""COMPUTED_VALUE"""),344.45) -> 344.45 | AE38: =IFERROR(__xludf.DUMMYFUNCTION("""COMPUTED_VALUE"""),8269010.0) -> 8269010 | AF38: =LN(AD38/AD37) -> 0.010066465 | AL38: =IFERROR(__xludf.DUMMYFUNCTION("""COMPUTED_VALUE"""),45429.64583333333) -> 45429.646 | AM38: =IFERROR(__xludf.DUMMYFUNCTION("""COMPUTED_VALUE"""),4644.95) -> 4644.95 | AN38: =IFERROR(__xludf.DUMMYFUNCTION("""COMPUTED_VALUE"""),4665.95) -> 4665.95 | AO38: =IFERROR(__xludf.DUMMYFUNCTION("""COMPUTED_VALUE"""),4485.05) -> 4485.05 | AP38: =IFERROR(__xludf.DUMMYFUNCTION("""COMPUTED_VALUE"""),4531.7) -> 4531.7 | AQ38: =IFERROR(__xludf.DUMMYFUNCTION("""COMPUTED_VALUE"""),5664667.0) -> 5664667 | AR38: =LN(AP38/AP37) -> -0.015763183 | AX38: =IFERROR(__xludf.DUMMYFUNCTION("""COMPUTED_VALUE"""),45429.64583333333) -> 45429.646 | AY38: =IFERROR(__xludf.DUMMYFUNCTION("""COMPUTED_VALUE"""),432.4) -> 432.4 | AZ38: =IFERROR(__xludf.DUMMYFUNCTION("""COMPUTED_VALUE"""),437.5) -> 437.5 | BA38: =IFERROR(__xludf.DUMMYFUNCTION("""COMPUTED_VALUE"""),428.9) -> 428.9 | BB38: =IFERROR(__xludf.DUMMYFUNCTION("""COMPUTED_VALUE"""),436.3) -> 436.3 | BC38: =IFERROR(__xludf.DUMMYFUNCTION("""COMPUTED_VALUE"""),1.1453714E7) -> 11453714 | BD38: =LN(BB38/BB37) -> 0.011178451
B39: 45433 | C39: 6498.12 | D39: 6518.78 | E39: 6445.52 | F39: 6479.12 | G39: - | H39: =LN(F39/F38) -> 0.0021012566 | N39: =IFERROR(__xludf.DUMMYFUNCTION("""COMPUTED_VALUE"""),45433.64583333333) -> 45433.646 | O39: =IFERROR(__xludf.DUMMYFUNCTION("""COMPUTED_VALUE"""),1122.2) -> 1122.2 | P39: =IFERROR(__xludf.DUMMYFUNCTION("""COMPUTED_VALUE"""),1133.8) -> 1133.8 | Q39: =IFERROR(__xludf.DUMMYFUNCTION("""COMPUTED_VALUE"""),1116.25) -> 1116.25 | R39: =IFERROR(__xludf.DUMMYFUNCTION("""COMPUTED_VALUE"""),1120.95) -> 1120.95 | S39: =IFERROR(__xludf.DUMMYFUNCTION("""COMPUTED_VALUE"""),1.04529E7) -> 10452900 | T39: =LN(R39/R38) -> -0.0084834727 | Z39: =IFERROR(__xludf.DUMMYFUNCTION("""COMPUTED_VALUE"""),45433.64583333333) -> 45433.646 | AA39: =IFERROR(__xludf.DUMMYFUNCTION("""COMPUTED_VALUE"""),347.0) -> 347 | AB39: =IFERROR(__xludf.DUMMYFUNCTION("""COMPUTED_VALUE"""),347.55) -> 347.55 | AC39: =IFERROR(__xludf.DUMMYFUNCTION("""COMPUTED_VALUE"""),338.15) -> 338.15 | AD39: =IFERROR(__xludf.DUMMYFUNCTION("""COMPUTED_VALUE"""),339.05) -> 339.05 | AE39: =IFERROR(__xludf.DUMMYFUNCTION("""COMPUTED_VALUE"""),7533289.0) -> 7533289 | AF39: =LN(AD39/AD38) -> -0.015801353 | AL39: =IFERROR(__xludf.DUMMYFUNCTION("""COMPUTED_VALUE"""),45433.64583333333) -> 45433.646 | AM39: =IFERROR(__xludf.DUMMYFUNCTION("""COMPUTED_VALUE"""),4750.0) -> 4750 | AN39: =IFERROR(__xludf.DUMMYFUNCTION("""COMPUTED_VALUE"""),4870.0) -> 4870 | AO39: =IFERROR(__xludf.DUMMYFUNCTION("""COMPUTED_VALUE"""),4725.15) -> 4725.15 | AP39: =IFERROR(__xludf.DUMMYFUNCTION("""COMPUTED_VALUE"""),4782.25) -> 4782.25 | AQ39: =IFERROR(__xludf.DUMMYFUNCTION("""COMPUTED_VALUE"""),5540182.0) -> 5540182 | AR39: =LN(AP39/AP38) -> 0.053814002 | AX39: =IFERROR(__xludf.DUMMYFUNCTION("""COMPUTED_VALUE"""),45433.64583333333) -> 45433.646 | AY39: =IFERROR(__xludf.DUMMYFUNCTION("""COMPUTED_VALUE"""),436.0) -> 436 | AZ39: =IFERROR(__xludf.DUMMYFUNCTION("""COMPUTED_VALUE"""),437.1) -> 437.1 | BA39: =IFERROR(__xludf.DUMMYFUNCTION("""COMPUTED_VALUE"""),433.2) -> 433.2 | BB39: =IFERROR(__xludf.DUMMYFUNCTION("""COMPUTED_VALUE"""),434.8) -> 434.8 | BC39: =IFERROR(__xludf.DUMMYFUNCTION("""COMPUTED_VALUE"""),1.0760726E7) -> 10760726 | BD39: =LN(BB39/BB38) -> -0.0034439249
B40: 45434 | C40: 6483.52 | D40: 6498.12 | E40: 6355.12 | F40: 6362.78 | G40: - | H40: =LN(F40/F39) -> -0.01811931 | N40: =IFERROR(__xludf.DUMMYFUNCTION("""COMPUTED_VALUE"""),45434.64583333333) -> 45434.646 | O40: =IFERROR(__xludf.DUMMYFUNCTION("""COMPUTED_VALUE"""),1125.0) -> 1125 | P40: =IFERROR(__xludf.DUMMYFUNCTION("""COMPUTED_VALUE"""),1125.9) -> 1125.9 | Q40: =IFERROR(__xludf.DUMMYFUNCTION("""COMPUTED_VALUE"""),1098.1) -> 1098.1 | R40: =IFERROR(__xludf.DUMMYFUNCTION("""COMPUTED_VALUE"""),1111.1) -> 1111.1 | S40: =IFERROR(__xludf.DUMMYFUNCTION("""COMPUTED_VALUE"""),1.7527411E7) -> 17527411 | T40: =LN(R40/R39) -> -0.0088260245 | Z40: =IFERROR(__xludf.DUMMYFUNCTION("""COMPUTED_VALUE"""),45434.64583333333) -> 45434.646 | AA40: =IFERROR(__xludf.DUMMYFUNCTION("""COMPUTED_VALUE"""),342.5) -> 342.5 | AB40: =IFERROR(__xludf.DUMMYFUNCTION("""COMPUTED_VALUE"""),345.25) -> 345.25 | AC40: =IFERROR(__xludf.DUMMYFUNCTION("""COMPUTED_VALUE"""),336.75) -> 336.75 | AD40: =IFERROR(__xludf.DUMMYFUNCTION("""COMPUTED_VALUE"""),339.5) -> 339.5 | AE40: =IFERROR(__xludf.DUMMYFUNCTION("""COMPUTED_VALUE"""),8139260.0) -> 8139260 | AF40: =LN(AD40/AD39) -> 0.0013263579 | AL40: =IFERROR(__xludf.DUMMYFUNCTION("""COMPUTED_VALUE"""),45434.64583333333) -> 45434.646 | AM40: =IFERROR(__xludf.DUMMYFUNCTION("""COMPUTED_VALUE"""),4810.0) -> 4810 | AN40: =IFERROR(__xludf.DUMMYFUNCTION("""COMPUTED_VALUE"""),4960.6) -> 4960.6 | AO40: =IFERROR(__xludf.DUMMYFUNCTION("""COMPUTED_VALUE"""),4735.0) -> 4735 | AP40: =IFERROR(__xludf.DUMMYFUNCTION("""COMPUTED_VALUE"""),4921.2) -> 4921.2 | AQ40: =IFERROR(__xludf.DUMMYFUNCTION("""COMPUTED_VALUE"""),5032087.0) -> 5032087 | AR40: =LN(AP40/AP39) -> 0.028641256 | AX40: =IFERROR(__xludf.DUMMYFUNCTION("""COMPUTED_VALUE"""),45434.64583333333) -> 45434.646 | AY40: =IFERROR(__xludf.DUMMYFUNCTION("""COMPUTED_VALUE"""),437.35) -> 437.35 | AZ40: =IFERROR(__xludf.DUMMYFUNCTION("""COMPUTED_VALUE"""),441.95) -> 441.95 | BA40: =IFERROR(__xludf.DUMMYFUNCTION("""COMPUTED_VALUE"""),435.4) -> 435.4 | BB40: =IFERROR(__xludf.DUMMYFUNCTION("""COMPUTED_VALUE"""),439.9) -> 439.9 | BC40: =IFERROR(__xludf.DUMMYFUNCTION("""COMPUTED_VALUE"""),1.0627595E7) -> 10627595 | BD40: =LN(BB40/BB39) -> 0.011661273
B41: 45435 | C41: 6365.12 | D41: 6381.52 | E41: 6227.71 | F41: 6232.12 | G41: - | H41: =LN(F41/F40) -> -0.020748825 | N41: =IFERROR(__xludf.DUMMYFUNCTION("""COMPUTED_VALUE"""),45435.64583333333) -> 45435.646 | O41: =IFERROR(__xludf.DUMMYFUNCTION("""COMPUTED_VALUE"""),1115.55) -> 1115.55 | P41: =IFERROR(__xludf.DUMMYFUNCTION("""COMPUTED_VALUE"""),1137.0) -> 1137 | Q41: =IFERROR(__xludf.DUMMYFUNCTION("""COMPUTED_VALUE"""),1111.4) -> 1111.4 | R41: =IFERROR(__xludf.DUMMYFUNCTION("""COMPUTED_VALUE"""),1134.5) -> 1134.5 | S41: =IFERROR(__xludf.DUMMYFUNCTION("""COMPUTED_VALUE"""),1.3787687E7) -> 13787687 | T41: =LN(R41/R40) -> 0.02084151 | Z41: =IFERROR(__xludf.DUMMYFUNCTION("""COMPUTED_VALUE"""),45435.64583333333) -> 45435.646 | AA41: =IFERROR(__xludf.DUMMYFUNCTION("""COMPUTED_VALUE"""),341.65) -> 341.65 | AB41: =IFERROR(__xludf.DUMMYFUNCTION("""COMPUTED_VALUE"""),347.65) -> 347.65 | AC41: =IFERROR(__xludf.DUMMYFUNCTION("""COMPUTED_VALUE"""),340.15) -> 340.15 | AD41: =IFERROR(__xludf.DUMMYFUNCTION("""COMPUTED_VALUE"""),343.8) -> 343.8 | AE41: =IFERROR(__xludf.DUMMYFUNCTION("""COMPUTED_VALUE"""),6693276.0) -> 6693276 | AF41: =LN(AD41/AD40) -> 0.012586146 | AL41: =IFERROR(__xludf.DUMMYFUNCTION("""COMPUTED_VALUE"""),45435.64583333333) -> 45435.646 | AM41: =IFERROR(__xludf.DUMMYFUNCTION("""COMPUTED_VALUE"""),4944.0) -> 4944 | AN41: =IFERROR(__xludf.DUMMYFUNCTION("""COMPUTED_VALUE"""),4993.0) -> 4993 | AO41: =IFERROR(__xludf.DUMMYFUNCTION("""COMPUTED_VALUE"""),4908.0) -> 4908 | AP41: =IFERROR(__xludf.DUMMYFUNCTION("""COMPUTED_VALUE"""),4949.9) -> 4949.9 | AQ41: =IFERROR(__xludf.DUMMYFUNCTION("""COMPUTED_VALUE"""),3335143.0) -> 3335143 | AR41: =LN(AP41/AP40) -> 0.0058149712 | AX41: =IFERROR(__xludf.DUMMYFUNCTION("""COMPUTED_VALUE"""),45435.64583333333) -> 45435.646 | AY41: =IFERROR(__xludf.DUMMYFUNCTION("""COMPUTED_VALUE"""),441.4) -> 441.4 | AZ41: =IFERROR(__xludf.DUMMYFUNCTION("""COMPUTED_VALUE"""),444.9) -> 444.9 | BA41: =IFERROR(__xludf.DUMMYFUNCTION("""COMPUTED_VALUE"""),436.55) -> 436.55 | BB41: =IFERROR(__xludf.DUMMYFUNCTION("""COMPUTED_VALUE"""),441.35) -> 441.35 | BC41: =IFERROR(__xludf.DUMMYFUNCTION("""COMPUTED_VALUE"""),2.6234369E7) -> 26234369 | BD41: =LN(BB41/BB40) -> 0.0032907831
B42: 45436 | C42: 6233.12 | D42: 6271.52 | E42: 6225.12 | F42: 6231.12 | G42: - | H42: =LN(F42/F41) -> -0.00016047192 | N42: =IFERROR(__xludf.DUMMYFUNCTION("""COMPUTED_VALUE"""),45436.64583333333) -> 45436.646 | O42: =IFERROR(__xludf.DUMMYFUNCTION("""COMPUTED_VALUE"""),1130.0) -> 1130 | P42: =IFERROR(__xludf.DUMMYFUNCTION("""COMPUTED_VALUE"""),1135.0) -> 1135 | Q42: =IFERROR(__xludf.DUMMYFUNCTION("""COMPUTED_VALUE"""),1124.15) -> 1124.15 | R42: =IFERROR(__xludf.DUMMYFUNCTION("""COMPUTED_VALUE"""),1131.95) -> 1131.95 | S42: =IFERROR(__xludf.DUMMYFUNCTION("""COMPUTED_VALUE"""),6312670.0) -> 6312670 | T42: =LN(R42/R41) -> -0.002250216 | Z42: =IFERROR(__xludf.DUMMYFUNCTION("""COMPUTED_VALUE"""),45436.64583333333) -> 45436.646 | AA42: =IFERROR(__xludf.DUMMYFUNCTION("""COMPUTED_VALUE"""),346.15) -> 346.15 | AB42: =IFERROR(__xludf.DUMMYFUNCTION("""COMPUTED_VALUE"""),356.45) -> 356.45 | AC42: =IFERROR(__xludf.DUMMYFUNCTION("""COMPUTED_VALUE"""),343.05) -> 343.05 | AD42: =IFERROR(__xludf.DUMMYFUNCTION("""COMPUTED_VALUE"""),346.7) -> 346.7 | AE42: =IFERROR(__xludf.DUMMYFUNCTION("""COMPUTED_VALUE"""),2.2371674E7) -> 22371674 | AF42: =LN(AD42/AD41) -> 0.0083997597 | AL42: =IFERROR(__xludf.DUMMYFUNCTION("""COMPUTED_VALUE"""),45436.64583333333) -> 45436.646 | AM42: =IFERROR(__xludf.DUMMYFUNCTION("""COMPUTED_VALUE"""),4950.0) -> 4950 | AN42: =IFERROR(__xludf.DUMMYFUNCTION("""COMPUTED_VALUE"""),5378.0) -> 5378 | AO42: =IFERROR(__xludf.DUMMYFUNCTION("""COMPUTED_VALUE"""),4921.1) -> 4921.1 | AP42: =IFERROR(__xludf.DUMMYFUNCTION("""COMPUTED_VALUE"""),5166.65) -> 5166.65 | AQ42: =IFERROR(__xludf.DUMMYFUNCTION("""COMPUTED_VALUE"""),9073866.0) -> 9073866 | AR42: =LN(AP42/AP41) -> 0.042857135 | AX42: =IFERROR(__xludf.DUMMYFUNCTION("""COMPUTED_VALUE"""),45436.64583333333) -> 45436.646 | AY42: =IFERROR(__xludf.DUMMYFUNCTION("""COMPUTED_VALUE"""),441.0) -> 441 | AZ42: =IFERROR(__xludf.DUMMYFUNCTION("""COMPUTED_VALUE"""),442.45) -> 442.45 | BA42: =IFERROR(__xludf.DUMMYFUNCTION("""COMPUTED_VALUE"""),435.3) -> 435.3 | BB42: =IFERROR(__xludf.DUMMYFUNCTION("""COMPUTED_VALUE"""),436.2) -> 436.2 | BC42: =IFERROR(__xludf.DUMMYFUNCTION("""COMPUTED_VALUE"""),1.2761457E7) -> 12761457 | BD42: =LN(BB42/BB41) -> -0.011737358
B43: 45439 | C43: 6233.71 | D43: 6303.16 | E43: 6228.12 | F43: 6280.12 | G43: - | H43: =LN(F43/F42) -> 0.0078329967 | N43: =IFERROR(__xludf.DUMMYFUNCTION("""COMPUTED_VALUE"""),45439.64583333333) -> 45439.646 | O43: =IFERROR(__xludf.DUMMYFUNCTION("""COMPUTED_VALUE"""),1131.9) -> 1131.9 | P43: =IFERROR(__xludf.DUMMYFUNCTION("""COMPUTED_VALUE"""),1147.8) -> 1147.8 | Q43: =IFERROR(__xludf.DUMMYFUNCTION("""COMPUTED_VALUE"""),1121.55) -> 1121.55 | R43: =IFERROR(__xludf.DUMMYFUNCTION("""COMPUTED_VALUE"""),1129.8) -> 1129.8 | S43: =IFERROR(__xludf.DUMMYFUNCTION("""COMPUTED_VALUE"""),1.1599857E7) -> 11599857 | T43: =LN(R43/R42) -> -0.0019011833 | Z43: =IFERROR(__xludf.DUMMYFUNCTION("""COMPUTED_VALUE"""),45439.64583333333) -> 45439.646 | AA43: =IFERROR(__xludf.DUMMYFUNCTION("""COMPUTED_VALUE"""),347.0) -> 347 | AB43: =IFERROR(__xludf.DUMMYFUNCTION("""COMPUTED_VALUE"""),352.0) -> 352 | AC43: =IFERROR(__xludf.DUMMYFUNCTION("""COMPUTED_VALUE"""),340.8) -> 340.8 | AD43: =IFERROR(__xludf.DUMMYFUNCTION("""COMPUTED_VALUE"""),342.75) -> 342.75 | AE43: =IFERROR(__xludf.DUMMYFUNCTION("""COMPUTED_VALUE"""),7873067.0) -> 7873067 | AF43: =LN(AD43/AD42) -> -0.011458534 | AL43: =IFERROR(__xludf.DUMMYFUNCTION("""COMPUTED_VALUE"""),45439.64583333333) -> 45439.646 | AM43: =IFERROR(__xludf.DUMMYFUNCTION("""COMPUTED_VALUE"""),5192.5) -> 5192.5 | AN43: =IFERROR(__xludf.DUMMYFUNCTION("""COMPUTED_VALUE"""),5223.2) -> 5223.2 | AO43: =IFERROR(__xludf.DUMMYFUNCTION("""COMPUTED_VALUE"""),5025.3) -> 5025.3 | AP43: =IFERROR(__xludf.DUMMYFUNCTION("""COMPUTED_VALUE"""),5142.35) -> 5142.35 | AQ43: =IFERROR(__xludf.DUMMYFUNCTION("""COMPUTED_VALUE"""),4228002.0) -> 4228002 | AR43: =LN(AP43/AP42) -> -0.004714336 | AX43: =IFERROR(__xludf.DUMMYFUNCTION("""COMPUTED_VALUE"""),45439.64583333333) -> 45439.646 | AY43: =IFERROR(__xludf.DUMMYFUNCTION("""COMPUTED_VALUE"""),438.8) -> 438.8 | AZ43: =IFERROR(__xludf.DUMMYFUNCTION("""COMPUTED_VALUE"""),438.9) -> 438.9 | BA43: =IFERROR(__xludf.DUMMYFUNCTION("""COMPUTED_VALUE"""),430.7) -> 430.7 | BB43: =IFERROR(__xludf.DUMMYFUNCTION("""COMPUTED_VALUE"""),431.5) -> 431.5 | BC43: =IFERROR(__xludf.DUMMYFUNCTION("""COMPUTED_VALUE"""),1.182705E7) -> 11827050 | BD43: =LN(BB43/BB42) -> -0.010833343
B44: 45440 | C44: 6283.12 | D44: 6322.12 | E44: 6255.12 | F44: 6313.12 | G44: - | H44: =LN(F44/F43) -> 0.005240919 | N44: =IFERROR(__xludf.DUMMYFUNCTION("""COMPUTED_VALUE"""),45440.64583333333) -> 45440.646 | O44: =IFERROR(__xludf.DUMMYFUNCTION("""COMPUTED_VALUE"""),1132.5) -> 1132.5 | P44: =IFERROR(__xludf.DUMMYFUNCTION("""COMPUTED_VALUE"""),1135.2) -> 1135.2 | Q44: =IFERROR(__xludf.DUMMYFUNCTION("""COMPUTED_VALUE"""),1125.0) -> 1125 | R44: =IFERROR(__xludf.DUMMYFUNCTION("""COMPUTED_VALUE"""),1126.95) -> 1126.95 | S44: =IFERROR(__xludf.DUMMYFUNCTION("""COMPUTED_VALUE"""),9311718.0) -> 9311718 | T44: =LN(R44/R43) -> -0.0025257574 | Z44: =IFERROR(__xludf.DUMMYFUNCTION("""COMPUTED_VALUE"""),45440.64583333333) -> 45440.646 | AA44: =IFERROR(__xludf.DUMMYFUNCTION("""COMPUTED_VALUE"""),346.0) -> 346 | AB44: =IFERROR(__xludf.DUMMYFUNCTION("""COMPUTED_VALUE"""),350.95) -> 350.95 | AC44: =IFERROR(__xludf.DUMMYFUNCTION("""COMPUTED_VALUE"""),340.05) -> 340.05 | AD44: =IFERROR(__xludf.DUMMYFUNCTION("""COMPUTED_VALUE"""),341.4) -> 341.4 | AE44: =IFERROR(__xludf.DUMMYFUNCTION("""COMPUTED_VALUE"""),1.0680935E7) -> 10680935 | AF44: =LN(AD44/AD43) -> -0.0039465081 | AL44: =IFERROR(__xludf.DUMMYFUNCTION("""COMPUTED_VALUE"""),45440.64583333333) -> 45440.646 | AM44: =IFERROR(__xludf.DUMMYFUNCTION("""COMPUTED_VALUE"""),5139.0) -> 5139 | AN44: =IFERROR(__xludf.DUMMYFUNCTION("""COMPUTED_VALUE"""),5207.9) -> 5207.9 | AO44: =IFERROR(__xludf.DUMMYFUNCTION("""COMPUTED_VALUE"""),4955.0) -> 4955 | AP44: =IFERROR(__xludf.DUMMYFUNCTION("""COMPUTED_VALUE"""),5019.75) -> 5019.75 | AQ44: =IFERROR(__xludf.DUMMYFUNCTION("""COMPUTED_VALUE"""),4402348.0) -> 4402348 | AR44: =LN(AP44/AP43) -> -0.024130042 | AX44: =IFERROR(__xludf.DUMMYFUNCTION("""COMPUTED_VALUE"""),45440.64583333333) -> 45440.646 | AY44: =IFERROR(__xludf.DUMMYFUNCTION("""COMPUTED_VALUE"""),432.1) -> 432.1 | AZ44: =IFERROR(__xludf.DUMMYFUNCTION("""COMPUTED_VALUE"""),432.5) -> 432.5 | BA44: =IFERROR(__xludf.DUMMYFUNCTION("""COMPUTED_VALUE"""),428.25) -> 428.25 | BB44: =IFERROR(__xludf.DUMMYFUNCTION("""COMPUTED_VALUE"""),429.0) -> 429 | BC44: =IFERROR(__xludf.DUMMYFUNCTION("""COMPUTED_VALUE"""),9310198.0) -> 9310198 | BD44: =LN(BB44/BB43) -> -0.0058105916
B45: 45441 | C45: 6308.78 | D45: 6322.12 | E45: 6257.71 | F45: 6263.12 | G45: - | H45: =LN(F45/F44) -> -0.0079515441 | N45: =IFERROR(__xludf.DUMMYFUNCTION("""COMPUTED_VALUE"""),45441.64583333333) -> 45441.646 | O45: =IFERROR(__xludf.DUMMYFUNCTION("""COMPUTED_VALUE"""),1115.05) -> 1115.05 | P45: =IFERROR(__xludf.DUMMYFUNCTION("""COMPUTED_VALUE"""),1123.55) -> 1123.55 | Q45: =IFERROR(__xludf.DUMMYFUNCTION("""COMPUTED_VALUE"""),1098.5) -> 1098.5 | R45: =IFERROR(__xludf.DUMMYFUNCTION("""COMPUTED_VALUE"""),1102.0) -> 1102 | S45: =IFERROR(__xludf.DUMMYFUNCTION("""COMPUTED_VALUE"""),1.9268547E7) -> 19268547 | T45: =LN(R45/R44) -> -0.022388158 | Z45: =IFERROR(__xludf.DUMMYFUNCTION("""COMPUTED_VALUE"""),45441.64583333333) -> 45441.646 | AA45: =IFERROR(__xludf.DUMMYFUNCTION("""COMPUTED_VALUE"""),343.0) -> 343 | AB45: =IFERROR(__xludf.DUMMYFUNCTION("""COMPUTED_VALUE"""),345.3) -> 345.3 | AC45: =IFERROR(__xludf.DUMMYFUNCTION("""COMPUTED_VALUE"""),340.25) -> 340.25 | AD45: =IFERROR(__xludf.DUMMYFUNCTION("""COMPUTED_VALUE"""),340.95) -> 340.95 | AE45: =IFERROR(__xludf.DUMMYFUNCTION("""COMPUTED_VALUE"""),6954616.0) -> 6954616 | AF45: =LN(AD45/AD44) -> -0.0013189714 | AL45: =IFERROR(__xludf.DUMMYFUNCTION("""COMPUTED_VALUE"""),45441.64583333333) -> 45441.646 | AM45: =IFERROR(__xludf.DUMMYFUNCTION("""COMPUTED_VALUE"""),5000.0) -> 5000 | AN45: =IFERROR(__xludf.DUMMYFUNCTION("""COMPUTED_VALUE"""),5152.0) -> 5152 | AO45: =IFERROR(__xludf.DUMMYFUNCTION("""COMPUTED_VALUE"""),4950.0) -> 4950 | AP45: =IFERROR(__xludf.DUMMYFUNCTION("""COMPUTED_VALUE"""),5051.75) -> 5051.75 | AQ45: =IFERROR(__xludf.DUMMYFUNCTION("""COMPUTED_VALUE"""),4225666.0) -> 4225666 | AR45: =LN(AP45/AP44) -> 0.0063545862 | AX45: =IFERROR(__xludf.DUMMYFUNCTION("""COMPUTED_VALUE"""),45441.64583333333) -> 45441.646 | AY45: =IFERROR(__xludf.DUMMYFUNCTION("""COMPUTED_VALUE"""),425.5) -> 425.5 | AZ45: =IFERROR(__xludf.DUMMYFUNCTION("""COMPUTED_VALUE"""),432.4) -> 432.4 | BA45: =IFERROR(__xludf.DUMMYFUNCTION("""COMPUTED_VALUE"""),425.5) -> 425.5 | BB45: =IFERROR(__xludf.DUMMYFUNCTION("""COMPUTED_VALUE"""),430.95) -> 430.95 | BC45: =IFERROR(__xludf.DUMMYFUNCTION("""COMPUTED_VALUE"""),1.0430363E7) -> 10430363 | BD45: =LN(BB45/BB44) -> 0.0045351552
B46: 45442 | C46: 6264.78 | D46: 6297.52 | E46: 6228.78 | F46: 6277.71 | G46: - | H46: =LN(F46/F45) -> 0.0023268008 | N46: =IFERROR(__xludf.DUMMYFUNCTION("""COMPUTED_VALUE"""),45442.64583333333) -> 45442.646 | O46: =IFERROR(__xludf.DUMMYFUNCTION("""COMPUTED_VALUE"""),1097.0) -> 1097 | P46: =IFERROR(__xludf.DUMMYFUNCTION("""COMPUTED_VALUE"""),1121.0) -> 1121 | Q46: =IFERROR(__xludf.DUMMYFUNCTION("""COMPUTED_VALUE"""),1096.9) -> 1096.9 | R46: =IFERROR(__xludf.DUMMYFUNCTION("""COMPUTED_VALUE"""),1113.7) -> 1113.7 | S46: =IFERROR(__xludf.DUMMYFUNCTION("""COMPUTED_VALUE"""),1.5255387E7) -> 15255387 | T46: =LN(R46/R45) -> 0.010561095 | Z46: =IFERROR(__xludf.DUMMYFUNCTION("""COMPUTED_VALUE"""),45442.64583333333) -> 45442.646 | AA46: =IFERROR(__xludf.DUMMYFUNCTION("""COMPUTED_VALUE"""),340.8) -> 340.8 | AB46: =IFERROR(__xludf.DUMMYFUNCTION("""COMPUTED_VALUE"""),346.4) -> 346.4 | AC46: =IFERROR(__xludf.DUMMYFUNCTION("""COMPUTED_VALUE"""),338.7) -> 338.7 | AD46: =IFERROR(__xludf.DUMMYFUNCTION("""COMPUTED_VALUE"""),343.75) -> 343.75 | AE46: =IFERROR(__xludf.DUMMYFUNCTION("""COMPUTED_VALUE"""),1.0307057E7) -> 10307057 | AF46: =LN(AD46/AD45) -> 0.00817881 | AL46: =IFERROR(__xludf.DUMMYFUNCTION("""COMPUTED_VALUE"""),45442.64583333333) -> 45442.646 | AM46: =IFERROR(__xludf.DUMMYFUNCTION("""COMPUTED_VALUE"""),5062.05) -> 5062.05 | AN46: =IFERROR(__xludf.DUMMYFUNCTION("""COMPUTED_VALUE"""),5090.0) -> 5090 | AO46: =IFERROR(__xludf.DUMMYFUNCTION("""COMPUTED_VALUE"""),4953.05) -> 4953.05 | AP46: =IFERROR(__xludf.DUMMYFUNCTION("""COMPUTED_VALUE"""),4976.25) -> 4976.25 | AQ46: =IFERROR(__xludf.DUMMYFUNCTION("""COMPUTED_VALUE"""),2751972.0) -> 2751972 | AR46: =LN(AP46/AP45) -> -0.015058123 | AX46: =IFERROR(__xludf.DUMMYFUNCTION("""COMPUTED_VALUE"""),45442.64583333333) -> 45442.646 | AY46: =IFERROR(__xludf.DUMMYFUNCTION("""COMPUTED_VALUE"""),428.5) -> 428.5 | AZ46: =IFERROR(__xludf.DUMMYFUNCTION("""COMPUTED_VALUE"""),430.95) -> 430.95 | BA46: =IFERROR(__xludf.DUMMYFUNCTION("""COMPUTED_VALUE"""),422.35) -> 422.35 | BB46: =IFERROR(__xludf.DUMMYFUNCTION("""COMPUTED_VALUE"""),423.85) -> 423.85 | BC46: =IFERROR(__xludf.DUMMYFUNCTION("""COMPUTED_VALUE"""),2.0524428E7) -> 20524428 | BD46: =LN(BB46/BB45) -> -0.016612455
B47: 45443 | C47: 6275.12 | D47: 6324.78 | E47: 6226.12 | F47: 6240.78 | G47: - | H47: =LN(F47/F46) -> -0.0059000897 | N47: =IFERROR(__xludf.DUMMYFUNCTION("""COMPUTED_VALUE"""),45443.64583333333) -> 45443.646 | O47: =IFERROR(__xludf.DUMMYFUNCTION("""COMPUTED_VALUE"""),1118.0) -> 1118 | P47: =IFERROR(__xludf.DUMMYFUNCTION("""COMPUTED_VALUE"""),1130.6) -> 1130.6 | Q47: =IFERROR(__xludf.DUMMYFUNCTION("""COMPUTED_VALUE"""),1111.25) -> 1111.25 | R47: =IFERROR(__xludf.DUMMYFUNCTION("""COMPUTED_VALUE"""),1121.05) -> 1121.05 | S47: =IFERROR(__xludf.DUMMYFUNCTION("""COMPUTED_VALUE"""),2.6197718E7) -> 26197718 | T47: =LN(R47/R46) -> 0.0065779407 | Z47: =IFERROR(__xludf.DUMMYFUNCTION("""COMPUTED_VALUE"""),45443.64583333333) -> 45443.646 | AA47: =IFERROR(__xludf.DUMMYFUNCTION("""COMPUTED_VALUE"""),347.2) -> 347.2 | AB47: =IFERROR(__xludf.DUMMYFUNCTION("""COMPUTED_VALUE"""),350.7) -> 350.7 | AC47: =IFERROR(__xludf.DUMMYFUNCTION("""COMPUTED_VALUE"""),342.0) -> 342 | AD47: =IFERROR(__xludf.DUMMYFUNCTION("""COMPUTED_VALUE"""),348.15) -> 348.15 | AE47: =IFERROR(__xludf.DUMMYFUNCTION("""COMPUTED_VALUE"""),1.10651268E8) -> 110651268 | AF47: =LN(AD47/AD46) -> 0.012718772 | AL47: =IFERROR(__xludf.DUMMYFUNCTION("""COMPUTED_VALUE"""),45443.64583333333) -> 45443.646 | AM47: =IFERROR(__xludf.DUMMYFUNCTION("""COMPUTED_VALUE"""),5020.0) -> 5020 | AN47: =IFERROR(__xludf.DUMMYFUNCTION("""COMPUTED_VALUE"""),5042.8) -> 5042.8 | AO47: =IFERROR(__xludf.DUMMYFUNCTION("""COMPUTED_VALUE"""),4862.2) -> 4862.2 | AP47: =IFERROR(__xludf.DUMMYFUNCTION("""COMPUTED_VALUE"""),4973.85) -> 4973.85 | AQ47: =IFERROR(__xludf.DUMMYFUNCTION("""COMPUTED_VALUE"""),3912234.0) -> 3912234 | AR47: =LN(AP47/AP46) -> -0.00048240722 | AX47: =IFERROR(__xludf.DUMMYFUNCTION("""COMPUTED_VALUE"""),45443.64583333333) -> 45443.646 | AY47: =IFERROR(__xludf.DUMMYFUNCTION("""COMPUTED_VALUE"""),426.75) -> 426.75 | AZ47: =IFERROR(__xludf.DUMMYFUNCTION("""COMPUTED_VALUE"""),429.55) -> 429.55 | BA47: =IFERROR(__xludf.DUMMYFUNCTION("""COMPUTED_VALUE"""),424.25) -> 424.25 | BB47: =IFERROR(__xludf.DUMMYFUNCTION("""COMPUTED_VALUE"""),426.45) -> 426.45 | BC47: =IFERROR(__xludf.DUMMYFUNCTION("""COMPUTED_VALUE"""),2.8214102E7) -> 28214102 | BD47: =LN(BB47/BB46) -> 0.0061155077
B48: 45446 | C48: 6240.12 | D48: 6291.71 | E48: 6181.12 | F48: 6275.52 | G48: - | H48: =LN(F48/F47) -> 0.0055511755 | N48: =IFERROR(__xludf.DUMMYFUNCTION("""COMPUTED_VALUE"""),45446.64583333333) -> 45446.646 | O48: =IFERROR(__xludf.DUMMYFUNCTION("""COMPUTED_VALUE"""),1170.0) -> 1170 | P48: =IFERROR(__xludf.DUMMYFUNCTION("""COMPUTED_VALUE"""),1173.0) -> 1173 | Q48: =IFERROR(__xludf.DUMMYFUNCTION("""COMPUTED_VALUE"""),1136.3) -> 1136.3 | R48: =IFERROR(__xludf.DUMMYFUNCTION("""COMPUTED_VALUE"""),1160.0) -> 1160 | S48: =IFERROR(__xludf.DUMMYFUNCTION("""COMPUTED_VALUE"""),2.5699977E7) -> 25699977 | T48: =LN(R48/R47) -> 0.034154259 | Z48: =IFERROR(__xludf.DUMMYFUNCTION("""COMPUTED_VALUE"""),45446.64583333333) -> 45446.646 | AA48: =IFERROR(__xludf.DUMMYFUNCTION("""COMPUTED_VALUE"""),360.5) -> 360.5 | AB48: =IFERROR(__xludf.DUMMYFUNCTION("""COMPUTED_VALUE"""),369.9) -> 369.9 | AC48: =IFERROR(__xludf.DUMMYFUNCTION("""COMPUTED_VALUE"""),341.7) -> 341.7 | AD48: =IFERROR(__xludf.DUMMYFUNCTION("""COMPUTED_VALUE"""),364.0) -> 364 | AE48: =IFERROR(__xludf.DUMMYFUNCTION("""COMPUTED_VALUE"""),2.9686486E7) -> 29686486 | AF48: =LN(AD48/AD47) -> 0.044520446 | AL48: =IFERROR(__xludf.DUMMYFUNCTION("""COMPUTED_VALUE"""),45446.64583333333) -> 45446.646 | AM48: =IFERROR(__xludf.DUMMYFUNCTION("""COMPUTED_VALUE"""),5444.0) -> 5444 | AN48: =IFERROR(__xludf.DUMMYFUNCTION("""COMPUTED_VALUE"""),5444.0) -> 5444 | AO48: =IFERROR(__xludf.DUMMYFUNCTION("""COMPUTED_VALUE"""),5162.3) -> 5162.3 | AP48: =IFERROR(__xludf.DUMMYFUNCTION("""COMPUTED_VALUE"""),5273.65) -> 5273.65 | AQ48: =IFERROR(__xludf.DUMMYFUNCTION("""COMPUTED_VALUE"""),4619434.0) -> 4619434 | AR48: =LN(AP48/AP47) -> 0.058528534 | AX48: =IFERROR(__xludf.DUMMYFUNCTION("""COMPUTED_VALUE"""),45446.64583333333) -> 45446.646 | AY48: =IFERROR(__xludf.DUMMYFUNCTION("""COMPUTED_VALUE"""),434.0) -> 434 | AZ48: =IFERROR(__xludf.DUMMYFUNCTION("""COMPUTED_VALUE"""),434.9) -> 434.9 | BA48: =IFERROR(__xludf.DUMMYFUNCTION("""COMPUTED_VALUE"""),428.65) -> 428.65 | BB48: =IFERROR(__xludf.DUMMYFUNCTION("""COMPUTED_VALUE"""),430.35) -> 430.35 | BC48: =IFERROR(__xludf.DUMMYFUNCTION("""COMPUTED_VALUE"""),1.5519148E7) -> 15519148 | BD48: =LN(BB48/BB47) -> 0.0091037043
B49: 45447 | C49: 6280.78 | D49: 6312.12 | E49: 6220.78 | F49: 6245.52 | G49: - | H49: =LN(F49/F48) -> -0.0047919434 | N49: =IFERROR(__xludf.DUMMYFUNCTION("""COMPUTED_VALUE"""),45447.64583333333) -> 45447.646 | O49: =IFERROR(__xludf.DUMMYFUNCTION("""COMPUTED_VALUE"""),1157.9) -> 1157.9 | P49: =IFERROR(__xludf.DUMMYFUNCTION("""COMPUTED_VALUE"""),1159.4) -> 1159.4 | Q49: =IFERROR(__xludf.DUMMYFUNCTION("""COMPUTED_VALUE"""),1053.55) -> 1053.55 | R49: =IFERROR(__xludf.DUMMYFUNCTION("""COMPUTED_VALUE"""),1071.45) -> 1071.45 | S49: =IFERROR(__xludf.DUMMYFUNCTION("""COMPUTED_VALUE"""),4.3476837E7) -> 43476837 | T49: =LN(R49/R48) -> -0.079407134 | Z49: =IFERROR(__xludf.DUMMYFUNCTION("""COMPUTED_VALUE"""),45447.64583333333) -> 45447.646 | AA49: =IFERROR(__xludf.DUMMYFUNCTION("""COMPUTED_VALUE"""),363.0) -> 363 | AB49: =IFERROR(__xludf.DUMMYFUNCTION("""COMPUTED_VALUE"""),363.0) -> 363 | AC49: =IFERROR(__xludf.DUMMYFUNCTION("""COMPUTED_VALUE"""),292.0) -> 292 | AD49: =IFERROR(__xludf.DUMMYFUNCTION("""COMPUTED_VALUE"""),307.95) -> 307.95 | AE49: =IFERROR(__xludf.DUMMYFUNCTION("""COMPUTED_VALUE"""),2.8901481E7) -> 28901481 | AF49: =LN(AD49/AD48) -> -0.16721644 | AL49: =IFERROR(__xludf.DUMMYFUNCTION("""COMPUTED_VALUE"""),45447.64583333333) -> 45447.646 | AM49: =IFERROR(__xludf.DUMMYFUNCTION("""COMPUTED_VALUE"""),5145.0) -> 5145 | AN49: =IFERROR(__xludf.DUMMYFUNCTION("""COMPUTED_VALUE"""),5145.0) -> 5145 | AO49: =IFERROR(__xludf.DUMMYFUNCTION("""COMPUTED_VALUE"""),3955.25) -> 3955.25 | AP49: =IFERROR(__xludf.DUMMYFUNCTION("""COMPUTED_VALUE"""),4333.35) -> 4333.35 | AQ49: =IFERROR(__xludf.DUMMYFUNCTION("""COMPUTED_VALUE"""),1.5486676E7) -> 15486676 | AR49: =LN(AP49/AP48) -> -0.19638181 | AX49: =IFERROR(__xludf.DUMMYFUNCTION("""COMPUTED_VALUE"""),45447.64583333333) -> 45447.646 | AY49: =IFERROR(__xludf.DUMMYFUNCTION("""COMPUTED_VALUE"""),426.0) -> 426 | AZ49: =IFERROR(__xludf.DUMMYFUNCTION("""COMPUTED_VALUE"""),426.3) -> 426.3 | BA49: =IFERROR(__xludf.DUMMYFUNCTION("""COMPUTED_VALUE"""),402.85) -> 402.85 | BB49: =IFERROR(__xludf.DUMMYFUNCTION("""COMPUTED_VALUE"""),415.2) -> 415.2 | BC49: =IFERROR(__xludf.DUMMYFUNCTION("""COMPUTED_VALUE"""),4.6019632E7) -> 46019632 | BD49: =LN(BB49/BB48) -> -0.035838499
B50: 45448 | C50: 6250.12 | D50: 6320.78 | E50: 6241.12 | F50: 6308.78 | G50: - | H50: =LN(F50/F49) -> 0.010077907 | N50: =IFERROR(__xludf.DUMMYFUNCTION("""COMPUTED_VALUE"""),45448.64583333333) -> 45448.646 | O50: =IFERROR(__xludf.DUMMYFUNCTION("""COMPUTED_VALUE"""),1085.0) -> 1085 | P50: =IFERROR(__xludf.DUMMYFUNCTION("""COMPUTED_VALUE"""),1123.25) -> 1123.25 | Q50: =IFERROR(__xludf.DUMMYFUNCTION("""COMPUTED_VALUE"""),1051.05) -> 1051.05 | R50: =IFERROR(__xludf.DUMMYFUNCTION("""COMPUTED_VALUE"""),1108.65) -> 1108.65 | S50: =IFERROR(__xludf.DUMMYFUNCTION("""COMPUTED_VALUE"""),4.2172104E7) -> 42172104 | T50: =LN(R50/R49) -> 0.034130188 | Z50: =IFERROR(__xludf.DUMMYFUNCTION("""COMPUTED_VALUE"""),45448.64583333333) -> 45448.646 | AA50: =IFERROR(__xludf.DUMMYFUNCTION("""COMPUTED_VALUE"""),319.3) -> 319.3 | AB50: =IFERROR(__xludf.DUMMYFUNCTION("""COMPUTED_VALUE"""),335.8) -> 335.8 | AC50: =IFERROR(__xludf.DUMMYFUNCTION("""COMPUTED_VALUE"""),309.25) -> 309.25 | AD50: =IFERROR(__xludf.DUMMYFUNCTION("""COMPUTED_VALUE"""),332.7) -> 332.7 | AE50: =IFERROR(__xludf.DUMMYFUNCTION("""COMPUTED_VALUE"""),1.4300262E7) -> 14300262 | AF50: =LN(AD50/AD49) -> 0.077303751 | AL50: =IFERROR(__xludf.DUMMYFUNCTION("""COMPUTED_VALUE"""),45448.64583333333) -> 45448.646 | AM50: =IFERROR(__xludf.DUMMYFUNCTION("""COMPUTED_VALUE"""),4421.15) -> 4421.15 | AN50: =IFERROR(__xludf.DUMMYFUNCTION("""COMPUTED_VALUE"""),4449.1) -> 4449.1 | AO50: =IFERROR(__xludf.DUMMYFUNCTION("""COMPUTED_VALUE"""),3920.0) -> 3920 | AP50: =IFERROR(__xludf.DUMMYFUNCTION("""COMPUTED_VALUE"""),4364.9) -> 4364.9 | AQ50: =IFERROR(__xludf.DUMMYFUNCTION("""COMPUTED_VALUE"""),1.3759681E7) -> 13759681 | AR50: =LN(AP50/AP49) -> 0.0072543646 | AX50: =IFERROR(__xludf.DUMMYFUNCTION("""COMPUTED_VALUE"""),45448.64583333333) -> 45448.646 | AY50: =IFERROR(__xludf.DUMMYFUNCTION("""COMPUTED_VALUE"""),422.0) -> 422 | AZ50: =IFERROR(__xludf.DUMMYFUNCTION("""COMPUTED_VALUE"""),436.0) -> 436 | BA50: =IFERROR(__xludf.DUMMYFUNCTION("""COMPUTED_VALUE"""),418.05) -> 418.05 | BB50: =IFERROR(__xludf.DUMMYFUNCTION("""COMPUTED_VALUE"""),430.3) -> 430.3 | BC50: =IFERROR(__xludf.DUMMYFUNCTION("""COMPUTED_VALUE"""),2.7151351E7) -> 27151351 | BD50: =LN(BB50/BB49) -> 0.035722308
B51: 45449 | C51: 6311.52 | D51: 6383.12 | E51: 6309.12 | F51: 6375.12 | G51: - | H51: =LN(F51/F50) -> 0.0104606 | N51: =IFERROR(__xludf.DUMMYFUNCTION("""COMPUTED_VALUE"""),45449.64583333333) -> 45449.646 | O51: =IFERROR(__xludf.DUMMYFUNCTION("""COMPUTED_VALUE"""),1118.0) -> 1118 | P51: =IFERROR(__xludf.DUMMYFUNCTION("""COMPUTED_VALUE"""),1118.0) -> 1118 | Q51: =IFERROR(__xludf.DUMMYFUNCTION("""COMPUTED_VALUE"""),1096.6) -> 1096.6 | R51: =IFERROR(__xludf.DUMMYFUNCTION("""COMPUTED_VALUE"""),1110.4) -> 1110.4 | S51: =IFERROR(__xludf.DUMMYFUNCTION("""COMPUTED_VALUE"""),1.8574162E7) -> 18574162 | T51: =LN(R51/R50) -> 0.0015772519 | Z51: =IFERROR(__xludf.DUMMYFUNCTION("""COMPUTED_VALUE"""),45449.64583333333) -> 45449.646 | AA51: =IFERROR(__xludf.DUMMYFUNCTION("""COMPUTED_VALUE"""),335.0) -> 335 | AB51: =IFERROR(__xludf.DUMMYFUNCTION("""COMPUTED_VALUE"""),344.95) -> 344.95 | AC51: =IFERROR(__xludf.DUMMYFUNCTION("""COMPUTED_VALUE"""),334.5) -> 334.5 | AD51: =IFERROR(__xludf.DUMMYFUNCTION("""COMPUTED_VALUE"""),339.35) -> 339.35 | AE51: =IFERROR(__xludf.DUMMYFUNCTION("""COMPUTED_VALUE"""),8216145.0) -> 8216145 | AF51: =LN(AD51/AD50) -> 0.01979084 | AL51: =IFERROR(__xludf.DUMMYFUNCTION("""COMPUTED_VALUE"""),45449.64583333333) -> 45449.646 | AM51: =IFERROR(__xludf.DUMMYFUNCTION("""COMPUTED_VALUE"""),4450.0) -> 4450 | AN51: =IFERROR(__xludf.DUMMYFUNCTION("""COMPUTED_VALUE"""),4800.0) -> 4800 | AO51: =IFERROR(__xludf.DUMMYFUNCTION("""COMPUTED_VALUE"""),4450.0) -> 4450 | AP51: =IFERROR(__xludf.DUMMYFUNCTION("""COMPUTED_VALUE"""),4666.6) -> 4666.6 | AQ51: =IFERROR(__xludf.DUMMYFUNCTION("""COMPUTED_VALUE"""),9128985.0) -> 9128985 | AR51: =LN(AP51/AP50) -> 0.066835476 | AX51: =IFERROR(__xludf.DUMMYFUNCTION("""COMPUTED_VALUE"""),45449.64583333333) -> 45449.646 | AY51: =IFERROR(__xludf.DUMMYFUNCTION("""COMPUTED_VALUE"""),436.0) -> 436 | AZ51: =IFERROR(__xludf.DUMMYFUNCTION("""COMPUTED_VALUE"""),437.7) -> 437.7 | BA51: =IFERROR(__xludf.DUMMYFUNCTION("""COMPUTED_VALUE"""),431.1) -> 431.1 | BB51: =IFERROR(__xludf.DUMMYFUNCTION("""COMPUTED_VALUE"""),435.4) -> 435.4 | BC51: =IFERROR(__xludf.DUMMYFUNCTION("""COMPUTED_VALUE"""),3.1119999E7) -> 31119999 | BD51: =LN(BB51/BB50) -> 0.011782509
B52: 45450 | C52: 6376.78 | D52: 6407.12 | E52: 6138.12 | F52: 6156.12 | G52: - | H52: =LN(F52/F51) -> -0.034956205 | N52: =IFERROR(__xludf.DUMMYFUNCTION("""COMPUTED_VALUE"""),45450.64583333333) -> 45450.646 | O52: =IFERROR(__xludf.DUMMYFUNCTION("""COMPUTED_VALUE"""),1110.4) -> 1110.4 | P52: =IFERROR(__xludf.DUMMYFUNCTION("""COMPUTED_VALUE"""),1128.3) -> 1128.3 | Q52: =IFERROR(__xludf.DUMMYFUNCTION("""COMPUTED_VALUE"""),1103.6) -> 1103.6 | R52: =IFERROR(__xludf.DUMMYFUNCTION("""COMPUTED_VALUE"""),1121.7) -> 1121.7 | S52: =IFERROR(__xludf.DUMMYFUNCTION("""COMPUTED_VALUE"""),1.7197635E7) -> 17197635 | T52: =LN(R52/R51) -> 0.010125081 | Z52: =IFERROR(__xludf.DUMMYFUNCTION("""COMPUTED_VALUE"""),45450.64583333333) -> 45450.646 | AA52: =IFERROR(__xludf.DUMMYFUNCTION("""COMPUTED_VALUE"""),338.05) -> 338.05 | AB52: =IFERROR(__xludf.DUMMYFUNCTION("""COMPUTED_VALUE"""),351.4) -> 351.4 | AC52: =IFERROR(__xludf.DUMMYFUNCTION("""COMPUTED_VALUE"""),337.1) -> 337.1 | AD52: =IFERROR(__xludf.DUMMYFUNCTION("""COMPUTED_VALUE"""),347.15) -> 347.15 | AE52: =IFERROR(__xludf.DUMMYFUNCTION("""COMPUTED_VALUE"""),1.0966598E7) -> 10966598 | AF52: =LN(AD52/AD51) -> 0.02272494 | AL52: =IFERROR(__xludf.DUMMYFUNCTION("""COMPUTED_VALUE"""),45450.64583333333) -> 45450.646 | AM52: =IFERROR(__xludf.DUMMYFUNCTION("""COMPUTED_VALUE"""),4666.65) -> 4666.65 | AN52: =IFERROR(__xludf.DUMMYFUNCTION("""COMPUTED_VALUE"""),4788.0) -> 4788 | AO52: =IFERROR(__xludf.DUMMYFUNCTION("""COMPUTED_VALUE"""),4550.0) -> 4550 | AP52: =IFERROR(__xludf.DUMMYFUNCTION("""COMPUTED_VALUE"""),4745.15) -> 4745.15 | AQ52: =IFERROR(__xludf.DUMMYFUNCTION("""COMPUTED_VALUE"""),4542809.0) -> 4542809 | AR52: =LN(AP52/AP51) -> 0.016692289 | AX52: =IFERROR(__xludf.DUMMYFUNCTION("""COMPUTED_VALUE"""),45450.64583333333) -> 45450.646 | AY52: =IFERROR(__xludf.DUMMYFUNCTION("""COMPUTED_VALUE"""),431.4) -> 431.4 | AZ52: =IFERROR(__xludf.DUMMYFUNCTION("""COMPUTED_VALUE"""),441.65) -> 441.65 | BA52: =IFERROR(__xludf.DUMMYFUNCTION("""COMPUTED_VALUE"""),431.1) -> 431.1 | BB52: =IFERROR(__xludf.DUMMYFUNCTION("""COMPUTED_VALUE"""),439.15) -> 439.15 | BC52: =IFERROR(__xludf.DUMMYFUNCTION("""COMPUTED_VALUE"""),2.8448041E7) -> 28448041 | BD52: =LN(BB52/BB51) -> 0.0085758916
B53: 45453 | C53: 6165.12 | D53: 6213.12 | E53: 6139.12 | F53: 6200.78 | G53: - | H53: =LN(F53/F52) -> 0.0072283816 | N53: =IFERROR(__xludf.DUMMYFUNCTION("""COMPUTED_VALUE"""),45453.64583333333) -> 45453.646 | O53: =IFERROR(__xludf.DUMMYFUNCTION("""COMPUTED_VALUE"""),1116.0) -> 1116 | P53: =IFERROR(__xludf.DUMMYFUNCTION("""COMPUTED_VALUE"""),1133.2) -> 1133.2 | Q53: =IFERROR(__xludf.DUMMYFUNCTION("""COMPUTED_VALUE"""),1115.1) -> 1115.1 | R53: =IFERROR(__xludf.DUMMYFUNCTION("""COMPUTED_VALUE"""),1123.8) -> 1123.8 | S53: =IFERROR(__xludf.DUMMYFUNCTION("""COMPUTED_VALUE"""),1.0851455E7) -> 10851455 | T53: =LN(R53/R52) -> 0.001870408 | Z53: =IFERROR(__xludf.DUMMYFUNCTION("""COMPUTED_VALUE"""),45453.64583333333) -> 45453.646 | AA53: =IFERROR(__xludf.DUMMYFUNCTION("""COMPUTED_VALUE"""),347.15) -> 347.15 | AB53: =IFERROR(__xludf.DUMMYFUNCTION("""COMPUTED_VALUE"""),352.5) -> 352.5 | AC53: =IFERROR(__xludf.DUMMYFUNCTION("""COMPUTED_VALUE"""),344.45) -> 344.45 | AD53: =IFERROR(__xludf.DUMMYFUNCTION("""COMPUTED_VALUE"""),348.15) -> 348.15 | AE53: =IFERROR(__xludf.DUMMYFUNCTION("""COMPUTED_VALUE"""),5450324.0) -> 5450324 | AF53: =LN(AD53/AD52) -> 0.0028764582 | AL53: =IFERROR(__xludf.DUMMYFUNCTION("""COMPUTED_VALUE"""),45453.64583333333) -> 45453.646 | AM53: =IFERROR(__xludf.DUMMYFUNCTION("""COMPUTED_VALUE"""),4800.0) -> 4800 | AN53: =IFERROR(__xludf.DUMMYFUNCTION("""COMPUTED_VALUE"""),4844.0) -> 4844 | AO53: =IFERROR(__xludf.DUMMYFUNCTION("""COMPUTED_VALUE"""),4751.55) -> 4751.55 | AP53: =IFERROR(__xludf.DUMMYFUNCTION("""COMPUTED_VALUE"""),4812.7) -> 4812.7 | AQ53: =IFERROR(__xludf.DUMMYFUNCTION("""COMPUTED_VALUE"""),2877321.0) -> 2877321 | AR53: =LN(AP53/AP52) -> 0.014135213 | AX53: =IFERROR(__xludf.DUMMYFUNCTION("""COMPUTED_VALUE"""),45453.64583333333) -> 45453.646 | AY53: =IFERROR(__xludf.DUMMYFUNCTION("""COMPUTED_VALUE"""),440.0) -> 440 | AZ53: =IFERROR(__xludf.DUMMYFUNCTION("""COMPUTED_VALUE"""),441.0) -> 441 | BA53: =IFERROR(__xludf.DUMMYFUNCTION("""COMPUTED_VALUE"""),435.85) -> 435.85 | BB53: =IFERROR(__xludf.DUMMYFUNCTION("""COMPUTED_VALUE"""),436.9) -> 436.9 | BC53: =IFERROR(__xludf.DUMMYFUNCTION("""COMPUTED_VALUE"""),1.1432393E7) -> 11432393 | BD53: =LN(BB53/BB52) -> -0.0051367044
B54: 45454 | C54: 6205.12 | D54: 6234.78 | E54: 6168.12 | F54: 6226.12 | G54: - | H54: =LN(F54/F53) -> 0.0040782553 | N54: =IFERROR(__xludf.DUMMYFUNCTION("""COMPUTED_VALUE"""),45454.64583333333) -> 45454.646 | O54: =IFERROR(__xludf.DUMMYFUNCTION("""COMPUTED_VALUE"""),1119.75) -> 1119.75 | P54: =IFERROR(__xludf.DUMMYFUNCTION("""COMPUTED_VALUE"""),1129.05) -> 1129.05 | Q54: =IFERROR(__xludf.DUMMYFUNCTION("""COMPUTED_VALUE"""),1111.0) -> 1111 | R54: =IFERROR(__xludf.DUMMYFUNCTION("""COMPUTED_VALUE"""),1118.2) -> 1118.2 | S54: =IFERROR(__xludf.DUMMYFUNCTION("""COMPUTED_VALUE"""),1.2250002E7) -> 12250002 | T54: =LN(R54/R53) -> -0.0049955501 | Z54: =IFERROR(__xludf.DUMMYFUNCTION("""COMPUTED_VALUE"""),45454.64583333333) -> 45454.646 | AA54: =IFERROR(__xludf.DUMMYFUNCTION("""COMPUTED_VALUE"""),350.1) -> 350.1 | AB54: =IFERROR(__xludf.DUMMYFUNCTION("""COMPUTED_VALUE"""),353.35) -> 353.35 | AC54: =IFERROR(__xludf.DUMMYFUNCTION("""COMPUTED_VALUE"""),342.0) -> 342 | AD54: =IFERROR(__xludf.DUMMYFUNCTION("""COMPUTED_VALUE"""),347.95) -> 347.95 | AE54: =IFERROR(__xludf.DUMMYFUNCTION("""COMPUTED_VALUE"""),6964630.0) -> 6964630 | AF54: =LN(AD54/AD53) -> -0.0005746301 | AL54: =IFERROR(__xludf.DUMMYFUNCTION("""COMPUTED_VALUE"""),45454.64583333333) -> 45454.646 | AM54: =IFERROR(__xludf.DUMMYFUNCTION("""COMPUTED_VALUE"""),4831.05) -> 4831.05 | AN54: =IFERROR(__xludf.DUMMYFUNCTION("""COMPUTED_VALUE"""),4922.55) -> 4922.55 | AO54: =IFERROR(__xludf.DUMMYFUNCTION("""COMPUTED_VALUE"""),4830.0) -> 4830 | AP54: =IFERROR(__xludf.DUMMYFUNCTION("""COMPUTED_VALUE"""),4856.6) -> 4856.6 | AQ54: =IFERROR(__xludf.DUMMYFUNCTION("""COMPUTED_VALUE"""),2718189.0) -> 2718189 | AR54: =LN(AP54/AP53) -> 0.0090803474 | AX54: =IFERROR(__xludf.DUMMYFUNCTION("""COMPUTED_VALUE"""),45454.64583333333) -> 45454.646 | AY54: =IFERROR(__xludf.DUMMYFUNCTION("""COMPUTED_VALUE"""),437.0) -> 437 | AZ54: =IFERROR(__xludf.DUMMYFUNCTION("""COMPUTED_VALUE"""),437.8) -> 437.8 | BA54: =IFERROR(__xludf.DUMMYFUNCTION("""COMPUTED_VALUE"""),432.25) -> 432.25 | BB54: =IFERROR(__xludf.DUMMYFUNCTION("""COMPUTED_VALUE"""),433.0) -> 433 | BC54: =IFERROR(__xludf.DUMMYFUNCTION("""COMPUTED_VALUE"""),1.2670589E7) -> 12670589 | BD54: =LN(BB54/BB53) -> -0.008966608
B55: 45455 | C55: 6229.71 | D55: 6283.12 | E55: 6207.12 | F55: 6230.12 | G55: - | H55: =LN(F55/F54) -> 0.00064224841 | N55: =IFERROR(__xludf.DUMMYFUNCTION("""COMPUTED_VALUE"""),45455.64583333333) -> 45455.646 | O55: =IFERROR(__xludf.DUMMYFUNCTION("""COMPUTED_VALUE"""),1121.0) -> 1121 | P55: =IFERROR(__xludf.DUMMYFUNCTION("""COMPUTED_VALUE"""),1133.4) -> 1133.4 | Q55: =IFERROR(__xludf.DUMMYFUNCTION("""COMPUTED_VALUE"""),1112.0) -> 1112 | R55: =IFERROR(__xludf.DUMMYFUNCTION("""COMPUTED_VALUE"""),1119.55) -> 1119.55 | S55: =IFERROR(__xludf.DUMMYFUNCTION("""COMPUTED_VALUE"""),1.6096514E7) -> 16096514 | T55: =LN(R55/R54) -> 0.0012065692 | Z55: =IFERROR(__xludf.DUMMYFUNCTION("""COMPUTED_VALUE"""),45455.64583333333) -> 45455.646 | AA55: =IFERROR(__xludf.DUMMYFUNCTION("""COMPUTED_VALUE"""),349.4) -> 349.4 | AB55: =IFERROR(__xludf.DUMMYFUNCTION("""COMPUTED_VALUE"""),349.4) -> 349.4 | AC55: =IFERROR(__xludf.DUMMYFUNCTION("""COMPUTED_VALUE"""),340.95) -> 340.95 | AD55: =IFERROR(__xludf.DUMMYFUNCTION("""COMPUTED_VALUE"""),342.15) -> 342.15 | AE55: =IFERROR(__xludf.DUMMYFUNCTION("""COMPUTED_VALUE"""),9458583.0) -> 9458583 | AF55: =LN(AD55/AD54) -> -0.016809554 | AL55: =IFERROR(__xludf.DUMMYFUNCTION("""COMPUTED_VALUE"""),45455.64583333333) -> 45455.646 | AM55: =IFERROR(__xludf.DUMMYFUNCTION("""COMPUTED_VALUE"""),4881.8) -> 4881.8 | AN55: =IFERROR(__xludf.DUMMYFUNCTION("""COMPUTED_VALUE"""),4925.3) -> 4925.3 | AO55: =IFERROR(__xludf.DUMMYFUNCTION("""COMPUTED_VALUE"""),4841.55) -> 4841.55 | AP55: =IFERROR(__xludf.DUMMYFUNCTION("""COMPUTED_VALUE"""),4889.0) -> 4889 | AQ55: =IFERROR(__xludf.DUMMYFUNCTION("""COMPUTED_VALUE"""),2031876.0) -> 2031876 | AR55: =LN(AP55/AP54) -> 0.006649179 | AX55: =IFERROR(__xludf.DUMMYFUNCTION("""COMPUTED_VALUE"""),45455.64583333333) -> 45455.646 | AY55: =IFERROR(__xludf.DUMMYFUNCTION("""COMPUTED_VALUE"""),430.55) -> 430.55 | AZ55: =IFERROR(__xludf.DUMMYFUNCTION("""COMPUTED_VALUE"""),434.4) -> 434.4 | BA55: =IFERROR(__xludf.DUMMYFUNCTION("""COMPUTED_VALUE"""),430.2) -> 430.2 | BB55: =IFERROR(__xludf.DUMMYFUNCTION("""COMPUTED_VALUE"""),432.3) -> 432.3 | BC55: =IFERROR(__xludf.DUMMYFUNCTION("""COMPUTED_VALUE"""),1.0352936E7) -> 10352936 | BD55: =LN(BB55/BB54) -> -0.0016179363
B56: 45456 | C56: 6233.71 | D56: 6248.12 | E56: 6165.52 | F56: 6186.12 | G56: - | H56: =LN(F56/F55) -> -0.0070875215 | N56: =IFERROR(__xludf.DUMMYFUNCTION("""COMPUTED_VALUE"""),45456.64583333333) -> 45456.646 | O56: =IFERROR(__xludf.DUMMYFUNCTION("""COMPUTED_VALUE"""),1122.2) -> 1122.2 | P56: =IFERROR(__xludf.DUMMYFUNCTION("""COMPUTED_VALUE"""),1123.2) -> 1123.2 | Q56: =IFERROR(__xludf.DUMMYFUNCTION("""COMPUTED_VALUE"""),1105.0) -> 1105 | R56: =IFERROR(__xludf.DUMMYFUNCTION("""COMPUTED_VALUE"""),1107.35) -> 1107.35 | S56: =IFERROR(__xludf.DUMMYFUNCTION("""COMPUTED_VALUE"""),1.2494254E7) -> 12494254 | T56: =LN(R56/R55) -> -0.010957045 | Z56: =IFERROR(__xludf.DUMMYFUNCTION("""COMPUTED_VALUE"""),45456.64583333333) -> 45456.646 | AA56: =IFERROR(__xludf.DUMMYFUNCTION("""COMPUTED_VALUE"""),344.1) -> 344.1 | AB56: =IFERROR(__xludf.DUMMYFUNCTION("""COMPUTED_VALUE"""),346.6) -> 346.6 | AC56: =IFERROR(__xludf.DUMMYFUNCTION("""COMPUTED_VALUE"""),337.0) -> 337 | AD56: =IFERROR(__xludf.DUMMYFUNCTION("""COMPUTED_VALUE"""),339.5) -> 339.5 | AE56: =IFERROR(__xludf.DUMMYFUNCTION("""COMPUTED_VALUE"""),7980545.0) -> 7980545 | AF56: =LN(AD56/AD55) -> -0.0077752904 | AL56: =IFERROR(__xludf.DUMMYFUNCTION("""COMPUTED_VALUE"""),45456.64583333333) -> 45456.646 | AM56: =IFERROR(__xludf.DUMMYFUNCTION("""COMPUTED_VALUE"""),4940.0) -> 4940 | AN56: =IFERROR(__xludf.DUMMYFUNCTION("""COMPUTED_VALUE"""),5117.55) -> 5117.55 | AO56: =IFERROR(__xludf.DUMMYFUNCTION("""COMPUTED_VALUE"""),4856.0) -> 4856 | AP56: =IFERROR(__xludf.DUMMYFUNCTION("""COMPUTED_VALUE"""),5099.7) -> 5099.7 | AQ56: =IFERROR(__xludf.DUMMYFUNCTION("""COMPUTED_VALUE"""),4364888.0) -> 4364888 | AR56: =LN(AP56/AP55) -> 0.042193931 | AX56: =IFERROR(__xludf.DUMMYFUNCTION("""COMPUTED_VALUE"""),45456.64583333333) -> 45456.646 | AY56: =IFERROR(__xludf.DUMMYFUNCTION("""COMPUTED_VALUE"""),436.9) -> 436.9 | AZ56: =IFERROR(__xludf.DUMMYFUNCTION("""COMPUTED_VALUE"""),436.9) -> 436.9 | BA56: =IFERROR(__xludf.DUMMYFUNCTION("""COMPUTED_VALUE"""),429.75) -> 429.75 | BB56: =IFERROR(__xludf.DUMMYFUNCTION("""COMPUTED_VALUE"""),430.3) -> 430.3 | BC56: =IFERROR(__xludf.DUMMYFUNCTION("""COMPUTED_VALUE"""),9283802.0) -> 9283802 | BD56: =LN(BB56/BB55) -> -0.0046371518
B57: 45457 | C57: 6186.78 | D57: 6276.12 | E57: 6180.12 | F57: 6265.12 | G57: - | H57: =LN(F57/F56) -> 0.012689669 | N57: =IFERROR(__xludf.DUMMYFUNCTION("""COMPUTED_VALUE"""),45457.64583333333) -> 45457.646 | O57: =IFERROR(__xludf.DUMMYFUNCTION("""COMPUTED_VALUE"""),1114.0) -> 1114 | P57: =IFERROR(__xludf.DUMMYFUNCTION("""COMPUTED_VALUE"""),1114.0) -> 1114 | Q57: =IFERROR(__xludf.DUMMYFUNCTION("""COMPUTED_VALUE"""),1099.45) -> 1099.45 | R57: =IFERROR(__xludf.DUMMYFUNCTION("""COMPUTED_VALUE"""),1105.65) -> 1105.65 | S57: =IFERROR(__xludf.DUMMYFUNCTION("""COMPUTED_VALUE"""),1.1377979E7) -> 11377979 | T57: =LN(R57/R56) -> -0.0015363763 | Z57: =IFERROR(__xludf.DUMMYFUNCTION("""COMPUTED_VALUE"""),45457.64583333333) -> 45457.646 | AA57: =IFERROR(__xludf.DUMMYFUNCTION("""COMPUTED_VALUE"""),340.0) -> 340 | AB57: =IFERROR(__xludf.DUMMYFUNCTION("""COMPUTED_VALUE"""),346.8) -> 346.8 | AC57: =IFERROR(__xludf.DUMMYFUNCTION("""COMPUTED_VALUE"""),338.5) -> 338.5 | AD57: =IFERROR(__xludf.DUMMYFUNCTION("""COMPUTED_VALUE"""),340.75) -> 340.75 | AE57: =IFERROR(__xludf.DUMMYFUNCTION("""COMPUTED_VALUE"""),1.2332822E7) -> 12332822 | AF57: =LN(AD57/AD56) -> 0.0036751236 | AL57: =IFERROR(__xludf.DUMMYFUNCTION("""COMPUTED_VALUE"""),45457.64583333333) -> 45457.646 | AM57: =IFERROR(__xludf.DUMMYFUNCTION("""COMPUTED_VALUE"""),5140.0) -> 5140 | AN57: =IFERROR(__xludf.DUMMYFUNCTION("""COMPUTED_VALUE"""),5260.0) -> 5260 | AO57: =IFERROR(__xludf.DUMMYFUNCTION("""COMPUTED_VALUE"""),5103.75) -> 5103.75 | AP57: =IFERROR(__xludf.DUMMYFUNCTION("""COMPUTED_VALUE"""),5200.55) -> 5200.55 | AQ57: =IFERROR(__xludf.DUMMYFUNCTION("""COMPUTED_VALUE"""),6319680.0) -> 6319680 | AR57: =LN(AP57/AP56) -> 0.019582675 | AX57: =IFERROR(__xludf.DUMMYFUNCTION("""COMPUTED_VALUE"""),45457.64583333333) -> 45457.646 | AY57: =IFERROR(__xludf.DUMMYFUNCTION("""COMPUTED_VALUE"""),431.0) -> 431 | AZ57: =IFERROR(__xludf.DUMMYFUNCTION("""COMPUTED_VALUE"""),431.9) -> 431.9 | BA57: =IFERROR(__xludf.DUMMYFUNCTION("""COMPUTED_VALUE"""),429.05) -> 429.05 | BB57: =IFERROR(__xludf.DUMMYFUNCTION("""COMPUTED_VALUE"""),431.15) -> 431.15 | BC57: =IFERROR(__xludf.DUMMYFUNCTION("""COMPUTED_VALUE"""),9217804.0) -> 9217804 | BD57: =LN(BB57/BB56) -> 0.0019734176
B58: 45461 | C58: 6225.52 | D58: 6253.12 | E58: 6185.52 | F58: 6239.12 | G58: - | H58: =LN(F58/F57) -> -0.0041585954 | N58: =IFERROR(__xludf.DUMMYFUNCTION("""COMPUTED_VALUE"""),45461.64583333333) -> 45461.646 | O58: =IFERROR(__xludf.DUMMYFUNCTION("""COMPUTED_VALUE"""),1113.95) -> 1113.95 | P58: =IFERROR(__xludf.DUMMYFUNCTION("""COMPUTED_VALUE"""),1135.05) -> 1135.05 | Q58: =IFERROR(__xludf.DUMMYFUNCTION("""COMPUTED_VALUE"""),1101.2) -> 1101.2 | R58: =IFERROR(__xludf.DUMMYFUNCTION("""COMPUTED_VALUE"""),1122.85) -> 1122.85 | S58: =IFERROR(__xludf.DUMMYFUNCTION("""COMPUTED_VALUE"""),1.8306176E7) -> 18306176 | T58: =LN(R58/R57) -> 0.015436699 | Z58: =IFERROR(__xludf.DUMMYFUNCTION("""COMPUTED_VALUE"""),45461.64583333333) -> 45461.646 | AA58: =IFERROR(__xludf.DUMMYFUNCTION("""COMPUTED_VALUE"""),335.3) -> 335.3 | AB58: =IFERROR(__xludf.DUMMYFUNCTION("""COMPUTED_VALUE"""),347.55) -> 347.55 | AC58: =IFERROR(__xludf.DUMMYFUNCTION("""COMPUTED_VALUE"""),331.65) -> 331.65 | AD58: =IFERROR(__xludf.DUMMYFUNCTION("""COMPUTED_VALUE"""),344.55) -> 344.55 | AE58: =IFERROR(__xludf.DUMMYFUNCTION("""COMPUTED_VALUE"""),1.7706369E7) -> 17706369 | AF58: =LN(AD58/AD57) -> 0.011090147 | AL58: =IFERROR(__xludf.DUMMYFUNCTION("""COMPUTED_VALUE"""),45461.64583333333) -> 45461.646 | AM58: =IFERROR(__xludf.DUMMYFUNCTION("""COMPUTED_VALUE"""),5460.1) -> 5460.1 | AN58: =IFERROR(__xludf.DUMMYFUNCTION("""COMPUTED_VALUE"""),5567.0) -> 5567 | AO58: =IFERROR(__xludf.DUMMYFUNCTION("""COMPUTED_VALUE"""),5389.5) -> 5389.5 | AP58: =IFERROR(__xludf.DUMMYFUNCTION("""COMPUTED_VALUE"""),5533.45) -> 5533.45 | AQ58: =IFERROR(__xludf.DUMMYFUNCTION("""COMPUTED_VALUE"""),9934132.0) -> 9934132 | AR58: =LN(AP58/AP57) -> 0.062047102 | AX58: =IFERROR(__xludf.DUMMYFUNCTION("""COMPUTED_VALUE"""),45461.64583333333) -> 45461.646 | AY58: =IFERROR(__xludf.DUMMYFUNCTION("""COMPUTED_VALUE"""),433.0) -> 433 | AZ58: =IFERROR(__xludf.DUMMYFUNCTION("""COMPUTED_VALUE"""),434.2) -> 434.2 | BA58: =IFERROR(__xludf.DUMMYFUNCTION("""COMPUTED_VALUE"""),428.2) -> 428.2 | BB58: =IFERROR(__xludf.DUMMYFUNCTION("""COMPUTED_VALUE"""),428.75) -> 428.75 | BC58: =IFERROR(__xludf.DUMMYFUNCTION("""COMPUTED_VALUE"""),1.4098178E7) -> 14098178 | BD58: =LN(BB58/BB57) -> -0.0055820589
B59: 45462 | C59: 6241.12 | D59: 6263.12 | E59: 6231.12 | F59: 6241.52 | G59: - | H59: =LN(F59/F58) -> 0.00038459567 | N59: =IFERROR(__xludf.DUMMYFUNCTION("""COMPUTED_VALUE"""),45462.64583333333) -> 45462.646 | O59: =IFERROR(__xludf.DUMMYFUNCTION("""COMPUTED_VALUE"""),1127.95) -> 1127.95 | P59: =IFERROR(__xludf.DUMMYFUNCTION("""COMPUTED_VALUE"""),1165.55) -> 1165.55 | Q59: =IFERROR(__xludf.DUMMYFUNCTION("""COMPUTED_VALUE"""),1126.15) -> 1126.15 | R59: =IFERROR(__xludf.DUMMYFUNCTION("""COMPUTED_VALUE"""),1144.45) -> 1144.45 | S59: =IFERROR(__xludf.DUMMYFUNCTION("""COMPUTED_VALUE"""),3.4309514E7) -> 34309514 | T59: =LN(R59/R58) -> 0.019054076 | Z59: =IFERROR(__xludf.DUMMYFUNCTION("""COMPUTED_VALUE"""),45462.64583333333) -> 45462.646 | AA59: =IFERROR(__xludf.DUMMYFUNCTION("""COMPUTED_VALUE"""),329.1) -> 329.1 | AB59: =IFERROR(__xludf.DUMMYFUNCTION("""COMPUTED_VALUE"""),341.95) -> 341.95 | AC59: =IFERROR(__xludf.DUMMYFUNCTION("""COMPUTED_VALUE"""),311.4) -> 311.4 | AD59: =IFERROR(__xludf.DUMMYFUNCTION("""COMPUTED_VALUE"""),334.0) -> 334 | AE59: =IFERROR(__xludf.DUMMYFUNCTION("""COMPUTED_VALUE"""),8.32154977E8) -> 832154977 | AF59: =LN(AD59/AD58) -> -0.031098225 | AL59: =IFERROR(__xludf.DUMMYFUNCTION("""COMPUTED_VALUE"""),45462.64583333333) -> 45462.646 | AM59: =IFERROR(__xludf.DUMMYFUNCTION("""COMPUTED_VALUE"""),5580.0) -> 5580 | AN59: =IFERROR(__xludf.DUMMYFUNCTION("""COMPUTED_VALUE"""),5582.8) -> 5582.8 | AO59: =IFERROR(__xludf.DUMMYFUNCTION("""COMPUTED_VALUE"""),5261.1) -> 5261.1 | AP59: =IFERROR(__xludf.DUMMYFUNCTION("""COMPUTED_VALUE"""),5311.95) -> 5311.95 | AQ59: =IFERROR(__xludf.DUMMYFUNCTION("""COMPUTED_VALUE"""),7351379.0) -> 7351379 | AR59: =LN(AP59/AP58) -> -0.040852491 | AX59: =IFERROR(__xludf.DUMMYFUNCTION("""COMPUTED_VALUE"""),45462.64583333333) -> 45462.646 | AY59: =IFERROR(__xludf.DUMMYFUNCTION("""COMPUTED_VALUE"""),430.0) -> 430 | AZ59: =IFERROR(__xludf.DUMMYFUNCTION("""COMPUTED_VALUE"""),430.75) -> 430.75 | BA59: =IFERROR(__xludf.DUMMYFUNCTION("""COMPUTED_VALUE"""),423.05) -> 423.05 | BB59: =IFERROR(__xludf.DUMMYFUNCTION("""COMPUTED_VALUE"""),423.65) -> 423.65 | BC59: =IFERROR(__xludf.DUMMYFUNCTION("""COMPUTED_VALUE"""),1.0909803E7) -> 10909803 | BD59: =LN(BB59/BB58) -> -0.011966356
B60: 45463 | C60: 6239.12 | D60: 6360.12 | E60: 6238.78 | F60: 6344.78 | G60: - | H60: =LN(F60/F59) -> 0.016408685 | N60: =IFERROR(__xludf.DUMMYFUNCTION("""COMPUTED_VALUE"""),45463.64583333333) -> 45463.646 | O60: =IFERROR(__xludf.DUMMYFUNCTION("""COMPUTED_VALUE"""),1154.05) -> 1154.05 | P60: =IFERROR(__xludf.DUMMYFUNCTION("""COMPUTED_VALUE"""),1160.0) -> 1160 | Q60: =IFERROR(__xludf.DUMMYFUNCTION("""COMPUTED_VALUE"""),1135.5) -> 1135.5 | R60: =IFERROR(__xludf.DUMMYFUNCTION("""COMPUTED_VALUE"""),1156.8) -> 1156.8 | S60: =IFERROR(__xludf.DUMMYFUNCTION("""COMPUTED_VALUE"""),1.5475933E7) -> 15475933 | T60: =LN(R60/R59) -> 0.0107334 | Z60: =IFERROR(__xludf.DUMMYFUNCTION("""COMPUTED_VALUE"""),45463.64583333333) -> 45463.646 | AA60: =IFERROR(__xludf.DUMMYFUNCTION("""COMPUTED_VALUE"""),335.75) -> 335.75 | AB60: =IFERROR(__xludf.DUMMYFUNCTION("""COMPUTED_VALUE"""),340.0) -> 340 | AC60: =IFERROR(__xludf.DUMMYFUNCTION("""COMPUTED_VALUE"""),334.0) -> 334 | AD60: =IFERROR(__xludf.DUMMYFUNCTION("""COMPUTED_VALUE"""),336.3) -> 336.3 | AE60: =IFERROR(__xludf.DUMMYFUNCTION("""COMPUTED_VALUE"""),2.6757768E7) -> 26757768 | AF60: =LN(AD60/AD59) -> 0.0068626258 | AL60: =IFERROR(__xludf.DUMMYFUNCTION("""COMPUTED_VALUE"""),45463.64583333333) -> 45463.646 | AM60: =IFERROR(__xludf.DUMMYFUNCTION("""COMPUTED_VALUE"""),5311.0) -> 5311 | AN60: =IFERROR(__xludf.DUMMYFUNCTION("""COMPUTED_VALUE"""),5381.3) -> 5381.3 | AO60: =IFERROR(__xludf.DUMMYFUNCTION("""COMPUTED_VALUE"""),5156.6) -> 5156.6 | AP60: =IFERROR(__xludf.DUMMYFUNCTION("""COMPUTED_VALUE"""),5288.6) -> 5288.6 | AQ60: =IFERROR(__xludf.DUMMYFUNCTION("""COMPUTED_VALUE"""),4867153.0) -> 4867153 | AR60: =LN(AP60/AP59) -> -0.0044054389 | AX60: =IFERROR(__xludf.DUMMYFUNCTION("""COMPUTED_VALUE"""),45463.64583333333) -> 45463.646 | AY60: =IFERROR(__xludf.DUMMYFUNCTION("""COMPUTED_VALUE"""),424.05) -> 424.05 | AZ60: =IFERROR(__xludf.DUMMYFUNCTION("""COMPUTED_VALUE"""),426.5) -> 426.5 | BA60: =IFERROR(__xludf.DUMMYFUNCTION("""COMPUTED_VALUE"""),421.5) -> 421.5 | BB60: =IFERROR(__xludf.DUMMYFUNCTION("""COMPUTED_VALUE"""),423.3) -> 423.3 | BC60: =IFERROR(__xludf.DUMMYFUNCTION("""COMPUTED_VALUE"""),1.4585806E7) -> 14585806 | BD60: =LN(BB60/BB59) -> -0.00082649512
B61: 45464 | C61: 6345.52 | D61: 6365.12 | E61: 6221.52 | F61: 6236.12 | G61: - | H61: =LN(F61/F60) -> -0.017274233 | N61: =IFERROR(__xludf.DUMMYFUNCTION("""COMPUTED_VALUE"""),45464.64583333333) -> 45464.646 | O61: =IFERROR(__xludf.DUMMYFUNCTION("""COMPUTED_VALUE"""),1163.55) -> 1163.55 | P61: =IFERROR(__xludf.DUMMYFUNCTION("""COMPUTED_VALUE"""),1169.9) -> 1169.9 | Q61: =IFERROR(__xludf.DUMMYFUNCTION("""COMPUTED_VALUE"""),1150.65) -> 1150.65 | R61: =IFERROR(__xludf.DUMMYFUNCTION("""COMPUTED_VALUE"""),1158.65) -> 1158.65 | S61: =IFERROR(__xludf.DUMMYFUNCTION("""COMPUTED_VALUE"""),6.9259425E7) -> 69259425 | T61: =LN(R61/R60) -> 0.0015979619 | Z61: =IFERROR(__xludf.DUMMYFUNCTION("""COMPUTED_VALUE"""),45464.64583333333) -> 45464.646 | AA61: =IFERROR(__xludf.DUMMYFUNCTION("""COMPUTED_VALUE"""),337.75) -> 337.75 | AB61: =IFERROR(__xludf.DUMMYFUNCTION("""COMPUTED_VALUE"""),339.45) -> 339.45 | AC61: =IFERROR(__xludf.DUMMYFUNCTION("""COMPUTED_VALUE"""),330.1) -> 330.1 | AD61: =IFERROR(__xludf.DUMMYFUNCTION("""COMPUTED_VALUE"""),336.45) -> 336.45 | AE61: =IFERROR(__xludf.DUMMYFUNCTION("""COMPUTED_VALUE"""),3.894098E7) -> 38940980 | AF61: =LN(AD61/AD60) -> 0.00044593089 | AL61: =IFERROR(__xludf.DUMMYFUNCTION("""COMPUTED_VALUE"""),45464.64583333333) -> 45464.646 | AM61: =IFERROR(__xludf.DUMMYFUNCTION("""COMPUTED_VALUE"""),5298.5) -> 5298.5 | AN61: =IFERROR(__xludf.DUMMYFUNCTION("""COMPUTED_VALUE"""),5341.5) -> 5341.5 | AO61: =IFERROR(__xludf.DUMMYFUNCTION("""COMPUTED_VALUE"""),5151.0) -> 5151 | AP61: =IFERROR(__xludf.DUMMYFUNCTION("""COMPUTED_VALUE"""),5170.55) -> 5170.55 | AQ61: =IFERROR(__xludf.DUMMYFUNCTION("""COMPUTED_VALUE"""),4063083.0) -> 4063083 | AR61: =LN(AP61/AP60) -> -0.022574495 | AX61: =IFERROR(__xludf.DUMMYFUNCTION("""COMPUTED_VALUE"""),45464.64583333333) -> 45464.646 | AY61: =IFERROR(__xludf.DUMMYFUNCTION("""COMPUTED_VALUE"""),425.0) -> 425 | AZ61: =IFERROR(__xludf.DUMMYFUNCTION("""COMPUTED_VALUE"""),425.3) -> 425.3 | BA61: =IFERROR(__xludf.DUMMYFUNCTION("""COMPUTED_VALUE"""),418.55) -> 418.55 | BB61: =IFERROR(__xludf.DUMMYFUNCTION("""COMPUTED_VALUE"""),419.6) -> 419.6 | BC61: =IFERROR(__xludf.DUMMYFUNCTION("""COMPUTED_VALUE"""),2.5205627E7) -> 25205627 | BD61: =LN(BB61/BB60) -> -0.008779271
B62: 45467 | C62: 6236.78 | D62: 6266.12 | E62: 6225.12 | F62: 6259.12 | G62: - | H62: =LN(F62/F61) -> 0.003681406 | N62: =IFERROR(__xludf.DUMMYFUNCTION("""COMPUTED_VALUE"""),45467.64583333333) -> 45467.646 | O62: =IFERROR(__xludf.DUMMYFUNCTION("""COMPUTED_VALUE"""),1154.65) -> 1154.65 | P62: =IFERROR(__xludf.DUMMYFUNCTION("""COMPUTED_VALUE"""),1175.65) -> 1175.65 | Q62: =IFERROR(__xludf.DUMMYFUNCTION("""COMPUTED_VALUE"""),1152.65) -> 1152.65 | R62: =IFERROR(__xludf.DUMMYFUNCTION("""COMPUTED_VALUE"""),1170.1) -> 1170.1 | S62: =IFERROR(__xludf.DUMMYFUNCTION("""COMPUTED_VALUE"""),1.2210295E7) -> 12210295 | T62: =LN(R62/R61) -> 0.009833681 | Z62: =IFERROR(__xludf.DUMMYFUNCTION("""COMPUTED_VALUE"""),45467.64583333333) -> 45467.646 | AA62: =IFERROR(__xludf.DUMMYFUNCTION("""COMPUTED_VALUE"""),338.95) -> 338.95 | AB62: =IFERROR(__xludf.DUMMYFUNCTION("""COMPUTED_VALUE"""),341.6) -> 341.6 | AC62: =IFERROR(__xludf.DUMMYFUNCTION("""COMPUTED_VALUE"""),331.25) -> 331.25 | AD62: =IFERROR(__xludf.DUMMYFUNCTION("""COMPUTED_VALUE"""),339.85) -> 339.85 | AE62: =IFERROR(__xludf.DUMMYFUNCTION("""COMPUTED_VALUE"""),2.7730484E7) -> 27730484 | AF62: =LN(AD62/AD61) -> 0.010054794 | AL62: =IFERROR(__xludf.DUMMYFUNCTION("""COMPUTED_VALUE"""),45467.64583333333) -> 45467.646 | AM62: =IFERROR(__xludf.DUMMYFUNCTION("""COMPUTED_VALUE"""),5170.0) -> 5170 | AN62: =IFERROR(__xludf.DUMMYFUNCTION("""COMPUTED_VALUE"""),5344.4) -> 5344.4 | AO62: =IFERROR(__xludf.DUMMYFUNCTION("""COMPUTED_VALUE"""),5114.6) -> 5114.6 | AP62: =IFERROR(__xludf.DUMMYFUNCTION("""COMPUTED_VALUE"""),5325.05) -> 5325.05 | AQ62: =IFERROR(__xludf.DUMMYFUNCTION("""COMPUTED_VALUE"""),3699083.0) -> 3699083 | AR62: =LN(AP62/AP61) -> 0.029443035 | AX62: =IFERROR(__xludf.DUMMYFUNCTION("""COMPUTED_VALUE"""),45467.64583333333) -> 45467.646 | AY62: =IFERROR(__xludf.DUMMYFUNCTION("""COMPUTED_VALUE"""),420.0) -> 420 | AZ62: =IFERROR(__xludf.DUMMYFUNCTION("""COMPUTED_VALUE"""),423.95) -> 423.95 | BA62: =IFERROR(__xludf.DUMMYFUNCTION("""COMPUTED_VALUE"""),420.0) -> 420 | BB62: =IFERROR(__xludf.DUMMYFUNCTION("""COMPUTED_VALUE"""),423.3) -> 423.3 | BC62: =IFERROR(__xludf.DUMMYFUNCTION("""COMPUTED_VALUE"""),9362433.0) -> 9362433 | BD62: =LN(BB62/BB61) -> 0.008779271
B63: 45468 | C63: 6264.78 | D63: 6270.12 | E63: 6211.12 | F63: 6218.78 | G63: - | H63: =LN(F63/F62) -> -0.0064658541 | N63: =IFERROR(__xludf.DUMMYFUNCTION("""COMPUTED_VALUE"""),45468.64583333333) -> 45468.646 | O63: =IFERROR(__xludf.DUMMYFUNCTION("""COMPUTED_VALUE"""),1170.25) -> 1170.25 | P63: =IFERROR(__xludf.DUMMYFUNCTION("""COMPUTED_VALUE"""),1206.0) -> 1206 | Q63: =IFERROR(__xludf.DUMMYFUNCTION("""COMPUTED_VALUE"""),1167.65) -> 1167.65 | R63: =IFERROR(__xludf.DUMMYFUNCTION("""COMPUTED_VALUE"""),1197.95) -> 1197.95 | S63: =IFERROR(__xludf.DUMMYFUNCTION("""COMPUTED_VALUE"""),2.7309845E7) -> 27309845 | T63: =LN(R63/R62) -> 0.023522547 | Z63: =IFERROR(__xludf.DUMMYFUNCTION("""COMPUTED_VALUE"""),45468.64583333333) -> 45468.646 | AA63: =IFERROR(__xludf.DUMMYFUNCTION("""COMPUTED_VALUE"""),342.95) -> 342.95 | AB63: =IFERROR(__xludf.DUMMYFUNCTION("""COMPUTED_VALUE"""),344.95) -> 344.95 | AC63: =IFERROR(__xludf.DUMMYFUNCTION("""COMPUTED_VALUE"""),341.0) -> 341 | AD63: =IFERROR(__xludf.DUMMYFUNCTION("""COMPUTED_VALUE"""),344.2) -> 344.2 | AE63: =IFERROR(__xludf.DUMMYFUNCTION("""COMPUTED_VALUE"""),2.0205939E7) -> 20205939 | AF63: =LN(AD63/AD62) -> 0.01271854 | AL63: =IFERROR(__xludf.DUMMYFUNCTION("""COMPUTED_VALUE"""),45468.64583333333) -> 45468.646 | AM63: =IFERROR(__xludf.DUMMYFUNCTION("""COMPUTED_VALUE"""),5375.0) -> 5375 | AN63: =IFERROR(__xludf.DUMMYFUNCTION("""COMPUTED_VALUE"""),5455.0) -> 5455 | AO63: =IFERROR(__xludf.DUMMYFUNCTION("""COMPUTED_VALUE"""),5330.0) -> 5330 | AP63: =IFERROR(__xludf.DUMMYFUNCTION("""COMPUTED_VALUE"""),5371.65) -> 5371.65 | AQ63: =IFERROR(__xludf.DUMMYFUNCTION("""COMPUTED_VALUE"""),3493916.0) -> 3493916 | AR63: =LN(AP63/AP62) -> 0.0087130227 | AX63: =IFERROR(__xludf.DUMMYFUNCTION("""COMPUTED_VALUE"""),45468.64583333333) -> 45468.646 | AY63: =IFERROR(__xludf.DUMMYFUNCTION("""COMPUTED_VALUE"""),423.0) -> 423 | AZ63: =IFERROR(__xludf.DUMMYFUNCTION("""COMPUTED_VALUE"""),424.0) -> 424 | BA63: =IFERROR(__xludf.DUMMYFUNCTION("""COMPUTED_VALUE"""),419.75) -> 419.75 | BB63: =IFERROR(__xludf.DUMMYFUNCTION("""COMPUTED_VALUE"""),423.3) -> 423.3 | BC63: =IFERROR(__xludf.DUMMYFUNCTION("""COMPUTED_VALUE"""),1.0260449E7) -> 10260449 | BD63: =LN(BB63/BB62) -> 0
B64: 45469 | C64: 6221.52 | D64: 6231.52 | E64: 6161.12 | F64: 6168.78 | G64: - | H64: =LN(F64/F63) -> -0.0080726586 | N64: =IFERROR(__xludf.DUMMYFUNCTION("""COMPUTED_VALUE"""),45469.64583333333) -> 45469.646 | O64: =IFERROR(__xludf.DUMMYFUNCTION("""COMPUTED_VALUE"""),1202.0) -> 1202 | P64: =IFERROR(__xludf.DUMMYFUNCTION("""COMPUTED_VALUE"""),1222.85) -> 1222.85 | Q64: =IFERROR(__xludf.DUMMYFUNCTION("""COMPUTED_VALUE"""),1193.85) -> 1193.85 | R64: =IFERROR(__xludf.DUMMYFUNCTION("""COMPUTED_VALUE"""),1218.0) -> 1218 | S64: =IFERROR(__xludf.DUMMYFUNCTION("""COMPUTED_VALUE"""),2.5403461E7) -> 25403461 | T64: =LN(R64/R63) -> 0.016598407 | Z64: =IFERROR(__xludf.DUMMYFUNCTION("""COMPUTED_VALUE"""),45469.64583333333) -> 45469.646 | AA64: =IFERROR(__xludf.DUMMYFUNCTION("""COMPUTED_VALUE"""),346.0) -> 346 | AB64: =IFERROR(__xludf.DUMMYFUNCTION("""COMPUTED_VALUE"""),358.0) -> 358 | AC64: =IFERROR(__xludf.DUMMYFUNCTION("""COMPUTED_VALUE"""),340.85) -> 340.85 | AD64: =IFERROR(__xludf.DUMMYFUNCTION("""COMPUTED_VALUE"""),356.1) -> 356.1 | AE64: =IFERROR(__xludf.DUMMYFUNCTION("""COMPUTED_VALUE"""),4.137898E7) -> 41378980 | AF64: =LN(AD64/AD63) -> 0.033988707 | AL64: =IFERROR(__xludf.DUMMYFUNCTION("""COMPUTED_VALUE"""),45469.64583333333) -> 45469.646 | AM64: =IFERROR(__xludf.DUMMYFUNCTION("""COMPUTED_VALUE"""),5367.55) -> 5367.55 | AN64: =IFERROR(__xludf.DUMMYFUNCTION("""COMPUTED_VALUE"""),5410.0) -> 5410 | AO64: =IFERROR(__xludf.DUMMYFUNCTION("""COMPUTED_VALUE"""),5274.6) -> 5274.6 | AP64: =IFERROR(__xludf.DUMMYFUNCTION("""COMPUTED_VALUE"""),5285.45) -> 5285.45 | AQ64: =IFERROR(__xludf.DUMMYFUNCTION("""COMPUTED_VALUE"""),2351908.0) -> 2351908 | AR64: =LN(AP64/AP63) -> -0.016177362 | AX64: =IFERROR(__xludf.DUMMYFUNCTION("""COMPUTED_VALUE"""),45469.64583333333) -> 45469.646 | AY64: =IFERROR(__xludf.DUMMYFUNCTION("""COMPUTED_VALUE"""),423.0) -> 423 | AZ64: =IFERROR(__xludf.DUMMYFUNCTION("""COMPUTED_VALUE"""),426.4) -> 426.4 | BA64: =IFERROR(__xludf.DUMMYFUNCTION("""COMPUTED_VALUE"""),422.05) -> 422.05 | BB64: =IFERROR(__xludf.DUMMYFUNCTION("""COMPUTED_VALUE"""),423.95) -> 423.95 | BC64: =IFERROR(__xludf.DUMMYFUNCTION("""COMPUTED_VALUE"""),1.1084805E7) -> 11084805 | BD64: =LN(BB64/BB63) -> 0.0015343762
B65: 45470 | C65: 6173.52 | D65: 6254.18 | E65: 6165.12 | F65: 6243.71 | G65: - | H65: =LN(F65/F64) -> 0.01207347 | N65: =IFERROR(__xludf.DUMMYFUNCTION("""COMPUTED_VALUE"""),45470.64583333333) -> 45470.646 | O65: =IFERROR(__xludf.DUMMYFUNCTION("""COMPUTED_VALUE"""),1228.35) -> 1228.35 | P65: =IFERROR(__xludf.DUMMYFUNCTION("""COMPUTED_VALUE"""),1235.0) -> 1235 | Q65: =IFERROR(__xludf.DUMMYFUNCTION("""COMPUTED_VALUE"""),1209.1) -> 1209.1 | R65: =IFERROR(__xludf.DUMMYFUNCTION("""COMPUTED_VALUE"""),1219.9) -> 1219.9 | S65: =IFERROR(__xludf.DUMMYFUNCTION("""COMPUTED_VALUE"""),2.0516632E7) -> 20516632 | T65: =LN(R65/R64) -> 0.0015587189 | Z65: =IFERROR(__xludf.DUMMYFUNCTION("""COMPUTED_VALUE"""),45470.64583333333) -> 45470.646 | AA65: =IFERROR(__xludf.DUMMYFUNCTION("""COMPUTED_VALUE"""),363.0) -> 363 | AB65: =IFERROR(__xludf.DUMMYFUNCTION("""COMPUTED_VALUE"""),369.2) -> 369.2 | AC65: =IFERROR(__xludf.DUMMYFUNCTION("""COMPUTED_VALUE"""),351.3) -> 351.3 | AD65: =IFERROR(__xludf.DUMMYFUNCTION("""COMPUTED_VALUE"""),365.15) -> 365.15 | AE65: =IFERROR(__xludf.DUMMYFUNCTION("""COMPUTED_VALUE"""),7.024177E7) -> 70241770 | AF65: =LN(AD65/AD64) -> 0.025096638 | AL65: =IFERROR(__xludf.DUMMYFUNCTION("""COMPUTED_VALUE"""),45470.64583333333) -> 45470.646 | AM65: =IFERROR(__xludf.DUMMYFUNCTION("""COMPUTED_VALUE"""),5265.0) -> 5265 | AN65: =IFERROR(__xludf.DUMMYFUNCTION("""COMPUTED_VALUE"""),5309.45) -> 5309.45 | AO65: =IFERROR(__xludf.DUMMYFUNCTION("""COMPUTED_VALUE"""),5213.0) -> 5213 | AP65: =IFERROR(__xludf.DUMMYFUNCTION("""COMPUTED_VALUE"""),5281.5) -> 5281.5 | AQ65: =IFERROR(__xludf.DUMMYFUNCTION("""COMPUTED_VALUE"""),2864946.0) -> 2864946 | AR65: =LN(AP65/AP64) -> -0.00074761406 | AX65: =IFERROR(__xludf.DUMMYFUNCTION("""COMPUTED_VALUE"""),45470.64583333333) -> 45470.646 | AY65: =IFERROR(__xludf.DUMMYFUNCTION("""COMPUTED_VALUE"""),423.95) -> 423.95 | AZ65: =IFERROR(__xludf.DUMMYFUNCTION("""COMPUTED_VALUE"""),427.25) -> 427.25 | BA65: =IFERROR(__xludf.DUMMYFUNCTION("""COMPUTED_VALUE"""),421.1) -> 421.1 | BB65: =IFERROR(__xludf.DUMMYFUNCTION("""COMPUTED_VALUE"""),425.6) -> 425.6 | BC65: =IFERROR(__xludf.DUMMYFUNCTION("""COMPUTED_VALUE"""),3.7012589E7) -> 37012589 | BD65: =LN(BB65/BB64) -> 0.0038844143
B66: 45471 | C66: 6245.52 | D66: 6269.52 | E66: 6220.78 | F66: 6234.78 | G66: - | H66: =LN(F66/F65) -> -0.0014312632 | N66: =IFERROR(__xludf.DUMMYFUNCTION("""COMPUTED_VALUE"""),45471.64583333333) -> 45471.646 | O66: =IFERROR(__xludf.DUMMYFUNCTION("""COMPUTED_VALUE"""),1227.0) -> 1227 | P66: =IFERROR(__xludf.DUMMYFUNCTION("""COMPUTED_VALUE"""),1227.0) -> 1227 | Q66: =IFERROR(__xludf.DUMMYFUNCTION("""COMPUTED_VALUE"""),1196.35) -> 1196.35 | R66: =IFERROR(__xludf.DUMMYFUNCTION("""COMPUTED_VALUE"""),1199.6) -> 1199.6 | S66: =IFERROR(__xludf.DUMMYFUNCTION("""COMPUTED_VALUE"""),1.2507092E7) -> 12507092 | T66: =LN(R66/R65) -> -0.01678072 | Z66: =IFERROR(__xludf.DUMMYFUNCTION("""COMPUTED_VALUE"""),45471.64583333333) -> 45471.646 | AA66: =IFERROR(__xludf.DUMMYFUNCTION("""COMPUTED_VALUE"""),374.0) -> 374 | AB66: =IFERROR(__xludf.DUMMYFUNCTION("""COMPUTED_VALUE"""),384.8) -> 384.8 | AC66: =IFERROR(__xludf.DUMMYFUNCTION("""COMPUTED_VALUE"""),370.0) -> 370 | AD66: =IFERROR(__xludf.DUMMYFUNCTION("""COMPUTED_VALUE"""),375.3) -> 375.3 | AE66: =IFERROR(__xludf.DUMMYFUNCTION("""COMPUTED_VALUE"""),7.5125583E7) -> 75125583 | AF66: =LN(AD66/AD65) -> 0.027417478 | AL66: =IFERROR(__xludf.DUMMYFUNCTION("""COMPUTED_VALUE"""),45471.64583333333) -> 45471.646 | AM66: =IFERROR(__xludf.DUMMYFUNCTION("""COMPUTED_VALUE"""),5299.0) -> 5299 | AN66: =IFERROR(__xludf.DUMMYFUNCTION("""COMPUTED_VALUE"""),5344.0) -> 5344 | AO66: =IFERROR(__xludf.DUMMYFUNCTION("""COMPUTED_VALUE"""),5250.05) -> 5250.05 | AP66: =IFERROR(__xludf.DUMMYFUNCTION("""COMPUTED_VALUE"""),5264.25) -> 5264.25 | AQ66: =IFERROR(__xludf.DUMMYFUNCTION("""COMPUTED_VALUE"""),1565629.0) -> 1565629 | AR66: =LN(AP66/AP65) -> -0.003271463 | AX66: =IFERROR(__xludf.DUMMYFUNCTION("""COMPUTED_VALUE"""),45471.64583333333) -> 45471.646 | AY66: =IFERROR(__xludf.DUMMYFUNCTION("""COMPUTED_VALUE"""),425.5) -> 425.5 | AZ66: =IFERROR(__xludf.DUMMYFUNCTION("""COMPUTED_VALUE"""),428.0) -> 428 | BA66: =IFERROR(__xludf.DUMMYFUNCTION("""COMPUTED_VALUE"""),423.5) -> 423.5 | BB66: =IFERROR(__xludf.DUMMYFUNCTION("""COMPUTED_VALUE"""),424.9) -> 424.9 | BC66: =IFERROR(__xludf.DUMMYFUNCTION("""COMPUTED_VALUE"""),1.7866326E7) -> 17866326 | BD66: =LN(BB66/BB65) -> -0.0016460909
B67: 45474 | C67: 6234.78 | D67: 6274.12 | E67: 6218.78 | F67: 6253.71 | G67: - | H67: =LN(F67/F66) -> 0.0030315938 | N67: =IFERROR(__xludf.DUMMYFUNCTION("""COMPUTED_VALUE"""),45474.64583333333) -> 45474.646 | O67: =IFERROR(__xludf.DUMMYFUNCTION("""COMPUTED_VALUE"""),1199.6) -> 1199.6 | P67: =IFERROR(__xludf.DUMMYFUNCTION("""COMPUTED_VALUE"""),1215.35) -> 1215.35 | Q67: =IFERROR(__xludf.DUMMYFUNCTION("""COMPUTED_VALUE"""),1192.05) -> 1192.05 | R67: =IFERROR(__xludf.DUMMYFUNCTION("""COMPUTED_VALUE"""),1211.85) -> 1211.85 | S67: =IFERROR(__xludf.DUMMYFUNCTION("""COMPUTED_VALUE"""),8636894.0) -> 8636894 | T67: =LN(R67/R66) -> 0.01015995 | Z67: =IFERROR(__xludf.DUMMYFUNCTION("""COMPUTED_VALUE"""),45474.64583333333) -> 45474.646 | AA67: =IFERROR(__xludf.DUMMYFUNCTION("""COMPUTED_VALUE"""),377.0) -> 377 | AB67: =IFERROR(__xludf.DUMMYFUNCTION("""COMPUTED_VALUE"""),391.0) -> 391 | AC67: =IFERROR(__xludf.DUMMYFUNCTION("""COMPUTED_VALUE"""),372.75) -> 372.75 | AD67: =IFERROR(__xludf.DUMMYFUNCTION("""COMPUTED_VALUE"""),389.65) -> 389.65 | AE67: =IFERROR(__xludf.DUMMYFUNCTION("""COMPUTED_VALUE"""),3.2581017E7) -> 32581017 | AF67: =LN(AD67/AD66) -> 0.037523194 | AL67: =IFERROR(__xludf.DUMMYFUNCTION("""COMPUTED_VALUE"""),45474.64583333333) -> 45474.646 | AM67: =IFERROR(__xludf.DUMMYFUNCTION("""COMPUTED_VALUE"""),5270.0) -> 5270 | AN67: =IFERROR(__xludf.DUMMYFUNCTION("""COMPUTED_VALUE"""),5409.0) -> 5409 | AO67: =IFERROR(__xludf.DUMMYFUNCTION("""COMPUTED_VALUE"""),5253.3) -> 5253.3 | AP67: =IFERROR(__xludf.DUMMYFUNCTION("""COMPUTED_VALUE"""),5394.05) -> 5394.05 | AQ67: =IFERROR(__xludf.DUMMYFUNCTION("""COMPUTED_VALUE"""),2307080.0) -> 2307080 | AR67: =LN(AP67/AP66) -> 0.024357809 | AX67: =IFERROR(__xludf.DUMMYFUNCTION("""COMPUTED_VALUE"""),45474.64583333333) -> 45474.646 | AY67: =IFERROR(__xludf.DUMMYFUNCTION("""COMPUTED_VALUE"""),426.3) -> 426.3 | AZ67: =IFERROR(__xludf.DUMMYFUNCTION("""COMPUTED_VALUE"""),430.25) -> 430.25 | BA67: =IFERROR(__xludf.DUMMYFUNCTION("""COMPUTED_VALUE"""),424.65) -> 424.65 | BB67: =IFERROR(__xludf.DUMMYFUNCTION("""COMPUTED_VALUE"""),429.05) -> 429.05 | BC67: =IFERROR(__xludf.DUMMYFUNCTION("""COMPUTED_VALUE"""),1.2894747E7) -> 12894747 | BD67: =LN(BB67/BB66) -> 0.0097196151
B68: 45475 | C68: 6257.12 | D68: 6268.78 | E68: 6222.78 | F68: 6252.52 | G68: - | H68: =LN(F68/F67) -> -0.00019030515 | N68: =IFERROR(__xludf.DUMMYFUNCTION("""COMPUTED_VALUE"""),45475.64583333333) -> 45475.646 | O68: =IFERROR(__xludf.DUMMYFUNCTION("""COMPUTED_VALUE"""),1217.0) -> 1217 | P68: =IFERROR(__xludf.DUMMYFUNCTION("""COMPUTED_VALUE"""),1217.0) -> 1217 | Q68: =IFERROR(__xludf.DUMMYFUNCTION("""COMPUTED_VALUE"""),1185.55) -> 1185.55 | R68: =IFERROR(__xludf.DUMMYFUNCTION("""COMPUTED_VALUE"""),1190.6) -> 1190.6 | S68: =IFERROR(__xludf.DUMMYFUNCTION("""COMPUTED_VALUE"""),1.6153925E7) -> 16153925 | T68: =LN(R68/R67) -> -0.017690736 | Z68: =IFERROR(__xludf.DUMMYFUNCTION("""COMPUTED_VALUE"""),45475.64583333333) -> 45475.646 | AA68: =IFERROR(__xludf.DUMMYFUNCTION("""COMPUTED_VALUE"""),391.6) -> 391.6 | AB68: =IFERROR(__xludf.DUMMYFUNCTION("""COMPUTED_VALUE"""),396.5) -> 396.5 | AC68: =IFERROR(__xludf.DUMMYFUNCTION("""COMPUTED_VALUE"""),379.8) -> 379.8 | AD68: =IFERROR(__xludf.DUMMYFUNCTION("""COMPUTED_VALUE"""),383.8) -> 383.8 | AE68: =IFERROR(__xludf.DUMMYFUNCTION("""COMPUTED_VALUE"""),2.7609215E7) -> 27609215 | AF68: =LN(AD68/AD67) -> -0.015127317 | AL68: =IFERROR(__xludf.DUMMYFUNCTION("""COMPUTED_VALUE"""),45475.64583333333) -> 45475.646 | AM68: =IFERROR(__xludf.DUMMYFUNCTION("""COMPUTED_VALUE"""),5400.0) -> 5400 | AN68: =IFERROR(__xludf.DUMMYFUNCTION("""COMPUTED_VALUE"""),5420.0) -> 5420 | AO68: =IFERROR(__xludf.DUMMYFUNCTION("""COMPUTED_VALUE"""),5300.0) -> 5300 | AP68: =IFERROR(__xludf.DUMMYFUNCTION("""COMPUTED_VALUE"""),5344.05) -> 5344.05 | AQ68: =IFERROR(__xludf.DUMMYFUNCTION("""COMPUTED_VALUE"""),1706329.0) -> 1706329 | AR68: =LN(AP68/AP67) -> -0.0093127018 | AX68: =IFERROR(__xludf.DUMMYFUNCTION("""COMPUTED_VALUE"""),45475.64583333333) -> 45475.646 | AY68: =IFERROR(__xludf.DUMMYFUNCTION("""COMPUTED_VALUE"""),430.0) -> 430 | AZ68: =IFERROR(__xludf.DUMMYFUNCTION("""COMPUTED_VALUE"""),430.65) -> 430.65 | BA68: =IFERROR(__xludf.DUMMYFUNCTION("""COMPUTED_VALUE"""),422.55) -> 422.55 | BB68: =IFERROR(__xludf.DUMMYFUNCTION("""COMPUTED_VALUE"""),425.5) -> 425.5 | BC68: =IFERROR(__xludf.DUMMYFUNCTION("""COMPUTED_VALUE"""),1.0763335E7) -> 10763335 | BD68: =LN(BB68/BB67) -> -0.0083085142
B69: 45476 | C69: 6254.18 | D69: 6347.12 | E69: 6246.85 | F69: 6325.52 | G69: - | H69: =LN(F69/F68) -> 0.011607662 | N69: =IFERROR(__xludf.DUMMYFUNCTION("""COMPUTED_VALUE"""),45476.64583333333) -> 45476.646 | O69: =IFERROR(__xludf.DUMMYFUNCTION("""COMPUTED_VALUE"""),1196.85) -> 1196.85 | P69: =IFERROR(__xludf.DUMMYFUNCTION("""COMPUTED_VALUE"""),1215.85) -> 1215.85 | Q69: =IFERROR(__xludf.DUMMYFUNCTION("""COMPUTED_VALUE"""),1179.45) -> 1179.45 | R69: =IFERROR(__xludf.DUMMYFUNCTION("""COMPUTED_VALUE"""),1201.6) -> 1201.6 | S69: =IFERROR(__xludf.DUMMYFUNCTION("""COMPUTED_VALUE"""),2.2330897E7) -> 22330897 | T69: =LN(R69/R68) -> 0.0091966203 | Z69: =IFERROR(__xludf.DUMMYFUNCTION("""COMPUTED_VALUE"""),45476.64583333333) -> 45476.646 | AA69: =IFERROR(__xludf.DUMMYFUNCTION("""COMPUTED_VALUE"""),389.0) -> 389 | AB69: =IFERROR(__xludf.DUMMYFUNCTION("""COMPUTED_VALUE"""),397.45) -> 397.45 | AC69: =IFERROR(__xludf.DUMMYFUNCTION("""COMPUTED_VALUE"""),385.0) -> 385 | AD69: =IFERROR(__xludf.DUMMYFUNCTION("""COMPUTED_VALUE"""),396.5) -> 396.5 | AE69: =IFERROR(__xludf.DUMMYFUNCTION("""COMPUTED_VALUE"""),2.0902391E7) -> 20902391 | AF69: =LN(AD69/AD68) -> 0.032554458 | AL69: =IFERROR(__xludf.DUMMYFUNCTION("""COMPUTED_VALUE"""),45476.64583333333) -> 45476.646 | AM69: =IFERROR(__xludf.DUMMYFUNCTION("""COMPUTED_VALUE"""),5366.95) -> 5366.95 | AN69: =IFERROR(__xludf.DUMMYFUNCTION("""COMPUTED_VALUE"""),5480.0) -> 5480 | AO69: =IFERROR(__xludf.DUMMYFUNCTION("""COMPUTED_VALUE"""),5331.45) -> 5331.45 | AP69: =IFERROR(__xludf.DUMMYFUNCTION("""COMPUTED_VALUE"""),5459.3) -> 5459.3 | AQ69: =IFERROR(__xludf.DUMMYFUNCTION("""COMPUTED_VALUE"""),2852572.0) -> 2852572 | AR69: =LN(AP69/AP68) -> 0.021336784 | AX69: =IFERROR(__xludf.DUMMYFUNCTION("""COMPUTED_VALUE"""),45476.64583333333) -> 45476.646 | AY69: =IFERROR(__xludf.DUMMYFUNCTION("""COMPUTED_VALUE"""),426.1) -> 426.1 | AZ69: =IFERROR(__xludf.DUMMYFUNCTION("""COMPUTED_VALUE"""),429.65) -> 429.65 | BA69: =IFERROR(__xludf.DUMMYFUNCTION("""COMPUTED_VALUE"""),425.5) -> 425.5 | BB69: =IFERROR(__xludf.DUMMYFUNCTION("""COMPUTED_VALUE"""),428.3) -> 428.3 | BC69: =IFERROR(__xludf.DUMMYFUNCTION("""COMPUTED_VALUE"""),7159756.0) -> 7159756 | BD69: =LN(BB69/BB68) -> 0.0065589366
B70: 45477 | C70: 6326.85 | D70: 6343.12 | E70: 6311.52 | F70: 6322.78 | G70: - | H70: =LN(F70/F69) -> -0.00043325981 | N70: =IFERROR(__xludf.DUMMYFUNCTION("""COMPUTED_VALUE"""),45477.64583333333) -> 45477.646 | O70: =IFERROR(__xludf.DUMMYFUNCTION("""COMPUTED_VALUE"""),1229.0) -> 1229 | P70: =IFERROR(__xludf.DUMMYFUNCTION("""COMPUTED_VALUE"""),1234.95) -> 1234.95 | Q70: =IFERROR(__xludf.DUMMYFUNCTION("""COMPUTED_VALUE"""),1214.3) -> 1214.3 | R70: =IFERROR(__xludf.DUMMYFUNCTION("""COMPUTED_VALUE"""),1233.0) -> 1233 | S70: =IFERROR(__xludf.DUMMYFUNCTION("""COMPUTED_VALUE"""),1.5275791E7) -> 15275791 | T70: =LN(R70/R69) -> 0.025796222 | Z70: =IFERROR(__xludf.DUMMYFUNCTION("""COMPUTED_VALUE"""),45477.64583333333) -> 45477.646 | AA70: =IFERROR(__xludf.DUMMYFUNCTION("""COMPUTED_VALUE"""),398.4) -> 398.4 | AB70: =IFERROR(__xludf.DUMMYFUNCTION("""COMPUTED_VALUE"""),408.4) -> 408.4 | AC70: =IFERROR(__xludf.DUMMYFUNCTION("""COMPUTED_VALUE"""),389.65) -> 389.65 | AD70: =IFERROR(__xludf.DUMMYFUNCTION("""COMPUTED_VALUE"""),404.05) -> 404.05 | AE70: =IFERROR(__xludf.DUMMYFUNCTION("""COMPUTED_VALUE"""),2.7983391E7) -> 27983391 | AF70: =LN(AD70/AD69) -> 0.018862592 | AL70: =IFERROR(__xludf.DUMMYFUNCTION("""COMPUTED_VALUE"""),45477.64583333333) -> 45477.646 | AM70: =IFERROR(__xludf.DUMMYFUNCTION("""COMPUTED_VALUE"""),5475.0) -> 5475 | AN70: =IFERROR(__xludf.DUMMYFUNCTION("""COMPUTED_VALUE"""),5568.7) -> 5568.7 | AO70: =IFERROR(__xludf.DUMMYFUNCTION("""COMPUTED_VALUE"""),5459.3) -> 5459.3 | AP70: =IFERROR(__xludf.DUMMYFUNCTION("""COMPUTED_VALUE"""),5515.1) -> 5515.1 | AQ70: =IFERROR(__xludf.DUMMYFUNCTION("""COMPUTED_VALUE"""),3743401.0) -> 3743401 | AR70: =LN(AP70/AP69) -> 0.010169209 | AX70: =IFERROR(__xludf.DUMMYFUNCTION("""COMPUTED_VALUE"""),45477.64583333333) -> 45477.646 | AY70: =IFERROR(__xludf.DUMMYFUNCTION("""COMPUTED_VALUE"""),430.0) -> 430 | AZ70: =IFERROR(__xludf.DUMMYFUNCTION("""COMPUTED_VALUE"""),431.5) -> 431.5 | BA70: =IFERROR(__xludf.DUMMYFUNCTION("""COMPUTED_VALUE"""),427.05) -> 427.05 | BB70: =IFERROR(__xludf.DUMMYFUNCTION("""COMPUTED_VALUE"""),429.05) -> 429.05 | BC70: =IFERROR(__xludf.DUMMYFUNCTION("""COMPUTED_VALUE"""),9127340.0) -> 9127340 | BD70: =LN(BB70/BB69) -> 0.0017495776
B71: 45478 | C71: 6325.52 | D71: 6424.78 | E71: 6318.78 | F71: 6420.12 | G71: - | H71: =LN(F71/F70) -> 0.015277824 | N71: =IFERROR(__xludf.DUMMYFUNCTION("""COMPUTED_VALUE"""),45478.64583333333) -> 45478.646 | O71: =IFERROR(__xludf.DUMMYFUNCTION("""COMPUTED_VALUE"""),1225.0) -> 1225 | P71: =IFERROR(__xludf.DUMMYFUNCTION("""COMPUTED_VALUE"""),1242.6) -> 1242.6 | Q71: =IFERROR(__xludf.DUMMYFUNCTION("""COMPUTED_VALUE"""),1220.85) -> 1220.85 | R71: =IFERROR(__xludf.DUMMYFUNCTION("""COMPUTED_VALUE"""),1233.4) -> 1233.4 | S71: =IFERROR(__xludf.DUMMYFUNCTION("""COMPUTED_VALUE"""),9535575.0) -> 9535575 | T71: =LN(R71/R70) -> 0.00032435939 | Z71: =IFERROR(__xludf.DUMMYFUNCTION("""COMPUTED_VALUE"""),45478.64583333333) -> 45478.646 | AA71: =IFERROR(__xludf.DUMMYFUNCTION("""COMPUTED_VALUE"""),401.0) -> 401 | AB71: =IFERROR(__xludf.DUMMYFUNCTION("""COMPUTED_VALUE"""),403.45) -> 403.45 | AC71: =IFERROR(__xludf.DUMMYFUNCTION("""COMPUTED_VALUE"""),392.3) -> 392.3 | AD71: =IFERROR(__xludf.DUMMYFUNCTION("""COMPUTED_VALUE"""),395.65) -> 395.65 | AE71: =IFERROR(__xludf.DUMMYFUNCTION("""COMPUTED_VALUE"""),1.3752975E7) -> 13752975 | AF71: =LN(AD71/AD70) -> -0.021008651 | AL71: =IFERROR(__xludf.DUMMYFUNCTION("""COMPUTED_VALUE"""),45478.64583333333) -> 45478.646 | AM71: =IFERROR(__xludf.DUMMYFUNCTION("""COMPUTED_VALUE"""),5535.0) -> 5535 | AN71: =IFERROR(__xludf.DUMMYFUNCTION("""COMPUTED_VALUE"""),5624.95) -> 5624.95 | AO71: =IFERROR(__xludf.DUMMYFUNCTION("""COMPUTED_VALUE"""),5482.5) -> 5482.5 | AP71: =IFERROR(__xludf.DUMMYFUNCTION("""COMPUTED_VALUE"""),5552.0) -> 5552 | AQ71: =IFERROR(__xludf.DUMMYFUNCTION("""COMPUTED_VALUE"""),3446662.0) -> 3446662 | AR71: =LN(AP71/AP70) -> 0.0066684383 | AX71: =IFERROR(__xludf.DUMMYFUNCTION("""COMPUTED_VALUE"""),45478.64583333333) -> 45478.646 | AY71: =IFERROR(__xludf.DUMMYFUNCTION("""COMPUTED_VALUE"""),429.0) -> 429 | AZ71: =IFERROR(__xludf.DUMMYFUNCTION("""COMPUTED_VALUE"""),434.0) -> 434 | BA71: =IFERROR(__xludf.DUMMYFUNCTION("""COMPUTED_VALUE"""),427.6) -> 427.6 | BB71: =IFERROR(__xludf.DUMMYFUNCTION("""COMPUTED_VALUE"""),433.65) -> 433.65 | BC71: =IFERROR(__xludf.DUMMYFUNCTION("""COMPUTED_VALUE"""),1.2929586E7) -> 12929586 | BD71: =LN(BB71/BB70) -> 0.010664295
B72: 45481 | C72: 6421.12 | D72: 6421.52 | E72: 6308.78 | F72: 6331.52 | G72: - | H72: =LN(F72/F71) -> -0.013896475 | N72: =IFERROR(__xludf.DUMMYFUNCTION("""COMPUTED_VALUE"""),45481.64583333333) -> 45481.646 | O72: =IFERROR(__xludf.DUMMYFUNCTION("""COMPUTED_VALUE"""),1228.9) -> 1228.9 | P72: =IFERROR(__xludf.DUMMYFUNCTION("""COMPUTED_VALUE"""),1239.5) -> 1239.5 | Q72: =IFERROR(__xludf.DUMMYFUNCTION("""COMPUTED_VALUE"""),1216.9) -> 1216.9 | R72: =IFERROR(__xludf.DUMMYFUNCTION("""COMPUTED_VALUE"""),1235.05) -> 1235.05 | S72: =IFERROR(__xludf.DUMMYFUNCTION("""COMPUTED_VALUE"""),6617190.0) -> 6617190 | T72: =LN(R72/R71) -> 0.0013368715 | Z72: =IFERROR(__xludf.DUMMYFUNCTION("""COMPUTED_VALUE"""),45481.64583333333) -> 45481.646 | AA72: =IFERROR(__xludf.DUMMYFUNCTION("""COMPUTED_VALUE"""),396.0) -> 396 | AB72: =IFERROR(__xludf.DUMMYFUNCTION("""COMPUTED_VALUE"""),398.85) -> 398.85 | AC72: =IFERROR(__xludf.DUMMYFUNCTION("""COMPUTED_VALUE"""),384.2) -> 384.2 | AD72: =IFERROR(__xludf.DUMMYFUNCTION("""COMPUTED_VALUE"""),385.75) -> 385.75 | AE72: =IFERROR(__xludf.DUMMYFUNCTION("""COMPUTED_VALUE"""),1.7394416E7) -> 17394416 | AF72: =LN(AD72/AD71) -> -0.025340491 | AL72: =IFERROR(__xludf.DUMMYFUNCTION("""COMPUTED_VALUE"""),45481.64583333333) -> 45481.646 | AM72: =IFERROR(__xludf.DUMMYFUNCTION("""COMPUTED_VALUE"""),5580.0) -> 5580 | AN72: =IFERROR(__xludf.DUMMYFUNCTION("""COMPUTED_VALUE"""),5662.45) -> 5662.45 | AO72: =IFERROR(__xludf.DUMMYFUNCTION("""COMPUTED_VALUE"""),5560.5) -> 5560.5 | AP72: =IFERROR(__xludf.DUMMYFUNCTION("""COMPUTED_VALUE"""),5621.95) -> 5621.95 | AQ72: =IFERROR(__xludf.DUMMYFUNCTION("""COMPUTED_VALUE"""),3536842.0) -> 3536842 | AR72: =LN(AP72/AP71) -> 0.012520356 | AX72: =IFERROR(__xludf.DUMMYFUNCTION("""COMPUTED_VALUE"""),45481.64583333333) -> 45481.646 | AY72: =IFERROR(__xludf.DUMMYFUNCTION("""COMPUTED_VALUE"""),435.15) -> 435.15 | AZ72: =IFERROR(__xludf.DUMMYFUNCTION("""COMPUTED_VALUE"""),444.55) -> 444.55 | BA72: =IFERROR(__xludf.DUMMYFUNCTION("""COMPUTED_VALUE"""),433.65) -> 433.65 | BB72: =IFERROR(__xludf.DUMMYFUNCTION("""COMPUTED_VALUE"""),443.6) -> 443.6 | BC72: =IFERROR(__xludf.DUMMYFUNCTION("""COMPUTED_VALUE"""),2.0521107E7) -> 20521107 | BD72: =LN(BB72/BB71) -> 0.022685498
B73: 45482 | C73: 6337.12 | D73: 6365.12 | E73: 6307.12 | F73: 6343.12 | G73: - | H73: =LN(F73/F72) -> 0.0018304273 | N73: =IFERROR(__xludf.DUMMYFUNCTION("""COMPUTED_VALUE"""),45482.64583333333) -> 45482.646 | O73: =IFERROR(__xludf.DUMMYFUNCTION("""COMPUTED_VALUE"""),1234.95) -> 1234.95 | P73: =IFERROR(__xludf.DUMMYFUNCTION("""COMPUTED_VALUE"""),1250.2) -> 1250.2 | Q73: =IFERROR(__xludf.DUMMYFUNCTION("""COMPUTED_VALUE"""),1229.3) -> 1229.3 | R73: =IFERROR(__xludf.DUMMYFUNCTION("""COMPUTED_VALUE"""),1248.25) -> 1248.25 | S73: =IFERROR(__xludf.DUMMYFUNCTION("""COMPUTED_VALUE"""),1.3366874E7) -> 13366874 | T73: =LN(R73/R72) -> 0.010631115 | Z73: =IFERROR(__xludf.DUMMYFUNCTION("""COMPUTED_VALUE"""),45482.64583333333) -> 45482.646 | AA73: =IFERROR(__xludf.DUMMYFUNCTION("""COMPUTED_VALUE"""),385.0) -> 385 | AB73: =IFERROR(__xludf.DUMMYFUNCTION("""COMPUTED_VALUE"""),387.45) -> 387.45 | AC73: =IFERROR(__xludf.DUMMYFUNCTION("""COMPUTED_VALUE"""),376.35) -> 376.35 | AD73: =IFERROR(__xludf.DUMMYFUNCTION("""COMPUTED_VALUE"""),385.0) -> 385 | AE73: =IFERROR(__xludf.DUMMYFUNCTION("""COMPUTED_VALUE"""),1.2570385E7) -> 12570385 | AF73: =LN(AD73/AD72) -> -0.001946157 | AL73: =IFERROR(__xludf.DUMMYFUNCTION("""COMPUTED_VALUE"""),45482.64583333333) -> 45482.646 | AM73: =IFERROR(__xludf.DUMMYFUNCTION("""COMPUTED_VALUE"""),5638.9) -> 5638.9 | AN73: =IFERROR(__xludf.DUMMYFUNCTION("""COMPUTED_VALUE"""),5674.75) -> 5674.75 | AO73: =IFERROR(__xludf.DUMMYFUNCTION("""COMPUTED_VALUE"""),5517.05) -> 5517.05 | AP73: =IFERROR(__xludf.DUMMYFUNCTION("""COMPUTED_VALUE"""),5539.6) -> 5539.6 | AQ73: =IFERROR(__xludf.DUMMYFUNCTION("""COMPUTED_VALUE"""),2392991.0) -> 2392991 | AR73: =LN(AP73/AP72) -> -0.014756283 | AX73: =IFERROR(__xludf.DUMMYFUNCTION("""COMPUTED_VALUE"""),45482.64583333333) -> 45482.646 | AY73: =IFERROR(__xludf.DUMMYFUNCTION("""COMPUTED_VALUE"""),447.6) -> 447.6 | AZ73: =IFERROR(__xludf.DUMMYFUNCTION("""COMPUTED_VALUE"""),455.0) -> 455 | BA73: =IFERROR(__xludf.DUMMYFUNCTION("""COMPUTED_VALUE"""),444.0) -> 444 | BB73: =IFERROR(__xludf.DUMMYFUNCTION("""COMPUTED_VALUE"""),452.6) -> 452.6 | BC73: =IFERROR(__xludf.DUMMYFUNCTION("""COMPUTED_VALUE"""),2.647026E7) -> 26470260 | BD73: =LN(BB73/BB72) -> 0.020085478
B74: 45483 | C74: 6346.12 | D74: 6408.12 | E74: 6341.12 | F74: 6365.52 | G74: - | H74: =LN(F74/F73) -> 0.0035251645 | N74: =IFERROR(__xludf.DUMMYFUNCTION("""COMPUTED_VALUE"""),45483.64583333333) -> 45483.646 | O74: =IFERROR(__xludf.DUMMYFUNCTION("""COMPUTED_VALUE"""),1252.75) -> 1252.75 | P74: =IFERROR(__xludf.DUMMYFUNCTION("""COMPUTED_VALUE"""),1252.75) -> 1252.75 | Q74: =IFERROR(__xludf.DUMMYFUNCTION("""COMPUTED_VALUE"""),1236.35) -> 1236.35 | R74: =IFERROR(__xludf.DUMMYFUNCTION("""COMPUTED_VALUE"""),1243.2) -> 1243.2 | S74: =IFERROR(__xludf.DUMMYFUNCTION("""COMPUTED_VALUE"""),1.8226503E7) -> 18226503 | T74: =LN(R74/R73) -> -0.0040538698 | Z74: =IFERROR(__xludf.DUMMYFUNCTION("""COMPUTED_VALUE"""),45483.64583333333) -> 45483.646 | AA74: =IFERROR(__xludf.DUMMYFUNCTION("""COMPUTED_VALUE"""),386.7) -> 386.7 | AB74: =IFERROR(__xludf.DUMMYFUNCTION("""COMPUTED_VALUE"""),388.45) -> 388.45 | AC74: =IFERROR(__xludf.DUMMYFUNCTION("""COMPUTED_VALUE"""),373.55) -> 373.55 | AD74: =IFERROR(__xludf.DUMMYFUNCTION("""COMPUTED_VALUE"""),382.9) -> 382.9 | AE74: =IFERROR(__xludf.DUMMYFUNCTION("""COMPUTED_VALUE"""),1.6109267E7) -> 16109267 | AF74: =LN(AD74/AD73) -> -0.0054694758 | AL74: =IFERROR(__xludf.DUMMYFUNCTION("""COMPUTED_VALUE"""),45483.64583333333) -> 45483.646 | AM74: =IFERROR(__xludf.DUMMYFUNCTION("""COMPUTED_VALUE"""),5568.8) -> 5568.8 | AN74: =IFERROR(__xludf.DUMMYFUNCTION("""COMPUTED_VALUE"""),5580.0) -> 5580 | AO74: =IFERROR(__xludf.DUMMYFUNCTION("""COMPUTED_VALUE"""),5319.0) -> 5319 | AP74: =IFERROR(__xludf.DUMMYFUNCTION("""COMPUTED_VALUE"""),5486.15) -> 5486.15 | AQ74: =IFERROR(__xludf.DUMMYFUNCTION("""COMPUTED_VALUE"""),2121407.0) -> 2121407 | AR74: =LN(AP74/AP73) -> -0.0096955615 | AX74: =IFERROR(__xludf.DUMMYFUNCTION("""COMPUTED_VALUE"""),45483.64583333333) -> 45483.646 | AY74: =IFERROR(__xludf.DUMMYFUNCTION("""COMPUTED_VALUE"""),453.7) -> 453.7 | AZ74: =IFERROR(__xludf.DUMMYFUNCTION("""COMPUTED_VALUE"""),455.35) -> 455.35 | BA74: =IFERROR(__xludf.DUMMYFUNCTION("""COMPUTED_VALUE"""),446.5) -> 446.5 | BB74: =IFERROR(__xludf.DUMMYFUNCTION("""COMPUTED_VALUE"""),451.45) -> 451.45 | BC74: =IFERROR(__xludf.DUMMYFUNCTION("""COMPUTED_VALUE"""),1.161821E7) -> 11618210 | BD74: =LN(BB74/BB73) -> -0.0025441084
B75: 45484 | C75: 6366.78 | D75: 6508.12 | E75: 6364.78 | F75: 6483.52 | G75: - | H75: =LN(F75/F74) -> 0.018367647 | N75: =IFERROR(__xludf.DUMMYFUNCTION("""COMPUTED_VALUE"""),45484.64583333333) -> 45484.646 | O75: =IFERROR(__xludf.DUMMYFUNCTION("""COMPUTED_VALUE"""),1246.35) -> 1246.35 | P75: =IFERROR(__xludf.DUMMYFUNCTION("""COMPUTED_VALUE"""),1257.8) -> 1257.8 | Q75: =IFERROR(__xludf.DUMMYFUNCTION("""COMPUTED_VALUE"""),1225.05) -> 1225.05 | R75: =IFERROR(__xludf.DUMMYFUNCTION("""COMPUTED_VALUE"""),1238.45) -> 1238.45 | S75: =IFERROR(__xludf.DUMMYFUNCTION("""COMPUTED_VALUE"""),1.1307116E7) -> 11307116 | T75: =LN(R75/R74) -> -0.0038281029 | Z75: =IFERROR(__xludf.DUMMYFUNCTION("""COMPUTED_VALUE"""),45484.64583333333) -> 45484.646 | AA75: =IFERROR(__xludf.DUMMYFUNCTION("""COMPUTED_VALUE"""),383.0) -> 383 | AB75: =IFERROR(__xludf.DUMMYFUNCTION("""COMPUTED_VALUE"""),395.6) -> 395.6 | AC75: =IFERROR(__xludf.DUMMYFUNCTION("""COMPUTED_VALUE"""),383.0) -> 383 | AD75: =IFERROR(__xludf.DUMMYFUNCTION("""COMPUTED_VALUE"""),394.25) -> 394.25 | AE75: =IFERROR(__xludf.DUMMYFUNCTION("""COMPUTED_VALUE"""),1.3286371E7) -> 13286371 | AF75: =LN(AD75/AD74) -> 0.029211367 | AL75: =IFERROR(__xludf.DUMMYFUNCTION("""COMPUTED_VALUE"""),45484.64583333333) -> 45484.646 | AM75: =IFERROR(__xludf.DUMMYFUNCTION("""COMPUTED_VALUE"""),5500.0) -> 5500 | AN75: =IFERROR(__xludf.DUMMYFUNCTION("""COMPUTED_VALUE"""),5575.0) -> 5575 | AO75: =IFERROR(__xludf.DUMMYFUNCTION("""COMPUTED_VALUE"""),5465.0) -> 5465 | AP75: =IFERROR(__xludf.DUMMYFUNCTION("""COMPUTED_VALUE"""),5547.6) -> 5547.6 | AQ75: =IFERROR(__xludf.DUMMYFUNCTION("""COMPUTED_VALUE"""),1843378.0) -> 1843378 | AR75: =LN(AP75/AP74) -> 0.011138667 | AX75: =IFERROR(__xludf.DUMMYFUNCTION("""COMPUTED_VALUE"""),45484.64583333333) -> 45484.646 | AY75: =IFERROR(__xludf.DUMMYFUNCTION("""COMPUTED_VALUE"""),450.0) -> 450 | AZ75: =IFERROR(__xludf.DUMMYFUNCTION("""COMPUTED_VALUE"""),459.5) -> 459.5 | BA75: =IFERROR(__xludf.DUMMYFUNCTION("""COMPUTED_VALUE"""),448.7) -> 448.7 | BB75: =IFERROR(__xludf.DUMMYFUNCTION("""COMPUTED_VALUE"""),458.65) -> 458.65 | BC75: =IFERROR(__xludf.DUMMYFUNCTION("""COMPUTED_VALUE"""),1.8831345E7) -> 18831345 | BD75: =LN(BB75/BB74) -> 0.015822767
B76: 45485 | C76: 6485.12 | D76: 6496.12 | E76: 6421.52 | F76: 6473.12 | G76: - | H76: =LN(F76/F75) -> -0.0016053548 | N76: =IFERROR(__xludf.DUMMYFUNCTION("""COMPUTED_VALUE"""),45485.64583333333) -> 45485.646 | O76: =IFERROR(__xludf.DUMMYFUNCTION("""COMPUTED_VALUE"""),1235.9) -> 1235.9 | P76: =IFERROR(__xludf.DUMMYFUNCTION("""COMPUTED_VALUE"""),1252.9) -> 1252.9 | Q76: =IFERROR(__xludf.DUMMYFUNCTION("""COMPUTED_VALUE"""),1230.1) -> 1230.1 | R76: =IFERROR(__xludf.DUMMYFUNCTION("""COMPUTED_VALUE"""),1232.9) -> 1232.9 | S76: =IFERROR(__xludf.DUMMYFUNCTION("""COMPUTED_VALUE"""),1.220829E7) -> 12208290 | T76: =LN(R76/R75) -> -0.0044914798 | Z76: =IFERROR(__xludf.DUMMYFUNCTION("""COMPUTED_VALUE"""),45485.64583333333) -> 45485.646 | AA76: =IFERROR(__xludf.DUMMYFUNCTION("""COMPUTED_VALUE"""),396.5) -> 396.5 | AB76: =IFERROR(__xludf.DUMMYFUNCTION("""COMPUTED_VALUE"""),398.55) -> 398.55 | AC76: =IFERROR(__xludf.DUMMYFUNCTION("""COMPUTED_VALUE"""),389.1) -> 389.1 | AD76: =IFERROR(__xludf.DUMMYFUNCTION("""COMPUTED_VALUE"""),392.0) -> 392 | AE76: =IFERROR(__xludf.DUMMYFUNCTION("""COMPUTED_VALUE"""),1.0718103E7) -> 10718103 | AF76: =LN(AD76/AD75) -> -0.0057233861 | AL76: =IFERROR(__xludf.DUMMYFUNCTION("""COMPUTED_VALUE"""),45485.64583333333) -> 45485.646 | AM76: =IFERROR(__xludf.DUMMYFUNCTION("""COMPUTED_VALUE"""),5570.0) -> 5570 | AN76: =IFERROR(__xludf.DUMMYFUNCTION("""COMPUTED_VALUE"""),5578.45) -> 5578.45 | AO76: =IFERROR(__xludf.DUMMYFUNCTION("""COMPUTED_VALUE"""),5446.0) -> 5446 | AP76: =IFERROR(__xludf.DUMMYFUNCTION("""COMPUTED_VALUE"""),5489.2) -> 5489.2 | AQ76: =IFERROR(__xludf.DUMMYFUNCTION("""COMPUTED_VALUE"""),1387762.0) -> 1387762 | AR76: =LN(AP76/AP75) -> -0.010582876 | AX76: =IFERROR(__xludf.DUMMYFUNCTION("""COMPUTED_VALUE"""),45485.64583333333) -> 45485.646 | AY76: =IFERROR(__xludf.DUMMYFUNCTION("""COMPUTED_VALUE"""),458.65) -> 458.65 | AZ76: =IFERROR(__xludf.DUMMYFUNCTION("""COMPUTED_VALUE"""),463.25) -> 463.25 | BA76: =IFERROR(__xludf.DUMMYFUNCTION("""COMPUTED_VALUE"""),455.85) -> 455.85 | BB76: =IFERROR(__xludf.DUMMYFUNCTION("""COMPUTED_VALUE"""),459.05) -> 459.05 | BC76: =IFERROR(__xludf.DUMMYFUNCTION("""COMPUTED_VALUE"""),1.89628E7) -> 18962800 | BD76: =LN(BB76/BB75) -> 0.00087174463
